Workbook

Sheet Uncovered Branches
A1: NIB International Bank S.C
A2: Internal Control Division
A3: Lists of Branches that failed to cover in the monthly internal Control Reports
A4: As of july,2026
A5: Ser. No | B5: Name of Branches | C5: Name of Districts | D5: Reasons for failing to uncover in the monthly internal Control Reports
D7: Operation area
A8: 1 | B8: 22 Megenagna | C8: East | D8: resign
A9: 2 | B9: Sheger menefesha | C9: North | D9: maturnity leave
A10: 3 | B10: Habte giorgis | C10: North | D10: maturnity leave
A11: 4 | B11: Salo Gora | C11: South | D11: Sick Leave
A12: 5 | B12: Asko | C12: West | D12: Sick Leave
A13: 6 | B13: Moyale | C13: Hawassa | D13: Controllers not assigned
A14: 7 | B14: Adare | C14: Hawassa | D14: maturnity leave
A15: 8 | B15: Alamura | C15: Hawassa | D15: maturnity leave
A16: 9 | B16: Tabor | C16: Hawassa | D16: maturnity leave
A17: 10 | B17: Nib Halal | C17: Hawassa | D17: Controllers has not given access right
A18: 11 | B18: Metema | C18: B-Dar | D18: Sick Leave
A19: 12 | B19: Agarfa | C19: Adama | D19: Controllers not assigned
... A57: 50 | B57: Bako | C57: Jimma | D57: Controller not Assigned

Sheet Case Summarised
A1: Monthly Controllers report as at July 2026
A2: SN | B2: Total No. of Branches | C2: District | D2: ATM Cases | H2: IT Case | J2: No. of zero balance account | L2: No. of inactive balance account | N2: Cheque Book case | P2: Others Case | R2: Status of the irregularities
D3: Mismatch | F3: Long outstanding | R3: Total Reported Case | S3: Rectified | T3: Outstanding Case | U3: rectified percetage
B4: A | C4: B | D4: ReportedCase | E4: Rectified | F4: Reported Case | G4: Rectified | H4: Reported Case | I4: Rectified | J4: Reported Case | K4: Rectified | L4: Reported Case | M4: Rectified | N4: Reported Case | O4: Rectified | P4: Reported Case | Q4: Rectified | R4: F | S4: G
A5: 1 | B5: 49 | C5: East | D5: =East!E763 -> 0 | E5: =East!O766 -> 0 | F5: =East!F760 -> 25057 | G5: =East!O767 -> 6 | H5: =East!G760 -> 135 | I5: =East!O768 -> 4 | J5: =East!H760 -> 3973 | K5: =East!O768 -> 4 | L5: =East!I760 -> 87889 | M5: =East!O770 -> 90 | N5: =East!J760 -> 49 | O5: =East!O771 -> 0 | P5: =East!K760 -> 625 | Q5: =East!O772 -> 241 | R5: =D5+F5+H5+J5+L5+N5+P5 -> 117728 | S5: =E5+G5+K5+I5+M5+O5+Q5 -> 345 | T5: =R5-S5 -> 117383
A6: 2 | B6: 42 | C6: North | D6: =North!G377 -> 5283 | E6: =North!K382 -> 90 | F6: =North!H377 -> 16438 | G6: =North!K383 -> 38 | H6: =North!I377 -> 129 | I6: =North!K384 -> 1 | J6: =North!J377 -> 6798 | K6: =North!K385 -> 143 | L6: =North!K377 -> 27137 | M6: =North!K386 -> 58 | N6: =North!L377 -> 990 | O6: =North!K387 -> 0 | P6: =North!M377 -> 228 | Q6: =North!K388 -> 65 | R6: =D6+F6+H6+J6+L6+N6+P6 -> 57003 | S6: =E6+G6+K6+I6+M6+O6+Q6 -> 395 | T6: =R6-S6 -> 56608 | U6: =S6/R6 -> 0.0069294599
A7: 3 | B7: 57 | C7: South | D7: =South!E1066 -> 8018 | E7: =South!O1072 -> 0 | F7: =South!F1066 -> 27504 | G7: =South!O1073 -> 0 | H7: =South!G1066 -> 312 | I7: =South!O1074 -> 0 | J7: =South!H1066 -> 9969 | K7: =South!O1075 -> 0 | L7: =South!I1066 -> 158159 | M7: =South!O1076 -> 0 | N7: =South!J1066 -> 971 | O7: =South!O1077 -> 0 | P7: =South!K1066 -> 818 | Q7: =South!O1078 -> 8 | R7: =D7+F7+H7+J7+L7+N7+P7 -> 205751 | S7: =E7+G7+K7+I7+M7+O7+Q7 -> 8 | T7: =R7-S7 -> 205743 | U7: =S7/R7 -> 3.888195e-05
A8: 4 | B8: 65 | C8: West | D8: =West!E514 -> 5776 | E8: =West!F524 -> 0 | F8: =West!F514 -> 19909 | G8: =West!F525 -> 0 | H8: =West!G514 -> 193 | I8: =West!F526 -> 0 | J8: =West!H514 -> 864 | K8: =West!F527 -> 0 | L8: =West!I514 -> 91240 | M8: =West!F528 -> 0 | N8: =West!J514 -> 2773 | O8: =West!F528 -> 0 | P8: =West!K514 -> 160 | Q8: =West!F530 -> 20 | R8: =D8+F8+H8+J8+L8+N8+P8 -> 120915 | S8: =E8+G8+K8+I8+M8+O8+Q8 -> 20 | T8: =R8-S8 -> 120895 | U8: =S8/R8 -> 0.00016540545
A9: 5 | B9: 33 | C9: Adama | D9: =Adama!E282 -> 1232 | E9: =Adama!F292 -> 20 | F9: =Adama!F282 -> 16571 | G9: =Adama!F293 -> 5 | H9: =Adama!G282 -> 73 | I9: =Adama!F294 -> 22 | J9: =Adama!H282 -> 274 | K9: =Adama!F295 -> 10 | L9: =Adama!I282 -> 94745 | M9: =Adama!F296 -> 0 | N9: =Adama!J282 -> 0 | O9: =Adama!F297 -> 0 | P9: =Adama!K282 -> 207 | Q9: =Adama!F298 -> 20 | R9: =D9+F9+H9+J9+L9+N9+P9 -> 113102 | S9: =E9+G9+K9+I9+M9+O9+Q9 -> 77 | T9: =R9-S9 -> 113025 | U9: =S9/R9 -> 0.0006808014
A10: 6 | B10: 25 | C10: Bahi Dar | D10: ='B-Dar'!F235 -> 1565 | E10: ='B-Dar'!G240 -> 12 | F10: ='B-Dar'!G235 -> 8851 | G10: ='B-Dar'!G241 -> 16 | H10: ='B-Dar'!H235 -> 44 | I10: ='B-Dar'!G242 -> 2 | J10: ='B-Dar'!I235 -> 12 | K10: ='B-Dar'!G243 -> 11 | L10: ='B-Dar'!J235 -> 25540 | M10: ='B-Dar'!G244 -> 1126 | N10: ='B-Dar'!K235 -> 345 | O10: ='B-Dar'!G245 -> 0 | P10: ='B-Dar'!L235 -> 4342 | Q10: ='B-Dar'!G246 -> 252 | R10: =D10+F10+H10+J10+L10+N10+P10 -> 40699 | S10: =E10+G10+K10+I10+M10+O10+Q10 -> 1419 | T10: =R10-S10 -> 39280 | U10: =S10/R10 -> 0.034865722
A11: 7 | B11: 11 | C11: Dessie | D11: =Desie!F161 -> 1105 | E11: =Desie!G167 -> 0 | F11: =Desie!G161 -> 2660 | G11: =Desie!G168 -> 20 | H11: =Desie!H161 -> 28 | I11: =Desie!G169 -> 2 | J11: =Desie!I161 -> 3434 | K11: =Desie!G170 -> 52 | L11: =Desie!J161 -> 13815 | M11: =Desie!G171 -> 240 | N11: =Desie!K161 -> 1 | O11: =Desie!G172 -> 0 | P11: =Desie!L161 -> 268 | Q11: =Desie!G173 -> 49 | R11: =D11+F11+H11+J11+L11+N11+P11 -> 21311 | S11: =E11+G11+K11+I11+M11+O11+Q11 -> 363 | T11: =R11-S11 -> 20948 | U11: =S11/R11 -> 0.017033457
A12: 8 | B12: 17 | C12: DIREDAWA | D12: ='Dire Dawa'!E92 -> 1366 | E12: ='Dire Dawa'!O98 -> 0 | F12: ='Dire Dawa'!F92 -> 8041 | G12: ='Dire Dawa'!O99 -> 0 | H12: ='Dire Dawa'!G92 -> 4 | I12: ='Dire Dawa'!O100 -> 0 | J12: ='Dire Dawa'!H92 -> 1171 | K12: ='Dire Dawa'!O101 -> 0 | L12: ='Dire Dawa'!I92 -> 24004 | M12: ='Dire Dawa'!O102 -> 0 | N12: ='Dire Dawa'!J92 -> 0 | O12: ='Dire Dawa'!O103 -> 0 | P12: ='Dire Dawa'!K92 -> 240 | Q12: ='Dire Dawa'!O104 -> 0 | R12: =D12+F12+H12+J12+L12+N12+P12 -> 34826 | S12: =E12+G12+K12+I12+M12+O12+Q12 -> 0 | T12: =R12-S12 -> 34826 | U12: =S12/R12 -> 0
A13: 9 | B13: 39 | C13: Hawassa | D13: =Hawassa!G297 -> 3320 | E13: =Hawassa!J300 -> 0 | F13: =Hawassa!H297 -> 29868 | G13: =Hawassa!J301 -> 0 | H13: =Hawassa!I297 -> 94 | I13: =Hawassa!J302 -> 0 | J13: =Hawassa!J297 -> 130 | K13: =Hawassa!J303 -> 0 | L13: =Hawassa!K297 -> 18486 | M13: =Hawassa!J304 -> 0 | N13: =Hawassa!L297 -> 1 | O13: =Hawassa!J305 -> 0 | P13: =Hawassa!M297 -> 582 | Q13: =Hawassa!J306 -> 0 | R13: =D13+F13+H13+J13+L13+N13+P13 -> 52481 | S13: =E13+G13+K13+I13+M13+O13+Q13 -> 0 | T13: =R13-S13 -> 52481 | U13: =S13/R13 -> 0
A14: 10 | B14: 36 | C14: Hossaena | D14: =Hossaena!F209 -> 5961 | E14: =Hossaena!G214 -> 1 | F14: =Hossaena!G209 -> 47643 | G14: =Hossaena!G215 -> 8 | H14: =Hossaena!H209 -> 40 | I14: =Hossaena!G216 -> 0 | J14: =Hossaena!I209 -> 164 | K14: =Hossaena!G217 -> 98 | L14: =Hossaena!J209 -> 121170 | M14: =Hossaena!G218 -> 968 | N14: =Hossaena!K209 -> 1 | O14: =Hossaena!G219 -> 1 | P14: =Hossaena!L209 -> 234 | Q14: =Hossaena!G220 -> 206 | R14: =D14+F14+H14+J14+L14+N14+P14 -> 175213 | S14: =E14+G14+K14+I14+M14+O14+Q14 -> 1282 | T14: =R14-S14 -> 173931 | U14: =S14/R14 -> 0.0073168087
A15: 11 | B15: 26 | C15: Wolkite | D15: =Wolkite!E185 -> 225 | E15: =Wolkite!F194 -> 3 | F15: =Wolkite!F185 -> 16435 | G15: =Wolkite!F195 -> 10 | H15: =Wolkite!G185 -> 42 | I15: =Wolkite!F196 -> 2 | J15: =Wolkite!H185 -> 294 | K15: =Wolkite!F197 -> 125 | L15: =Wolkite!I185 -> 53926 | M15: =Wolkite!F198 -> 107 | N15: =Wolkite!J185 -> 0 | O15: =Wolkite!F199 -> 0 | P15: =Wolkite!K185 -> 101 | Q15: =Wolkite!F200 -> 11 | R15: =D15+F15+H15+J15+L15+N15+P15 -> 71023 | S15: =E15+G15+K15+I15+M15+O15+Q15 -> 258 | T15: =R15-S15 -> 70765 | U15: =S15/R15 -> 0.0036326261
A16: 12 | B16: 20 | C16: Jimma | D16: =Jimma!G126 -> 129 | E16: =Jimma!L135 -> 0 | F16: =Jimma!H126 -> 4114 | G16: =Jimma!L136 -> 0 | H16: =Jimma!I126 -> 32 | I16: =Jimma!L137 -> 0 | J16: =Jimma!J126 -> 3238 | K16: =Jimma!L138 -> 0 | L16: =Jimma!K139 -> 62264 | M16: =Jimma!L140 -> 0 | N16: =Jimma!L126 -> 16 | O16: =Jimma!L140 -> 0 | P16: =Jimma!M126 -> 300 | Q16: =Jimma!L141 -> 0 | R16: =D16+F16+H16+J16+L16+N16+P16 -> 70093 | S16: =E16+G16+K16+I16+M16+O16+Q16 -> 0 | T16: =R16-S16 -> 70093
A17: 13 | B17: 7 | C17: Mekelle | D17: =Mekelle!E26 -> 0 | E17: =Mekelle!F36 -> 0 | F17: =Mekelle!F26 -> 1536 | G17: =Mekelle!F37 -> 2 | H17: =Mekelle!G26 -> 0 | I17: =Mekelle!F38 -> 0 | J17: =Mekelle!H26 -> 0 | K17: =Mekelle!F39 -> 0 | L17: =Mekelle!I26 -> 6357 | M17: =Mekelle!F40 -> 87 | N17: =Mekelle!J26 -> 13 | O17: =Mekelle!F41 -> 0 | P17: =Mekelle!K26 -> 6 | Q17: =Mekelle!F42 -> 3 | R17: =D17+F17+H17+J17+L17+N17+P17 -> 7912 | S17: =E17+G17+K17+I17+M17+O17+Q17 -> 92 | T17: =R17-S17 -> 7820 | U17: =S17/R17 -> 0.011627907
B18: =SUM(B5:B17) -> 427 | C18: TOTAL | D18: =SUM(D5:D17) -> 33980 | E18: =SUM(E5:E17) -> 126 | F18: =SUM(F5:F17) -> 224627 | G18: =SUM(G5:G17) -> 105 | H18: =SUM(H5:H17) -> 1126 | I18: =SUM(I5:I17) -> 33 | J18: =SUM(J5:J17) -> 30321 | K18: =SUM(K5:K17) -> 443 | ... Q18: =SUM(Q5:Q17) -> 875 | R18: =D18+F18+H18+J18+L18+N18+P18 -> 1088057 | S18: =SUM(S5:S17) -> 4259 | T18: =SUM(T5:T17) -> 1083798 | U18: =SUM(U5:U17) -> 0.082291069
E19: =D18-E18 -> 33854 | G19: =F18-G18 -> 224522 | I19: =H18-I18 -> 1093 | K19: =J18-K18 -> 29878 | M19: =L18-M18 -> 782056 | O19: =N18-O18 -> 5159 | Q19: =Q18/P18 -> 0.10787819
C21: Current | E21: Previous
C22: No. of inactive balance account | E22: No. of inactive balance account
G23: Weekly rectification
C24: Unrectified | D24: Rectified | E24: Unrectified | F24: Rectified | G24: Unrectified | H24: Rectified
B25: East | G25: =C25-E25 -> 0 | H25: =D25-F25 -> 0
B26: North | G26: =C26-E26 -> 0 | H26: =D26-F26 -> 0
B27: South | G27: =C27-E27 -> 0 | H27: =D27-F27 -> 0
B28: West | G28: =C28-E28 -> 0 | H28: =D28-F28 -> 0
B29: Adama | G29: =C29-E29 -> 0 | H29: =D29-F29 -> 0
B30: Bahi Dar | G30: =C30-E30 -> 0 | H30: =D30-F30 -> 0
B31: Dessie | G31: =C31-E31 -> 0 | H31: =D31-F31 -> 0
B32: DIREDAWA | G32: =C32-E32 -> 0 | H32: =D32-F32 -> 0
B33: Hawassa | G33: =C33-E33 -> 0 | H33: =D33-F33 -> 0
B34: Hossaena | G34: =C34-E34 -> 0 | H34: =D34-F34 -> 0
B35: Wolkite | G35: =C35-E35 -> 0 | H35: =D35-F35 -> 0
B36: Jimma | G36: =C36-E36 -> 0 | H36: =D36-F36 -> 0
B37: Mekelle | G37: =C37-E37 -> 0 | H37: =D37-F37 -> 0
C38: =SUM(C25:C37) -> 0 | D38: =SUM(D25:D37) -> 0 | G38: =SUM(G25:G37) -> 0 | H38: =SUM(H25:H37) -> 0
D39: =C38-D38 -> 0 | F39: =E38-F38 -> 0

Sheet Summarised
A1: Monthly Controllers report as at july 2026
A2: SN | B2: Total No. of Branches | C2: District | D2: ATM Cases | F2: IT Case | G2: No. of zero balance account | H2: No. of inactive balance account | I2: Cheque Book case | J2: Others Case No | K2: Amount involved in Birr | L2: Status of the irregularities | O2: No. of Branches not dispatched | P2: No. of Branches Dispatched reports | Q2: Total No. of cases
D3: Mismatch | E3: Long outstanding | L3: Unrectified | M3: Rectified | N3: rectified percetage
B4: A | C4: B | J4: D | K4: E | L4: F | M4: G | O4: I | P4: I
A5: 1 | B5: 49 | C5: East | D5: ='Case Summarised'!D5 -> 0 | E5: ='Case Summarised'!F5 -> 25057 | F5: ='Case Summarised'!H5 -> 135 | G5: ='Case Summarised'!J5 -> 3973 | H5: ='Case Summarised'!L5 -> 87889 | I5: ='Case Summarised'!N5 -> 49 | J5: ='Case Summarised'!P5 -> 625 | K5: =East!N760 -> 1.484968e+09 | L5: =D5+E5+F5+G5+H5+I5+J5 -> 117728 | M5: ='Case Summarised'!Q5 -> 241 | N5: =M5/J5 -> 0.3856 | O5: 1 | P5: =B5-O5 -> 48 | Q5: =D5+E5+F5+G5+H5+I5+J5 -> 117728
A6: 2 | B6: 42 | C6: North | D6: ='Case Summarised'!D6 -> 5283 | E6: ='Case Summarised'!F6 -> 16438 | F6: ='Case Summarised'!H6 -> 129 | G6: ='Case Summarised'!J6 -> 6798 | H6: ='Case Summarised'!L6 -> 27137 | I6: ='Case Summarised'!N6 -> 990 | J6: ='Case Summarised'!P6 -> 228 | K6: =North!N377 -> 3.6939536e+09 | L6: =D6+E6+F6+G6+H6+I6+J6 -> 57003 | M6: ='Case Summarised'!Q6 -> 65 | N6: =M6/J6 -> 0.28508772 | O6: 2 | P6: =B6-O6 -> 40 | Q6: =D6+E6+F6+G6+H6+I6+J6 -> 57003
A7: 3 | B7: 57 | C7: South | D7: ='Case Summarised'!D7 -> 8018 | E7: ='Case Summarised'!F7 -> 27504 | F7: ='Case Summarised'!H7 -> 312 | G7: ='Case Summarised'!J7 -> 9969 | H7: ='Case Summarised'!L7 -> 158159 | I7: ='Case Summarised'!N7 -> 971 | J7: ='Case Summarised'!P7 -> 818 | K7: =South!N1066 -> -3.2776797e+09 | L7: =D7+E7+F7+G7+H7+I7+J7 -> 205751 | M7: ='Case Summarised'!Q7 -> 8 | N7: =M7/J7 -> 0.0097799511 | O7: 1 | P7: =B7-O7 -> 56 | Q7: =D7+E7+F7+G7+H7+I7+J7 -> 205751
A8: 4 | B8: 57 | C8: West | D8: ='Case Summarised'!D8 -> 5776 | E8: ='Case Summarised'!F8 -> 19909 | F8: ='Case Summarised'!H8 -> 193 | G8: ='Case Summarised'!J8 -> 864 | H8: ='Case Summarised'!L8 -> 91240 | I8: ='Case Summarised'!N8 -> 2773 | J8: ='Case Summarised'!P8 -> 160 | K8: =West!N514 -> 3.9882254e+09 | L8: =D8+E8+F8+G8+H8+I8+J8 -> 120915 | M8: ='Case Summarised'!Q8 -> 20 | N8: =M8/J8 -> 0.125 | O8: 1 | P8: =B8-O8 -> 56 | Q8: =D8+E8+F8+G8+H8+I8+J8 -> 120915
A9: 5 | B9: 33 | C9: Adama | D9: ='Case Summarised'!D9 -> 1232 | E9: ='Case Summarised'!F9 -> 16571 | F9: ='Case Summarised'!H9 -> 73 | G9: ='Case Summarised'!J9 -> 274 | H9: ='Case Summarised'!L9 -> 94745 | I9: ='Case Summarised'!N9 -> 0 | J9: ='Case Summarised'!P9 -> 207 | K9: =Adama!N282 -> 1.0649864e+09 | L9: =D9+E9+F9+G9+H9+I9+J9 -> 113102 | M9: ='Case Summarised'!Q9 -> 20 | N9: =M9/J9 -> 0.096618357 | O9: 6 | P9: =B9-O9 -> 27 | Q9: =D9+E9+F9+G9+H9+I9+J9 -> 113102
A10: 6 | B10: 25 | C10: Bahi Dar | D10: ='Case Summarised'!D10 -> 1565 | E10: ='Case Summarised'!F10 -> 8851 | F10: ='Case Summarised'!H10 -> 44 | G10: ='Case Summarised'!J10 -> 12 | H10: ='Case Summarised'!L10 -> 25540 | I10: ='Case Summarised'!N10 -> 345 | J10: ='Case Summarised'!P10 -> 4342 | K10: ='B-Dar'!M235 -> 5.0140589e+08 | L10: =D10+E10+F10+G10+H10+I10+J10 -> 40699 | M10: ='Case Summarised'!Q10 -> 252 | N10: =M10/J10 -> 0.058037771 | O10: 1 | P10: =B10-O10 -> 24 | Q10: =D10+E10+F10+G10+H10+I10+J10 -> 40699
A11: 7 | B11: 11 | C11: Dessie | D11: ='Case Summarised'!D11 -> 1105 | E11: ='Case Summarised'!F11 -> 2660 | F11: ='Case Summarised'!H11 -> 28 | G11: ='Case Summarised'!J11 -> 3434 | H11: ='Case Summarised'!L11 -> 13815 | I11: ='Case Summarised'!N11 -> 1 | J11: ='Case Summarised'!P11 -> 268 | K11: =Desie!M161 -> 1.1208084e+08 | L11: =D11+E11+F11+G11+H11+I11+J11 -> 21311 | M11: ='Case Summarised'!Q11 -> 49 | N11: =M11/J11 -> 0.18283582 | P11: =B11-O11 -> 11 | Q11: =D11+E11+F11+G11+H11+I11+J11 -> 21311
A12: 8 | B12: 18 | C12: DIREDAWA | D12: ='Case Summarised'!D12 -> 1366 | E12: ='Case Summarised'!F12 -> 8041 | F12: ='Case Summarised'!H12 -> 4 | G12: ='Case Summarised'!J12 -> 1171 | H12: ='Case Summarised'!L12 -> 24004 | I12: ='Case Summarised'!N12 -> 0 | J12: ='Case Summarised'!P12 -> 240 | K12: ='Dire Dawa'!N92 -> -1.3426429e+08 | L12: =D12+E12+F12+G12+H12+I12+J12 -> 34826 | M12: ='Case Summarised'!Q12 -> 0 | N12: =M12/J12 -> 0 | O12: 11 | P12: =B12-O12 -> 7 | Q12: =D12+E12+F12+G12+H12+I12+J12 -> 34826
A13: 9 | B13: 39 | C13: Hawassa | D13: ='Case Summarised'!D13 -> 3320 | E13: ='Case Summarised'!F13 -> 29868 | F13: ='Case Summarised'!H13 -> 94 | G13: ='Case Summarised'!J13 -> 130 | H13: ='Case Summarised'!L13 -> 18486 | I13: ='Case Summarised'!N13 -> 1 | J13: ='Case Summarised'!P13 -> 582 | K13: =Hawassa!N297 -> 5.8689031e+08 | L13: =D13+E13+F13+G13+H13+I13+J13 -> 52481 | M13: ='Case Summarised'!Q13 -> 0 | N13: =M13/J13 -> 0 | O13: 5 | P13: =B13-O13 -> 34 | Q13: =D13+E13+F13+G13+H13+I13+J13 -> 52481
A14: 10 | B14: 36 | C14: Hossaena | D14: ='Case Summarised'!D14 -> 5961 | E14: ='Case Summarised'!F14 -> 47643 | F14: ='Case Summarised'!H14 -> 40 | G14: ='Case Summarised'!J14 -> 164 | H14: ='Case Summarised'!L14 -> 121170 | I14: ='Case Summarised'!N14 -> 1 | J14: ='Case Summarised'!P14 -> 234 | K14: =Hossaena!M209 -> 22785826 | L14: =D14+E14+F14+G14+H14+I14+J14 -> 175213 | M14: ='Case Summarised'!Q14 -> 206 | N14: =M14/J14 -> 0.88034188 | O14: 5 | P14: =B14-O14 -> 31 | Q14: =D14+E14+F14+G14+H14+I14+J14 -> 175213
A15: 11 | B15: 26 | C15: Wolkite | D15: ='Case Summarised'!D15 -> 225 | E15: ='Case Summarised'!F15 -> 16435 | F15: ='Case Summarised'!H15 -> 42 | G15: ='Case Summarised'!J15 -> 294 | H15: ='Case Summarised'!L15 -> 53926 | I15: ='Case Summarised'!N15 -> 0 | J15: ='Case Summarised'!P15 -> 101 | K15: =Wolkite!N185 -> 92500185 | L15: =D15+E15+F15+G15+H15+I15+J15 -> 71023 | M15: ='Case Summarised'!Q15 -> 11 | N15: =M15/J15 -> 0.10891089 | O15: 3 | P15: =B15-O15 -> 23 | Q15: =D15+E15+F15+G15+H15+I15+J15 -> 71023
A16: 12 | B16: 20 | C16: Jimma | D16: ='Case Summarised'!D16 -> 129 | E16: ='Case Summarised'!F16 -> 4114 | F16: ='Case Summarised'!H16 -> 32 | G16: ='Case Summarised'!J16 -> 3238 | H16: ='Case Summarised'!L16 -> 62264 | I16: ='Case Summarised'!N16 -> 16 | J16: ='Case Summarised'!P16 -> 300 | K16: =Jimma!N126 -> 1.4931622e+08 | L16: =D16+E16+F16+G16+H16+I16+J16 -> 70093 | M16: ='Case Summarised'!Q16 -> 0 | O16: 14 | P16: =B16-O16 -> 6 | Q16: =D16+E16+F16+G16+H16+I16+J16 -> 70093
A17: 13 | B17: 11 | C17: Mekelle | D17: ='Case Summarised'!D17 -> 0 | E17: ='Case Summarised'!F17 -> 1536 | F17: ='Case Summarised'!H17 -> 0 | G17: ='Case Summarised'!J17 -> 0 | H17: ='Case Summarised'!L17 -> 6357 | I17: ='Case Summarised'!N17 -> 13 | J17: ='Case Summarised'!P17 -> 6 | K17: =Mekelle!N26 -> 21633865 | L17: =D17+E17+F17+G17+H17+I17+J17 -> 7912 | M17: ='Case Summarised'!Q17 -> 3 | N17: =M17/J17 -> 0.5 | P17: =B17-O17 -> 11 | Q17: =D17+E17+F17+G17+H17+I17+J17 -> 7912
B18: =SUM(B5:B17) -> 424 | C18: TOTAL | D18: =SUM(D5:D17) -> 33980 | E18: ='Case Summarised'!F18 -> 224627 | F18: ='Case Summarised'!H18 -> 1126 | G18: ='Case Summarised'!J18 -> 30321 | H18: ='Case Summarised'!L18 -> 784732 | I18: ='Case Summarised'!N18 -> 5160 | J18: ='Case Summarised'!P18 -> 8111 | K18: =SUM(K5:K17) -> 8.3068025e+09 | L18: =D18+E18+F18+G18+H18+I18+J18 -> 1088057 | M18: ='Case Summarised'!Q18 -> 875 | N18: =M18/J18 -> 0.10787819 | O18: =SUM(O5:O17) -> 50 | P18: =B18-O18 -> 374 | Q18: =D18+E18+F18+G18+H18+I18+J18 -> 1088057
O19: =O18/B18 -> 0.11792453 | P19: =P18/B18 -> 0.88207547

Sheet East
B1: NIB International Bank S.C
B2: Monthly internal Control Reports
B3: As of July 31, 2026
A4: Ser.No | B4: Branch | C4: District | D4: Operation area | E4: ATM Cases | G4: It Case | H4: Zero Balance | I4: Dormant A/C | J4: Cheque Bok Case | K4: Other cases | L4: Posting Date | M4: Types of Irregularities/problems | N4: Amount involved | O4: Status of the irregularities
D5: Operation area | E5: Mismatch | F5: Long outstanding | K5: finding NO. | M5: Finding | O5: Unrectified | P5: Rectified | Q5: Unrectified In Amount
A6: 1 | B6: ARABSSA | C6: East district | D6: Cash and Cash Items | K6: 1 | L6: JULY 31,2026 | M6: Difference observed on ATM cash balance.(The physical cash count balance of ATM have shown a difference of Birr compared with the general ledger balance . ) | N6: -12403.62 | O6: 1
A7: 2 | B7: ARABSSA | C7: East district | D7: Account Management | G7: 1 | L7: october 10,2021 | M7: System suspense account AC | N7: 1087.8 | O7: 1
A8: 3 | B8: ARABSSA | C8: East district | D8: Account Management | G8: 1 | L8: october 10,2021 | M8: Migration suspense accounts | N8: 0.48 | O8: 1
A9: 4 | B9: ARABSSA | C9: East district | D9: Deposit Accounts | H9: 37 | L9: JULY 31,2026 | M9: Zero (0.00) balance Account Found at branch | O9: 37 | P9: 35
A10: 5 | B10: ARABSSA | C10: East district | D10: Deposit Accounts | I10: 827 | L10: JULY 31,2026 | M10: Dormant accounts Found at the branch | N10: 509552.22 | O10: 827
A11: 6 | B11: ARABSSA | C11: East district | D11: Card Banking | F11: 354 | L11: JULY 31,2026 | M11: ATM cards & PIN mailers were not delivered to the respective account holders/ customers for a long period of time as presented below. 354 Card & 22 PIN | O11: 354
A12: 7 | B12: ARABSSA | C12: East district | D12: Ticket Vouching | K12: 1 | L12: JULY 6,2026 | M12: Diposit vocher missing date | N12: 4000 | O12: 1 | P12: 1
A13: 8 | B13: ARABSSA | C13: East district | D13: Ticket Vouching | K13: 1 | L13: JULY 8,2026 | M13: fund transfer missing signaature | N13: 10000 | O13: 1
A14: 9 | B14: ARABSSA | C14: East district | D14: Ticket Vouching | K14: 1 | L14: JULY 17,2026 | M14: Missing date in withdrawal voucher | N14: 6000 | O14: 1 | P14: 1
A15: 10 | B15: ARABSSA | C15: East district | D15: Ticket Vouching | K15: 1 | L15: JULY 25,2026 | M15: Withddrawal vocher in word&f igure d/c | N15: 2000 | O15: 1 | P15: 1
A16: 11 | B16: AYAT 72 | C16: East district | D16: Cash and Cash Items | K16: 1 | M16: Abnormal balances of ATM cash | N16: 34700 | O16: 1
A17: 12 | B17: AYAT 72 | C17: East district | D17: Account Management | G17: 1 | M17: Inter branch T-24 R10 | N17: -9282596.8 | O17: 1
A18: 13 | B18: AYAT 72 | C18: East district | D18: Account Management | G18: 1 | M18: Migration suspense accounts | N18: 4611.81 | O18: 1
A19: 14 | B19: AYAT 72 | C19: East district | G19: 1 | M19: Catch all asset and liability | N19: 591.07 | O19: 1 | P19: 1
A20: 15 | B20: AYAT 72 | C20: East district | D20: Account Management | K20: 1 | M20: Sundry creditors | N20: -3193 | O20: 1
A21: 16 | B21: AYAT 72 | C21: East district | D21: Deposit Accounts | I21: 262 | M21: Dormant accounts Found at the branch | O21: 262
A22: 17 | B22: AYAT 72 | C22: East district | D22: Card Banking | F22: 278 | M22: ATM cards & PIN mailers were not delivered to the respective account holders/ customers for a long period of time as presented below. | N22: 2700 | O22: 278 | P22: 1
A23: 18 | B23: AYAT 72 | C23: East district | D23: =D24 -> Ticket Vouching | K23: 1 | L23: 46029 | M23: Ato addis ashenafi acc transfe wrong date 150USD | N23: 150 | O23: 1 | P23: 1
A24: 19 | B24: AYAT 72 | C24: East district | D24: =D25 -> Ticket Vouching | K24: =K23 -> 1 | L24: 46029 | M24: cash withdrawal with wrong year but | N24: 5000 | O24: 1 | P24: 1
A25: 20 | B25: AYAT 72 | C25: East district | D25: =D26 -> Ticket Vouching | K25: =K24 -> 1 | L25: 46060 | M25: tsedenia manaye cash deposit date error | N25: 15000 | O25: 1 | P25: 1
A26: 21 | B26: AYAT 72 | C26: East district | D26: =D27 -> Ticket Vouching | K26: =K25 -> 1 | L26: 46060 | M26: tsedenia manaye acc transfer date error | N26: 10000 | O26: 1 | P26: 1
A27: 22 | B27: AYAT 72 | C27: East district | D27: =D28 -> Ticket Vouching | K27: =K26 -> 1 | L27: 46210 | M27: cash withdrawal with out customer signatuer | N27: 1100 | O27: 1 | P27: 1
A28: 23 | B28: AYAT 72 | C28: East district | D28: =D30 -> Ticket Vouching | K28: =K29 -> 1 | L28: 21/07/26 | M28: cash withdrawal with out customer signature | N28: 1050 | O28: 1 | P28: 1
A29: 24 | B29: AYAT 72 | C29: East district | D29: =D28 -> Ticket Vouching | K29: =K30 -> 1 | L29: 24/07/26 | M29: cash withdrawal with wrong date | N29: 100 | O29: 1 | P29: 1
A30: 25 | B30: AYAT 72 | C30: East district | D30: Ticket Vouching | K30: 1 | L30: 23/07/26 | M30: cash withdrawal with customer signature error | N30: 2000 | O30: 1 | P30: 1
A31: 26 | B31: AYAT ADEBABAY | C31: East district | D31: Account Management | G31: 1 | M31: Inter branch T-24 R10 | N31: -1.0536097e+08 | O31: 1
A32: 27 | B32: AYAT ADEBABAY | C32: East district | D32: Account Management | G32: 1 | M32: Migration suspense accounts | N32: -2634499.9 | O32: 1
A33: 28 | B33: AYAT ADEBABAY | C33: East district | K33: 1 | M33: Un collected Service fee on RTGS transfer from customers in Nov 2022 | N33: 1150 | O33: 1
A34: 29 | B34: AYAT ADEBABAY | C34: East district | D34: Deposit Accounts | H34: 433 | M34: Zero (0.00) balance Account Found at branch | O34: 433 | P34: 21
A35: 30 | B35: AYAT ADEBABAY | C35: East district | D35: Deposit Accounts | I35: 109 | M35: Dormant accounts Found at the branch | N35: 3752611.3 | O35: 109
A36: 31 | B36: AYAT ADEBABAY | C36: East district | D36: Card Banking | F36: 722 | M36: ATM cards & PIN mailers were not delivered to the respective account holders/ customers for a long period of time.(691 Cards & 722 Pins) | N36: - | O36: 722
A37: 32 | B37: AYAT ADEBABAY | C37: East district | D37: Loan and Advances | K37: 3 | M37: Loans with Arears | N37: 2345481 | O37: 3
A38: 33 | B38: AYAT ADEBABAY | C38: East district | D38: Ticket Vouching | K38: 1 | L38: 46180 | M38: Date error made on cash withdrawal voucher | N38: 7500 | O38: 1 | P38: 1
A39: 34 | B39: AYAT ADEBABAY | C39: East district | D39: Ticket Vouching | K39: 1 | L39: 46363 | M39: Date error made on cash withdrawal voucher | N39: 600 | O39: 1
A40: 35 | B40: AYAT ADEBABAY | C40: East district | D40: Ticket Vouching | K40: 1 | L40: 24/7/2026 | M40: Amount in words not written in cash withdrawal Voucherform | N40: 3300 | O40: 1
A41: 36 | B41: AYAT ADEBABAY | C41: East district | D41: Ticket Vouching | K41: 1 | M41: Fcy cash GBP is kept on custody of the branch that denied by treasury due to in genuinity. GBP 15 | N41: 15 | O41: 1
A42: 37 | B42: AYAT ADEBABAY | C42: East district | D42: Ticket Vouching | K42: 1 | M42: Tickets & Stationery materials kept in cash area | O42: 1
A43: 38 | B43: BESHALE | C43: East district | D43: Cash and Cash Items | K43: 1 | L43: 30/06/2026 | M43: Difference observed on ATM cash balance.(The physical cash count balance of ATM have shown a difference of Birr compared with the general ledger balance . ) | N43: 53202.69 | O43: 1
A44: 39 | B44: BESHALE | C44: East district | D44: Account Management | G44: 1 | L44: 30/06/2026 | M44: Inter branch T-24 R10 | N44: -37540550 | O44: 1
A45: 40 | B45: BESHALE | C45: East district | D45: Account Management | G45: 1 | L45: 30/06/2026 | M45: Inter branch ACC T-24 | N45: -37362526 | O45: 1
A46: 41 | B46: BESHALE | C46: East district | D46: Account Management | G46: 1 | L46: 30/06/2026 | M46: Migration suspense accounts | N46: -167191.79 | O46: 1
A47: 42 | B47: BESHALE | C47: East district | D47: Account Management | G47: 1 | L47: 30/06/2026 | M47: System Suspense-Ac | N47: -0.01 | O47: 1
A48: 43 | B48: BESHALE | C48: East district | D48: Account Management | G48: 1 | L48: 30/06/2026 | M48: Catch all unassigned pl | N48: 141.5 | O48: 1
A49: 44 | B49: BESHALE | C49: East district | D49: Deposit Accounts | H49: 397 | L49: 30/06/2026 | M49: Zero (0.00) balance Account Found at branch | N49: 0 | O49: 397 | P49: 2
A50: 45 | B50: BESHALE | C50: East district | D50: Deposit Accounts | I50: 2527 | L50: 30/06/2026 | M50: Dormant accounts Found at the branch | N50: 3695035.5 | O50: 2527
A51: 46 | B51: BESHALE | C51: East district | D51: Card Banking | F51: 352 | L51: 30/06/2026 | M51: ATM cards & PIN mailers were not delivered to the respective account holders/ customers for a long period of time | O51: 352
A52: 47 | B52: BESHALE | C52: East district | D52: Ticket Vouching | K52: 1 | L52: 16/05/2026 | M52: fund transfer made without authorized customer signature | N52: 100000 | O52: 1 | P52: 1
A53: 48 | B53: BESHALE | C53: East district | D53: Ticket Vouching | K53: 1 | L53: 26/07/2026 | M53: ACCOUNT FUND TRANSFER MADE WITHOUT AUTRIZED CUSTOMER SIGNATURE | N53: 1070000 | O53: 1 | P53: 1
A54: 49 | B54: BESHALE | C54: East district | D54: Ticket Vouching | K54: 1 | L54: 28/05/2026 | M54: fund transfer made without authorized customer signature | N54: 100000 | O54: 1 | P54: 1
A55: 50 | B55: BESHALE | C55: East district | D55: Ticket Vouching | K55: 1 | L55: 28/5/2026 | M55: check book prepaired and deliverd to customer without authorized signature | N55: 200 | O55: 1
A56: 51 | B56: BESHALE | C56: East district | D56: Ticket Vouching | K56: 1 | L56: Feb/5/2026 | M56: fund transfer made without authorized customer signature | N56: 7698.8 | O56: 1 | P56: 1
A57: 52 | B57: BESHALE | C57: East district | D57: Ticket Vouching | K57: 1 | L57: Feb/4/2026 | M57: Employee salary transfer with out Athourized custmor sign | N57: 257709.99 | O57: 1 | P57: 1
A58: 53 | B58: BESHALE | C58: East district | D58: Ticket Vouching | K58: 1 | L58: Feb/5/2026 | M58: Fund Transfer made from Z-Addis Hotel Account for wtihholding tax payment woth out Athourized sign | N58: 7031.62 | O58: 1 | P58: 1
A59: 54 | B59: BESHALE | C59: East district | D59: Ticket Vouching | K59: 1 | L59: Feb/10/2026 | M59: fund transfer made without authorized customer signature | N59: 500000 | O59: 1 | P59: 1
A60: 55 | B60: BESHALE | C60: East district | D60: Ticket Vouching | K60: 1 | L60: 46085 | M60: fund transfer made without authorized customer signature | N60: 15602.49 | O60: 1 | P60: 1
A61: 56 | B61: BESHALE | C61: East district | D61: Ticket Vouching | K61: 1 | L61: 23/03/26 | M61: CASH WITHDRWAL MADE MISMACH WITH PAYMENT TCIKET AND TRANSACTION IN T24 SYSTEM | N61: 4884.18 | O61: 1
A62: 57 | B62: BESHALE | C62: East district | D62: Ticket Vouching | K62: 1 | L62: 46268 | M62: FUND TRNSFER MDE WITH ATTACHING NATIONAL ID | N62: 165000 | O62: 1 | P62: 1
A63: 58 | B63: BESHALE | C63: East district | D63: Ticket Vouching | K63: 1 | L63: 22/06/2026 | M63: CASH WITHDRWAL MADE WITH D/T OR MISMACH AMOUNT INWORD AND INFIGUR | N63: 2200 | O63: 1 | P63: 1
A64: 59 | B64: BESHALE | C64: East district | D64: Ticket Vouching | K64: 1 | M64: fund transfer made without authorized customer signature | N64: 200000 | O64: 1 | P64: 1
A65: 60 | B65: BESHALE | C65: East district | D65: Ticket Vouching | K65: 1 | L65: 30/07/2026 | M65: fund transfer made without authorized customer signature | N65: 100000 | O65: 1 | P65: 1
A66: 61 | B66: BESHALE | C66: East district | K66: 1 | L66: 46026 | M66: ACCOUNT FUND TRANSFER MADE WITHOUT AUTORIZED SIGNATURE | N66: 5800000 | O66: 1 | P66: 1
A67: 62 | B67: BESHALE | C67: East district | D67: Ticket Vouching | K67: 1 | L67: 31/07/2026 | M67: fund transfer made without authorized customer signature | N67: 4000 | O67: 1 | P67: 1
A68: 63 | B68: Bole Brass | C68: East district | D68: Account Management | K68: 1 | M68: Abnormal balances of ATM cash | N68: 34650 | O68: 1
A69: 64 | B69: Bole Brass | C69: East district | D69: Account Management | G69: 1 | M69: Migration suspense accounts | N69: 137244.54 | O69: 1
A70: 65 | B70: Bole Brass | C70: East district | D70: Deposit Accounts | I70: 337 | M70: Dormant accounts Found at the branch 12 Active | O70: 337
A71: 66 | B71: Bole Brass | C71: East district | D71: Negotiable Instrument | K71: 1 | M71: Dis-functional metal detector. | O71: 1
A72: 67 | B72: Bole Brass | C72: East district | D72: Others | K72: 1 | M72: FEMAL SEARCHER | O72: 1
A73: 68 | B73: Bole Brass | C73: East district | D73: Card Banking | F73: 390 | M73: ATM cards & PIN mailers were not delivered to the respective account holders/ customers for a long period of time as presented below. ATM 306 AND PIN 390 | O73: 390
A74: 69 | B74: Bole Brass | C74: East district | D74: Ticket Vouching | K74: 1 | L74: 46180 | M74: CASH WITHDRAWAL SIGNATURE MISSED | N74: 90 | O74: 1 | P74: 1
A75: 70 | B75: Bole Brass | C75: East district | D75: Ticket Vouching | K75: 1 | L75: 46210 | M75: CASH WITHDRWAL SIGNATURE MISSED | N75: 11000 | O75: 1 | P75: 1
A76: 71 | B76: Bole Brass | C76: East district | D76: Ticket Vouching | K76: 1 | L76: 46210 | M76: CASH WITHDRAWAL SIGNATURE MISSED | N76: 4764.2 | O76: 1 | P76: 1
A77: 72 | B77: Bole Brass | C77: East district | D77: Ticket Vouching | K77: 1 | L77: 18/7/2026 | M77: TRANSFER DATE MISSING | N77: 1000 | O77: 1 | P77: 1
A78: 73 | B78: Bole Brass | C78: East district | D78: Ticket Vouching | K78: 1 | L78: 27/7/26 | M78: DEPOSIT DATE MISSING | N78: 1300 | O78: 1 | P78: 1
A79: 74 | B79: Bole Brass | C79: East district | D79: Ticket Vouching | K79: 1 | L79: 28/7/2026 | M79: WITHDRAWAL ID NOT ATTACHED | N79: 954.43 | O79: 1 | P79: 1
A80: 75 | B80: Imperial sport acadamy | C80: East district | D80: CASh and Cash Items | K80: 1 | M80: Difference observed on ATM cash balance.(The physical cash count balance of ATM have shown a difference of Birr ……….. compared with the general ledger balance . ) | N80: 50703 | O80: 1
A81: 76 | B81: Imperial sport acadamy | C81: East district | D81: Account Management | G81: 1 | M81: Total fixed asset | N81: -26994538 | O81: 1
A82: 77 | B82: Imperial sport acadamy | C82: East district | D82: Account Management | G82: 1 | M82: Inter branch T-24 R10 | N82: 17429345 | O82: 1
A83: 78 | B83: Imperial sport acadamy | C83: East district | D83: Account Management | G83: 1 | M83: System suspense account AC | N83: 0 | O83: 1 | P83: 1
A84: 79 | B84: Imperial sport acadamy | C84: East district | D84: Account Management | G84: 1 | M84: Migration suspense accounts | N84: 60.38 | O84: 1
A85: 80 | B85: Imperial sport acadamy | C85: East district | D85: Deposit Accounts | H85: 189 | M85: Zero (0.00) balance Account Found at branch | O85: 189
A86: 81 | B86: Imperial sport acadamy | C86: East district | D86: Deposit Accounts | I86: 1200 | M86: Dormant accounts Found at the branch | O86: 1200
A87: 82 | B87: Imperial sport acadamy | C87: East district | D87: Card Banking | F87: 265 | M87: ATM cards & PIN mailers were not delivered to the respective account holders/ customers for a long period of time as presented below. 265 CARD & 264 PIN | O87: 265
A88: 83 | B88: MEGENAGNA GURD SHOLLA | C88: East district | D88: Cash and Cash Items | K88: 1 | M88: Dofference observed On Cash balance (physical cash count balance of cash have shown a difference of bir 502.50 compared with the General sedger balance.) | N88: 502.5 | O88: 1
A89: 84 | B89: MEGENAGNA GURD SHOLLA | C89: East district | D89: Account Management | G89: 1 | M89: Inter branch T-24 R10 | N89: 4049363.6 | O89: 1
A90: 85 | B90: MEGENAGNA GURD SHOLLA | C90: East district | D90: Account Management | G90: 1 | M90: Migration suspense accounts | N90: 502.2 | O90: 1
A91: 86 | B91: MEGENAGNA GURD SHOLLA | C91: East district | D91: Ticket Voucher | K91: 1 | L91: 46217 | M91: RTGS WITHOUT CUSTOMER SiGNACHERE RTGS TEDROS ALEMU 7000112722381 | N91: 2670000 | O91: 1
A92: 87 | B92: MEGENAGNA GURD SHOLLA | C92: East district | D92: Ticket Voucher | K92: 1 | L92: 46222 | M92: RTGS TEDROS ALEMU 7000112722381 WITHOUT CUSTOMER SiGNACHERE | N92: 250000 | O92: 1
A93: 88 | B93: MEGENAGNA GURD SHOLLA | C93: East district | D93: Ticket Voucher | K93: 1 | L93: 46224 | M93: RTGS BERCHUMA PLC 351SPS23 WITHOUT CUSTOMER SiGNACHERE | N93: 500000 | O93: 1
A94: 89 | B94: MEGENAGNA GURD SHOLLA | C94: East district | D94: Ticket Voucher | K94: 1 | L94: 46237 | M94: RTGS WITHOUT CUSTOMER SIGNACHER/TWO SIGNCHER Abel 351SAV7173 | N94: 300000 | O94: 1
A95: 90 | B95: MEGENAGNA GURD SHOLLA | C95: East district | D95: Ticket Voucher | K95: 1 | L95: 46224 | M95: RTGS ABEL DUGUMA 7000062459137 WITHOUT CUSTOMER SIGNACHERE | N95: 700000 | O95: 1
A96: 91 | B96: MEGENAGNA GURD SHOLLA | C96: East district | D96: Ticket Voucher | K96: 1 | L96: 46206 | M96: WITHOUT CUSTEMERE SEGNCHERE WITHDRAW 7000103066437 SLTANIE BOGALE | N96: 13000 | O96: 1 | P96: 1
A97: 92 | B97: MEGENAGNA GURD SHOLLA | C97: East district | D97: Ticket Voucher | K97: 1 | L97: 46204 | M97: TRANSFER REQUEST FORM ELECTRONIC PAYMENT MINSTRY OF TREDE AND REGIONAL 7000067533017 WITHOUT CUSTEMERE SEGNCHERE | N97: 9575 | O97: 1 | P97: 1
A98: 93 | B98: MEGENAGNA GURD SHOLLA | C98: East district | D98: Ticket Voucher | K98: 1 | L98: 46205 | M98: CHEQU WITHDRWAL WITHOUT CUSTEMERE SEGNCHERE MOTORI 7000067533017 | N98: 50000 | O98: 1 | P98: 1
A99: 94 | B99: MEGENAGNA GURD SHOLLA | C99: East district | D99: Ticket Voucher | K99: 1 | L99: 46206 | M99: CHEQU ORGNIZATION FOR SOCLALSERVIC WITHOUT COUSTEMERE SEGNCHERE 7000048081628 | N99: 10200 | O99: 1 | P99: 1
A100: 95 | B100: MEGENAGNA GURD SHOLLA | C100: East district | D100: Ticket Voucher | K100: 1 | L100: 46210 | M100: Account transfer Emoloy consumers privat WITHOUT CUSTOMER SIGNCAHER 7000067533017 | N100: 1326824.2 | O100: 1 | P100: 1
...

Sheet North
A1: NIB International Bank S.C
A2: North A.A District
A3: Detailed Monthly internal Control Reports
A4: As of JULY, 2026
A5: Ser. No | B5: Branch Name | C5: District Name | D5: Operation area | E5: Date | F5: Types of Irregularities/problems | G5: ATM Cases | I5: 0 | J5: 0 | K5: 0 | L5: 0 | M5: Other Case No. | N5: Amount involved | O5: status of irregularity | P5: 0
F6: Finding | G6: Mismatch | H6: Long O/S | I6: IT Cases | J6: Zero Bal. | K6: Dormant A/C | L6: CK Book | M6: 0 | N6: 0 | O6: Unrectified | P6: Rectified
A7: 1 | B7: Abakoran | C7: North A.A | D7: Cash & Cash Items | E7: 31/07/2026 | F7: Difference observed on ATM cash balance.(The physical cash count balance of ATM (240,300) have shown a difference of Birr 15,598.34 compared with the general ledger balance .(255,898.34) | G7: 0 | H7: 0 | I7: 0 | J7: 0 | K7: 0 | L7: 0 | M7: 1 | N7: 15598.34 | O7: =G7+H7+I7+J7+K7+L7+M7-P7 -> 1 | P7: 0
A8: 2 | B8: Abakoran | C8: North A.A | D8: Negotiable Instrument | E8: 31/07/2025 | F8: Cheque books prepared but not delivered to customers for a long period of time. | G8: 0 | H8: 0 | I8: 0 | J8: 0 | K8: 0 | L8: 51 | M8: 0 | N8: 0 | O8: =G8+H8+I8+J8+K8+L8+M8-P8 -> 51 | P8: 0
A9: 3 | B9: Abakoran | C9: North A.A | D9: Account Management | E9: 31/07/25 | F9: Inter branch T-24 R10 | G9: 0 | H9: 0 | I9: 1 | J9: 0 | K9: 0 | L9: 0 | M9: 0 | N9: -77522181 | O9: =G9+H9+I9+J9+K9+L9+M9-P9 -> 1 | P9: 0
A10: 4 | B10: Abakoran | C10: North A.A | D10: Account Management | E10: 31/07/25 | F10: Migration suspense accounts | G10: 0 | H10: 0 | I10: 1 | J10: 0 | K10: 0 | L10: 0 | M10: 0 | N10: 113922.37 | O10: =G10+H10+I10+J10+K10+L10+M10-P10 -> 1 | P10: 0
A11: 5 | B11: Abakoran | C11: North A.A | D11: Account Management | E11: 31/08/2025 | F11: Sundry debtors | G11: 0 | H11: 0 | I11: 0 | J11: 0 | K11: 0 | L11: 0 | M11: 3 | N11: 194773.41 | O11: =G11+H11+I11+J11+K11+L11+M11-P11 -> 3 | P11: 0
A12: 6 | B12: Abakoran | C12: North A.A | D12: Loan and Advances | E12: 31/08/2026 | F12: arrears loan show on the branch and NPL for long period of time | G12: 0 | H12: 0 | I12: 0 | J12: 0 | K12: 0 | L12: 0 | M12: 5 | N12: 1601059.5 | O12: =G12+H12+I12+J12+K12+L12+M12-P12 -> 5 | P12: 0
A13: 7 | B13: Abakoran | C13: North A.A | D13: Deposit Account | E13: 31/08/2026 | F13: Zero (0.00) balance Account Found at branch | G13: 0 | H13: 0 | I13: 0 | J13: 124 | K13: 0 | L13: 0 | M13: 0 | N13: 0 | O13: =G13+H13+I13+J13+K13+L13+M13-P13 -> 124 | P13: 0
A14: 8 | B14: Abakoran | C14: North A.A | D14: Deposit Account | E14: 31/07/2026 | F14: Dormant accounts Found at the branch | G14: 0 | H14: 0 | I14: 0 | J14: 0 | K14: 503 | L14: 0 | M14: 0 | N14: 3190418.7 | O14: =G14+H14+I14+J14+K14+L14+M14-P14 -> 500 | P14: 3
A15: 9 | B15: Abakoran | C15: North A.A | D15: Fixed Asset Management | E15: 31/07/2026 | F15: Absence of tag number | G15: 0 | H15: 0 | I15: 0 | J15: 0 | K15: 0 | L15: 0 | M15: 4 | N15: 0 | O15: =G15+H15+I15+J15+K15+L15+M15-P15 -> 0 | P15: 4
A16: 10 | B16: Abakoran | C16: North A.A | D16: Fixed Asset Management | E16: 31/08/2026 | F16: Defective/obsolete fixed assets found at the branch | G16: 0 | H16: 0 | I16: 0 | J16: 0 | K16: 0 | L16: 0 | M16: 4 | N16: 0 | O16: =G16+H16+I16+J16+K16+L16+M16-P16 -> 0 | P16: 4
A17: 11 | B17: Abakoran | C17: North A.A | D17: Card Banking | E17: 31/08/2026 | F17: ATM cards & PIN mailers were not delivered to the respective account holders/ customers for a long period of time as presented below. | G17: 0 | H17: 321 | I17: 0 | J17: 0 | K17: 0 | L17: 0 | M17: 0 | N17: 0 | O17: =G17+H17+I17+J17+K17+L17+M17-P17 -> 321 | P17: 0
A18: 12 | B18: Abakoran | C18: North A.A | D18: Card Banking | E18: 31/08/2026 | F18: ATM card(321) and PIN Mailers(105) were differ | G18: =321-105 -> 216 | H18: 0 | I18: 0 | J18: 0 | K18: 0 | L18: 0 | M18: 0 | N18: 0 | O18: =G18+H18+I18+J18+K18+L18+M18-P18 -> 216 | P18: 0
A19: 13 | B19: Abakoran | C19: North A.A | D19: Ticket Vouching | E19: 31/08/2026 | F19: Cash withdrawal Without Signature | G19: 0 | H19: 0 | I19: 0 | J19: 0 | K19: 0 | L19: 0 | M19: 1 | N19: 40000 | O19: =G19+H19+I19+J19+K19+L19+M19-P19 -> 0 | P19: 1
A20: 14 | B20: Abakoran | C20: North A.A | D20: Ticket Vouching | E20: 31/08/2026 | F20: RTGS without signature | G20: 0 | H20: 0 | I20: 0 | J20: 0 | K20: 0 | L20: 0 | M20: 5 | N20: 16580000 | O20: =G20+H20+I20+J20+K20+L20+M20-P20 -> 0 | P20: 5
A21: 15 | B21: Abakoran | C21: North A.A | D21: Ticket Vouching | E21: 31/08/2026 | F21: Account transfer without signature | G21: 0 | H21: 0 | I21: 0 | J21: 0 | K21: 0 | L21: 0 | M21: 7 | N21: 4385300 | O21: =G21+H21+I21+J21+K21+L21+M21-P21 -> 0 | P21: 7
A22: 16 | B22: Abakoran | C22: North A.A | D22: Others | E22: 26/12/25 | F22: Catch All - Unassigned PL | G22: 0 | H22: 0 | I22: 1 | J22: 0 | K22: 0 | L22: 0 | M22: 0 | N22: 3128.32 | O22: =G22+H22+I22+J22+K22+L22+M22-P22 -> 1 | P22: 0
A23: 17 | B23: Adidisu Gebeya | C23: North A.A | D23: Cash & Cash Items | E23: 30/6/26 | F23: Difference observed on ATM cash balance.(The physical cash count balance of ATM have shown a difference of Birr ……….. compared with the general ledger balance . ) | G23: 0 | H23: 0 | I23: 0 | J23: 0 | K23: 0 | L23: 0 | M23: 1 | N23: 23500 | O23: =G23+H23+I23+J23+K23+L23+M23-P23 -> 1 | P23: 0
A24: 18 | B24: Adidisu Gebeya | C24: North A.A | D24: Account Management | E24: 30/6/26 | F24: Difference in non contingent | G24: 0 | H24: 0 | I24: 1 | J24: 0 | K24: 0 | L24: 0 | M24: 0 | N24: 930401 | O24: =G24+H24+I24+J24+K24+L24+M24-P24 -> 1 | P24: 0
A25: 19 | B25: Adidisu Gebeya | C25: North A.A | D25: Account Management | E25: 30/6/26 | F25: Inter branch T-24 R10 | G25: 0 | H25: 0 | I25: 1 | J25: 0 | K25: 0 | L25: 0 | M25: 0 | N25: 5516790.1 | O25: =G25+H25+I25+J25+K25+L25+M25-P25 -> 1 | P25: 0
A26: 20 | B26: Adidisu Gebeya | C26: North A.A | D26: Account Management | E26: 30/6/26 | F26: Sundry debtors (Loan Balance CorrectionExpense) | G26: 0 | H26: 0 | I26: 0 | J26: 0 | K26: 0 | L26: 0 | M26: 1 | N26: 758257.7 | O26: =G26+H26+I26+J26+K26+L26+M26-P26 -> 1 | P26: 0
A27: 21 | B27: Adidisu Gebeya | C27: North A.A | D27: Deposit Account | E27: 30/6/26 | F27: Dormant accounts Found at the branch | G27: 0 | H27: 0 | I27: 0 | J27: 0 | K27: 750 | L27: 0 | M27: 0 | N27: 14333701 | O27: =G27+H27+I27+J27+K27+L27+M27-P27 -> 748 | P27: 2
A28: 22 | B28: Amist Killo | C28: North A.A | D28: Account Management | E28: 44206 | F28: Inter branch T-24 R10 | G28: 0 | H28: 0 | I28: 1 | J28: 0 | K28: 0 | L28: 0 | M28: 0 | N28: 47868363 | O28: =G28+H28+I28+J28+K28+L28+M28-P28 -> 1 | P28: 0
A29: 23 | B29: Amist Killo | C29: North A.A | D29: Account Management | E29: 31/07/26 | F29: loss on A/L Revaluation | G29: 0 | H29: 0 | I29: 1 | J29: 0 | K29: 0 | L29: 0 | M29: 0 | N29: 75908.56 | O29: =G29+H29+I29+J29+K29+L29+M29-P29 -> 1 | P29: 0
A30: 24 | B30: Amist Killo | C30: North A.A | D30: Card Banking | E30: 31/07/26 | F30: Dormant accounts Found at the branch | G30: 0 | I30: 0 | J30: 0 | K30: 307 | L30: 0 | M30: 0 | N30: 112833 | O30: =G30+H30+I30+J30+K30+L30+M30-P30 -> 307 | P30: 0
A31: 25 | B31: Amist Killo | C31: North A.A | D31: Card Banking | E31: 45664 | F31: ATM cards & PIN mailers were not delivered to the respective account holders/ customers for a long period of time as presented below. | G31: 0 | H31: 897 | I31: 0 | J31: 0 | K31: 0 | L31: 0 | M31: 0 | N31: 0 | O31: =G31+H31+I31+J31+K31+L31+M31-P31 -> 897 | P31: 0
A32: 26 | B32: Amist Killo | C32: North A.A | D32: Card Banking | E32: 45664 | F32: ATM card(897) and PIN Mailers(278) were differ | G32: 619 | H32: 0 | I32: 0 | J32: 0 | K32: 0 | L32: 0 | M32: 0 | N32: 0 | O32: =G32+H32+I32+J32+K32+L32+M32-P32 -> 619 | P32: 0
A33: 27 | B33: Arada Giorgis | C33: North AA | D33: Cash and Cash Items | E33: 45863 | F33: Abnormal balances of ATM cash | G33: 0 | H33: 0 | I33: 0 | J33: 0 | K33: 0 | L33: 0 | M33: 1 | N33: 81.08 | O33: =G33+H33+I33+J33+K33+L33+M33-P33 -> 1 | P33: 0
A34: 28 | B34: Arada Giorgis | C34: North AA | D34: Cash & Cash Items | E34: 46081 | F34: Difference observed on ATM cash balance.(The physical cash count balance of ATM have shown a difference of Birr ……….. compared with the general ledger balance . ) | G34: 0 | H34: 0 | I34: 0 | J34: 0 | K34: 0 | L34: 0 | M34: 1 | N34: 35138.94 | O34: =G34+H34+I34+J34+K34+L34+M34-P34 -> 1 | P34: 0
A35: 29 | B35: Arada Giorgis | C35: North AA | D35: Account Management | E35: 45863 | F35: Inter branch T-24 R10 | G35: 0 | H35: 0 | I35: 1 | J35: 0 | K35: 0 | L35: 0 | M35: 0 | N35: 23705127 | O35: =G35+H35+I35+J35+K35+L35+M35-P35 -> 1 | P35: 0
A36: 30 | B36: Arada Giorgis | C36: North AA | D36: Account Management | E36: 45863 | F36: Migration suspense accounts | G36: 0 | H36: 0 | I36: 1 | J36: 0 | K36: 0 | L36: 0 | M36: 0 | N36: 225315.21 | O36: =G36+H36+I36+J36+K36+L36+M36-P36 -> 1 | P36: 0
A37: 31 | B37: Arada Giorgis | C37: North AA | D37: Account Management | F37: sundry debtors uncollected RTGS commission | G37: 0 | H37: 0 | I37: 0 | J37: 0 | K37: 0 | L37: 0 | M37: 1 | N37: 350 | O37: =G37+H37+I37+J37+K37+L37+M37-P37 -> 0 | P37: 1
A38: 32 | B38: Arada Giorgis | C38: North AA | D38: Account Management | E38: 45863 | F38: Sundry debtors - RECEIVABLE COURT CASE | G38: 0 | H38: 0 | I38: 0 | J38: 0 | K38: 0 | L38: 0 | M38: 1 | N38: 184 | O38: =G38+H38+I38+J38+K38+L38+M38-P38 -> 1 | P38: 0
A39: 33 | B39: Arada Giorgis | C39: North AA | D39: Account Management | E39: 45863 | F39: Sundry creditors(OFFICE RENT) | G39: 0 | H39: 0 | I39: 0 | J39: 0 | K39: 0 | L39: 0 | M39: 1 | N39: 3146426.2 | O39: =G39+H39+I39+J39+K39+L39+M39-P39 -> 1 | P39: 0
A40: 34 | B40: Arada Giorgis | C40: North AA | D40: Deposit Account | F40: Dormant accounts Found at the branch | G40: 0 | H40: 0 | I40: 0 | J40: 0 | K40: 259 | L40: 0 | M40: 0 | N40: 2597508 | O40: =G40+H40+I40+J40+K40+L40+M40-P40 -> 258 | P40: 1
A41: 35 | B41: Arada Giorgis | C41: North AA | D41: Card Banking | E41: 25/072025 | F41: ATM cards & PIN mailers were not delivered to the respective account holders/ customers for a long period of time as presented below. | G41: 0 | H41: 227 | I41: 0 | J41: 0 | K41: 0 | L41: 0 | M41: 0 | N41: 0 | O41: =G41+H41+I41+J41+K41+L41+M41-P41 -> 227 | P41: 0
A42: 36 | B42: Arada Giorgis | C42: North AA | D42: Card Banking | F42: ATM card(227) and PIN Mailers(21) were differ | G42: 206 | H42: 0 | I42: 0 | J42: 0 | K42: 0 | L42: 0 | M42: 0 | N42: 0 | O42: =G42+H42+I42+J42+K42+L42+M42-P42 -> 206 | P42: 0
A43: 37 | B43: Arat Killo | C43: North AA | D43: Account Management | E43: 31/07/2025 | F43: Inter branch T-24 R10 | G43: 0 | H43: 0 | I43: 1 | J43: 0 | K43: 0 | L43: 0 | M43: 0 | N43: 35818221 | O43: =G43+H43+I43+J43+K43+L43+M43-P43 -> 1 | P43: 0
A44: 38 | B44: Arat Killo | C44: North AA | D44: Account Management | E44: 31/07/2025 | F44: Migration suspense accounts | G44: 0 | H44: 0 | I44: 1 | J44: 0 | K44: 0 | L44: 0 | M44: 0 | N44: 34.08 | O44: =G44+H44+I44+J44+K44+L44+M44-P44 -> 1 | P44: 0
A45: 39 | B45: Arat Killo | C45: North AA | D45: Account Management | E45: 31/07/2025 | F45: Catch all asset and liability | G45: 0 | H45: 0 | I45: 1 | J45: 0 | K45: 0 | L45: 0 | M45: 0 | N45: 62.01 | O45: =G45+H45+I45+J45+K45+L45+M45-P45 -> 1 | P45: 0
A46: 40 | B46: Arat Killo | C46: North AA | D46: Account Management | E46: 31/07/2026 | F46: Sundry debtors | G46: 0 | H46: 0 | I46: 0 | J46: 0 | K46: 0 | L46: 0 | M46: 1 | N46: 1850 | O46: =G46+H46+I46+J46+K46+L46+M46-P46 -> 1 | P46: 0
A47: 41 | B47: Arat Killo | C47: North AA | D47: Account Management | E47: 31/07/2026 | F47: Sundry creditors | G47: 0 | H47: 0 | I47: 0 | J47: 0 | K47: 0 | L47: 0 | M47: 1 | N47: 383901.2 | O47: =G47+H47+I47+J47+K47+L47+M47-P47 -> 1 | P47: 0
A48: 42 | B48: Arat Killo | C48: North AA | D48: Deposit Account | E48: 31/07/2026 | F48: Dormant accounts Found at the branch | G48: 0 | H48: 0 | I48: 0 | J48: 0 | K48: 3257 | L48: 0 | M48: 0 | N48: 7535721.1 | O48: =G48+H48+I48+J48+K48+L48+M48-P48 -> 3257 | P48: 0
A49: 43 | B49: Artist Mohammud | C49: North AA | D49: Cash and Cash Items | E49: 31/08/2025 | F49: Abnormal balances of ATM cash | G49: 0 | H49: 0 | I49: 0 | J49: 0 | K49: 0 | L49: 0 | M49: 5 | N49: 488795.69 | O49: =G49+H49+I49+J49+K49+L49+M49-P49 -> 5 | P49: 0
A50: 44 | B50: Artist Mohammud | C50: North AA | D50: Negotiable Instrument | E50: 31/08/2025 | F50: Cheque books prepared but not delivered to customers for a long period of time. | G50: 0 | H50: 0 | I50: 0 | J50: 0 | K50: 0 | L50: 205 | M50: 0 | N50: 7143.5 | O50: =G50+H50+I50+J50+K50+L50+M50-P50 -> 205 | P50: 0
A51: 45 | B51: Artist Mohammud | C51: North AA | D51: Account Management | E51: 31/08/2025 | F51: Inter branch T-24 R10 | G51: 0 | H51: 0 | I51: 1 | J51: 0 | K51: 0 | L51: 0 | M51: 0 | N51: -5.2305083e+08 | O51: =G51+H51+I51+J51+K51+L51+M51-P51 -> 1 | P51: 0
A52: 46 | B52: Artist Mohammud | C52: North AA | D52: Account Management | E52: 31/08/2025 | F52: Migration suspense accounts | G52: 0 | H52: 0 | I52: 1 | J52: 0 | K52: 0 | L52: 0 | M52: 0 | N52: -48553.62 | O52: =G52+H52+I52+J52+K52+L52+M52-P52 -> 1 | P52: 0
A53: 47 | B53: Artist Mohammud | C53: North AA | D53: Account Management | E53: 31/08/2025 | F53: loss on A/L Revaluation | G53: 0 | H53: 0 | I53: 1 | J53: 0 | K53: 0 | L53: 0 | M53: 0 | N53: -548277.13 | O53: =G53+H53+I53+J53+K53+L53+M53-P53 -> 1 | P53: 0
A54: 48 | B54: Artist Mohammud | C54: North AA | D54: Account Management | E54: 31/08/2025 | F54: Sundry debtors | G54: 0 | H54: 0 | I54: 0 | J54: 0 | K54: 0 | L54: 0 | M54: 1 | N54: 14000 | O54: =G54+H54+I54+J54+K54+L54+M54-P54 -> 1 | P54: 0
... A56: 50 | B56: Artist Mohammud | C56: North AA | D56: Deposit Account | E56: 31/08/2025 | F56: Zero (0.00) balance Account Found at branch | G56: 0 | H56: 0 | I56: 0 | J56: 212 | K56: 0 | L56: 0 | M56: 0 | N56: 0 | O56: =G56+H56+I56+J56+K56+L56+M56-P56 -> 212 | P56: 0
A57: 51 | B57: Artist Mohammud | C57: North AA | D57: Deposit Account | E57: 46203 | F57: Dormant accounts Found at the branch | G57: 0 | H57: 0 | I57: 0 | J57: 0 | K57: 1255 | L57: 0 | M57: 0 | N57: 5172772.7 | O57: =G57+H57+I57+J57+K57+L57+M57-P57 -> 1255 | P57: 0
A58: 52 | B58: Artist Mohammud | C58: North AA | D58: Card Banking | E58: 31/08/2025 | F58: ATM cards & PIN mailers were not delivered to the respective account holders/ customers for a long period of time as presented below. | G58: 0 | H58: 299 | I58: 0 | J58: 0 | K58: 0 | L58: 0 | M58: 0 | N58: 0 | O58: =G58+H58+I58+J58+K58+L58+M58-P58 -> 299 | P58: 0
A59: 53 | B59: Artist Mohammud | C59: North AA | D59: Card Banking | E59: 31/08/2025 | F59: ATM card(299) and PIN Mailers(278) were differ | G59: 21 | H59: 0 | I59: 0 | J59: 0 | K59: 0 | L59: 0 | M59: 0 | O59: =G59+H59+I59+J59+K59+L59+M59-P59 -> 21 | P59: 0
A60: 54 | B60: Atikilt Tera | C60: North AA | D60: Account Management | E60: 30/04/2026 | F60: Total fixed asset | G60: 0 | H60: 0 | I60: 1 | J60: 0 | K60: 0 | L60: 0 | M60: 0 | N60: 1521977.9 | O60: =G60+H60+I60+J60+K60+L60+M60-P60 -> 1 | P60: 0
A61: 55 | B61: Atikilt Tera | C61: North AA | D61: Account Management | E61: 28/02/2026 | F61: Inter branch T-24 R10 | G61: 0 | H61: 0 | I61: 1 | J61: 0 | K61: 0 | L61: 0 | M61: 0 | N61: 10853532 | O61: =G61+H61+I61+J61+K61+L61+M61-P61 -> 1 | P61: 0
A62: 56 | B62: Atikilt Tera | C62: North AA | D62: Account Management | E62: 31/03/2026 | F62: Catch all asset and liability PL | G62: 0 | H62: 0 | I62: 1 | J62: 0 | K62: 0 | L62: 0 | M62: 0 | N62: 53099.08 | O62: =G62+H62+I62+J62+K62+L62+M62-P62 -> 0 | P62: 1
A63: 57 | B63: Atikilt Tera | C63: North AA | D63: Deposit Account | E63: 31/03/2026 | F63: Dormant accounts Found at the branch | G63: 0 | H63: 0 | I63: 0 | J63: 0 | K63: 33 | L63: 0 | M63: 0 | N63: 461110.98 | O63: =G63+H63+I63+J63+K63+L63+M63-P63 -> 33 | P63: 0
A64: 58 | B64: Atikilt Tera | C64: North AA | D64: Card Banking | E64: 31/03/2026 | F64: ATM cards & PIN mailers were not delivered to the respective account holders/ customers for a long period of time as presented below. | G64: 0 | H64: 359 | I64: 0 | J64: 0 | K64: 0 | L64: 0 | M64: 0 | N64: 0 | O64: =G64+H64+I64+J64+K64+L64+M64-P64 -> 359 | P64: 0
A65: 59 | B65: Aware | C65: North AA | D65: Cash and Cash Items | E65: January ,2021 | F65: Abnormal balances of ATM cash | G65: 0 | H65: 0 | I65: 0 | J65: 0 | K65: 0 | L65: 0 | M65: 1 | N65: 29041.43 | O65: =G65+H65+I65+J65+K65+L65+M65-P65 -> 1 | P65: 0
A66: 60 | B66: Aware | C66: North AA | D66: Account Management | E66: June 29,2026 | F66: Account Rec.Miscellaneous | G66: 0 | H66: 0 | J66: 0 | K66: 0 | L66: 0 | M66: 1 | N66: 910 | O66: =G66+H66+I66+J66+K66+L66+M66-P66 -> 0 | P66: 1
A67: 61 | B67: Aware | C67: North AA | D67: Account Management | E67: October,2021 | F67: Migration suspense accounts | G67: 0 | H67: 0 | I67: 1 | J67: 0 | K67: 0 | L67: 0 | M67: 0 | N67: 1741.43 | O67: =G67+H67+I67+J67+K67+L67+M67-P67 -> 1 | P67: 0
A68: 62 | B68: Aware | C68: North AA | D68: Account Management | E68: June 10,2026 | F68: Catch all asset and liability | G68: 0 | H68: 0 | I68: 1 | J68: 0 | K68: 0 | L68: 0 | M68: 0 | N68: 6.68 | O68: =G68+H68+I68+J68+K68+L68+M68-P68 -> 1 | P68: 0
A69: 63 | B69: Aware | C69: North AA | D69: Deposit Account | F69: Zero (0.00) balance Account Found at branch | G69: 0 | H69: 0 | I69: 0 | J69: 555 | K69: 0 | L69: 0 | M69: 0 | N69: 0 | O69: =G69+H69+I69+J69+K69+L69+M69-P69 -> 555 | P69: 0
A70: 64 | B70: Aware | C70: North AA | D70: Security Management | F70: Dis-functional metal detector. | G70: 0 | H70: 0 | I70: 0 | J70: 0 | K70: 0 | L70: 0 | M70: 1 | N70: 0 | O70: =G70+H70+I70+J70+K70+L70+M70-P70 -> 1 | P70: 0
A71: 65 | B71: Aware | C71: North AA | D71: Card Banking | F71: ATM card(2720) and PIN Mailers(1351) were differ | G71: 0 | H71: 2720 | I71: 0 | J71: 0 | K71: 0 | L71: 0 | M71: 0 | N71: 0 | O71: =G71+H71+I71+J71+K71+L71+M71-P71 -> 2720 | P71: 0
A72: 66 | B72: Aware | C72: North AA | D72: Card Banking | F72: ATM cards & PIN mailers were not delivered to the respective account holders/ customers for a long period of time as presented below. | G72: =H71-1351 -> 1369 | H72: 0 | I72: 0 | J72: 0 | K72: 0 | L72: 0 | M72: 0 | N72: 0 | O72: =G72+H72+I72+J72+K72+L72+M72-P72 -> 1369 | P72: 0
A73: 67 | B73: Cathedral | C73: North AA | D73: Cash and Cash Items | E73: 31/07/2025 | F73: Abnormal balances of ATM cash | G73: 0 | H73: 0 | I73: 0 | J73: 0 | K73: 0 | L73: 0 | M73: 1 | N73: 331950 | O73: =G73+H73+I73+J73+K73+L73+M73-P73 -> 1 | P73: 0
A74: 68 | B74: Cathedral | C74: North AA | D74: Cash & Cash Items | E74: 31/07/2026 | F74: Difference observed on ATM cash balance.(The physical cash count balance of ATM have shown a difference of Birr ……….. compared with the general ledger balance . ) | G74: 0 | H74: 0 | I74: 0 | J74: 0 | K74: 0 | L74: 0 | M74: 1 | N74: 350750 | O74: =G74+H74+I74+J74+K74+L74+M74-P74 -> 1 | P74: 0
A75: 69 | B75: Cathedral | C75: North AA | D75: Negotiable Instrument | E75: 31/07/2025 | F75: Cheque books prepared but not delivered to customers for a long period of time. | G75: 0 | H75: 0 | I75: 0 | J75: 0 | K75: 0 | L75: 563 | M75: 0 | N75: 33386.5 | O75: =G75+H75+I75+J75+K75+L75+M75-P75 -> 563 | P75: 0
A76: 70 | B76: Cathedral | C76: North AA | D76: Account Management | E76: 31/07/2025 | F76: Inter branch T-24 R10 | G76: 0 | H76: 0 | I76: 1 | J76: 0 | K76: 0 | L76: 0 | M76: 0 | N76: 1.7404708e+08 | O76: =G76+H76+I76+J76+K76+L76+M76-P76 -> 1 | P76: 0
A77: 71 | B77: Cathedral | C77: North AA | D77: Account Management | E77: 31/07/2025 | F77: Migration suspense accounts | G77: 0 | H77: 0 | I77: 1 | J77: 0 | K77: 0 | L77: 0 | M77: 0 | N77: 151117.63 | O77: =G77+H77+I77+J77+K77+L77+M77-P77 -> 1 | P77: 0
A78: 72 | B78: Cathedral | C78: North AA | D78: Account Management | E78: 31/07/2025 | F78: Catch all asset and liability | G78: 0 | H78: 0 | I78: 5 | J78: 0 | K78: 0 | L78: 0 | M78: 0 | N78: 5 | O78: =G78+H78+I78+J78+K78+L78+M78-P78 -> 5 | P78: 0
A79: 73 | B79: Cathedral | C79: North AA | D79: Account Management | F79: Difference in Non Contingent | G79: 0 | H79: 0 | I79: 1 | J79: 0 | K79: 0 | L79: 0 | M79: 0 | N79: 25 | O79: =G79+H79+I79+J79+K79+L79+M79-P79 -> 1 | P79: 0
A80: 74 | B80: Cathedral | C80: North AA | D80: Account Management | E80: 31/07/2025 | F80: Sundry debtors | G80: 0 | H80: 0 | I80: 0 | J80: 0 | K80: 0 | L80: 0 | M80: 5 | N80: 595690.16 | O80: =G80+H80+I80+J80+K80+L80+M80-P80 -> 5 | P80: 0
A81: 75 | B81: Cathedral | C81: North AA | D81: Deposit Account | E81: 31/07/2026 | F81: Dormant accounts Found at the branch | G81: 0 | H81: 0 | I81: 0 | J81: 0 | K81: 2552 | L81: 0 | M81: 0 | N81: 59856699 | O81: =G81+H81+I81+J81+K81+L81+M81-P81 -> 2552 | P81: 0
A82: 76 | B82: Cathedral | C82: North AA | D82: Card Banking | E82: 31/07/2025 | F82: ATM cards & PIN mailers were not delivered to the respective account holders/ customers for a long period of time as presented below. | G82: 0 | H82: 256 | I82: 0 | J82: 0 | K82: 0 | L82: 0 | M82: 0 | N82: 0 | O82: =G82+H82+I82+J82+K82+L82+M82-P82 -> 256 | P82: 0
A83: 77 | B83: Cathedral | C83: North AA | D83: Card Banking | F83: ATM card(256) and PIN Mailers(117) were differ | G83: =H82-117 -> 139 | H83: 0 | I83: 0 | J83: 0 | K83: 0 | L83: 0 | M83: 0 | N83: 0 | O83: =G83+H83+I83+J83+K83+L83+M83-P83 -> 139 | P83: 0
A84: 78 | B84: Cathedral | C84: North AA | D84: Account Management | E84: 31/07/2026 | F84: CATH ALL -UNASSIGNED PL | G84: 0 | H84: 0 | I84: 4 | J84: 0 | K84: 0 | L84: 0 | M84: 0 | N84: 40151.28 | O84: =G84+H84+I84+J84+K84+L84+M84-P84 -> 4 | P84: 0
A85: 79 | B85: Cathedral | C85: North AA | D85: Account Management | E85: 30/06/2026 | F85: Diff of cost of cheque b/n physical count and general ledger | G85: 0 | H85: 0 | J85: 0 | K85: 0 | L85: 1 | M85: 0 | N85: 382.15 | O85: =G85+H85+I85+J85+K85+L85+M85-P85 -> 1 | P85: 0
A86: 80 | B86: Churchil | C86: North AA | D86: Cash and Cash Items | E86: FEB 12 2026 | F86: Abnormal balances of ATM cash | G86: 0 | H86: 0 | I86: 0 | J86: 0 | K86: 0 | L86: 0 | M86: 1 | N86: 5589 | O86: =G86+H86+I86+J86+K86+L86+M86-P86 -> 1 | P86: 0
A87: 81 | B87: Churchil | C87: North AA | D87: Cash & Cash Items | E87: LULY 31 2025 | F87: Long-term unconsolidated POS cash advance(POS Cash advance of Birr 4700left over in the General Ledger for a long time without being deposited) | G87: 0 | H87: 0 | I87: 0 | J87: 0 | K87: 0 | L87: 0 | M87: 1 | N87: 4700 | O87: =G87+H87+I87+J87+K87+L87+M87-P87 -> 1 | P87: 0
A88: 82 | B88: Churchil | C88: North AA | D88: Negotiable Instrument | E88: JUL-31,2025 | F88: Cheque books prepared but not delivered to customers for a long period of time. | G88: 0 | H88: 0 | I88: 0 | J88: 0 | K88: 0 | L88: 3 | M88: 0 | N88: 174.18 | O88: =G88+H88+I88+J88+K88+L88+M88-P88 -> 3 | P88: 0
A89: 83 | B89: Churchil | C89: North AA | D89: Account Management | E89: APR-30,2026 | F89: Total fixed asset | G89: 0 | H89: 0 | I89: 1 | J89: 0 | K89: 0 | L89: 0 | M89: 0 | N89: -2345362.9 | O89: =G89+H89+I89+J89+K89+L89+M89-P89 -> 1 | P89: 0
A90: 84 | B90: Churchil | C90: North AA | D90: Account Management | E90: JUL-31,2025 | F90: Inter branch T-24 R10 | G90: 0 | H90: 0 | I90: 1 | J90: 0 | K90: 0 | L90: 0 | M90: 0 | N90: -6105012.8 | O90: =G90+H90+I90+J90+K90+L90+M90-P90 -> 1 | P90: 0
A91: 85 | B91: Churchil | C91: North AA | D91: Account Management | E91: JUL-31,2025 | F91: System suspense account AC | G91: 0 | H91: 0 | I91: 1 | J91: 0 | K91: 0 | L91: 0 | M91: 0 | N91: -5455.02 | O91: =G91+H91+I91+J91+K91+L91+M91-P91 -> 1 | P91: 0
A92: 86 | B92: Churchil | C92: North AA | D92: Account Management | E92: JUL-31,2025 | F92: Migration suspense accounts | G92: 0 | H92: 0 | I92: 1 | J92: 0 | K92: 0 | L92: 0 | M92: 0 | N92: -2021.68 | O92: =G92+H92+I92+J92+K92+L92+M92-P92 -> 1 | P92: 0
A93: 87 | B93: Churchil | C93: North AA | D93: Deposit Account | F93: Dormant Account | G93: 0 | H93: 0 | I93: 0 | J93: 0 | K93: 0 | L93: 0 | M93: 0 | N93: 0 | O93: =G93+H93+I93+J93+K93+L93+M93-P93 -> 0 | P93: 0
A94: 88 | B94: Churchil | C94: North AA | D94: Card Banking | E94: AUG-31,2025 | F94: ATM cards & PIN mailers were not delivered to the respective account holders/ customers for a long period of time as presented below. | G94: 0 | H94: 223 | I94: 0 | J94: 0 | K94: 0 | L94: 0 | M94: 0 | N94: 0 | O94: =G94+H94+I94+J94+K94+L94+M94-P94 -> 223 | P94: 0
A95: 89 | B95: Churchil | C95: North AA | D95: Card Banking | E95: AUG-31,2025 | F95: ATM card(211) and PIN Mailers(223) were differ | G95: 12 | H95: 0 | I95: 0 | J95: 0 | K95: 0 | L95: 0 | M95: 0 | N95: 0 | O95: =G95+H95+I95+J95+K95+L95+M95-P95 -> 12 | P95: 0
A96: 90 | B96: Chilto | C96: North AA | D96: Cash & Cash Items | E96: 31/07/2026 | F96: Difference observed on ATM cash balance.(The physical cash count balance of ATM have shown a difference of Birr ……….. compared with the general ledger balance . ) | G96: 0 | H96: 0 | I96: 0 | J96: 0 | K96: 0 | L96: 0 | M96: 1 | N96: 4921.36 | O96: =G96+H96+I96+J96+K96+L96+M96-P96 -> 1 | P96: 0
A97: 91 | B97: Chilto | C97: North AA | D97: Account Management | E97: 31/07/2026 | F97: Inter branch T-24 R10 | G97: 0 | H97: 0 | I97: 1 | J97: 0 | K97: 0 | L97: 0 | M97: 0 | N97: 61584248 | O97: =G97+H97+I97+J97+K97+L97+M97-P97 -> 1 | P97: 0
A98: 92 | B98: Chilto | C98: North AA | D98: Account Management | E98: 31/07/2026 | F98: Catch All -Unassigned PL | G98: 0 | H98: 0 | I98: 1 | J98: 0 | K98: 0 | L98: 0 | M98: 0 | N98: 40.5 | O98: =G98+H98+I98+J98+K98+L98+M98-P98 -> 1 | P98: 0
A99: 93 | B99: Chilto | C99: North AA | D99: Account Management | E99: 31/07/2026 | F99: Migration suspense accounts | G99: 0 | H99: 0 | I99: 1 | J99: 0 | K99: 0 | L99: 0 | M99: 0 | N99: 0.06 | O99: =G99+H99+I99+J99+K99+L99+M99-P99 -> 1 | P99: 0
A100: 94 | B100: Chilto | C100: North AA | D100: Deposit Account | E100: 31/07/2026 | F100: Zero (0.00) balance Account Found at branch | G100: 0 | H100: 0 | I100: 0 | J100: 37 | K100: 0 | L100: 0 | M100: 0 | N100: 1850 | O100: =G100+H100+I100+J100+K100+L100+M100-P100 -> 37 | P100: 0
A101: 95 | B101: Chilto | C101: North AA | D101: Deposit Account | E101: 31/07/2026 | F101: Dormant accounts Found at the branch | G101: 0 | H101: 0 | I101: 0 | J101: 0 | K101: 41 | L101: 0 | M101: 0 | N101: 730077.64 | O101: =G101+H101+I101+J101+K101+L101+M101-P101 -> 40 | P101: 1
...

Sheet South
B1: NIB International Bank S.C
B2: South AA District
B3: Monthly internal Control Reports
B4: As of July 31, 2026
A5: Ser. No | B5: Branch | C5: District | D5: Operation area | E5: ATM Cases | G5: It Case | H5: Zero Balance | I5: Dormant A/C | J5: Cheque Bok Case | K5: Other cases | L5: Posting Date | M5: Types of Irregularities/problems | N5: Amount involved in Birr | O5: Status of the irregularities
D6: Operation area | E6: Mismatch | F6: Long outstanding | K6: finding NO. | M6: Finding | O6: Unrectified | P6: Rectified | Q6: Unrectified In Amount
A7: 1 | B7: Africa Avenue | C7: South AA | D7: Cash and Cash Items | K7: 1 | N7: 579734 | O7: =E7+F7+G7+H7+I7+J7+K7 -> 1
A8: 2 | B8: Africa Avenue | C8: South AA | K8: 1 | M8: CASH sorting,counting and wrapping area of the branch were not separeted | N8: 0 | O8: =E8+F8+G8+H8+I8+J8+K8 -> 1
A9: 3 | B9: Africa Avenue | C9: South AA | D9: Account Management | M9: Absence of source documents. | O9: =E9+F9+G9+H9+I9+J9+K9 -> 0
A10: 4 | B10: Africa Avenue | C10: South AA | G10: 1 | M10: Total fixed asset | N10: -4394768.3 | O10: =E10+F10+G10+H10+I10+J10+K10 -> 1
A11: 5 | B11: Africa Avenue | C11: South AA | G11: 1 | M11: Inter branch T-24 R10 | N11: -6.1324863e+08 | O11: =E11+F11+G11+H11+I11+J11+K11 -> 1
A12: 6 | B12: Africa Avenue | C12: South AA | G12: 1 | M12: Migration suspense accounts | N12: 30607.14 | O12: =E12+F12+G12+H12+I12+J12+K12 -> 1
A13: 7 | B13: Africa Avenue | C13: South AA | G13: 1 | M13: Gain on A/L Revaluation | N13: 1175664.6 | O13: =E13+F13+G13+H13+I13+J13+K13 -> 1
A14: 8 | B14: Africa Avenue | C14: South AA | M14: Abnormal Balance | O14: =E14+F14+G14+H14+I14+J14+K14 -> 0
A15: 9 | B15: Africa Avenue | C15: South AA | G15: 1 | M15: Catch All - Unassigned PL | N15: 89957.59 | O15: =E15+F15+G15+H15+I15+J15+K15 -> 1
A16: 10 | B16: Africa Avenue | C16: South AA | G16: 1 | M16: DIFRERENCE IN NON-CONTINGENT | N16: 1500 | O16: =E16+F16+G16+H16+I16+J16+K16 -> 1
A17: 11 | B17: Africa Avenue | C17: South AA | M17: Long outstanding items. | O17: =E17+F17+G17+H17+I17+J17+K17 -> 0
A18: 12 | B18: Africa Avenue | C18: south AA | K18: 1 | M18: Sundry debtors :-accr interest Govt Bond & Dep | N18: -19221.55 | O18: =E18+F18+G18+H18+I18+J18+K18 -> 1
A19: 13 | B19: Africa Avenue | C19: South AA | K19: 1 | M19: Sundry debtors :-loan balance correction expense | N19: -9108.73 | O19: =E19+F19+G19+H19+I19+J19+K19 -> 1
A20: 14 | B20: Africa Avenue | C20: South AA | K20: 1 | M20: Sundry debtors :-Receivable from Atayol Asphalt | N20: -11887832 | O20: =E20+F20+G20+H20+I20+J20+K20 -> 1
A21: 15 | B21: Africa Avenue | C21: South AA | K21: 1 | M21: Sundry creditors:- loan balance correction income | N21: 43170.66 | O21: =E21+F21+G21+H21+I21+J21+K21 -> 1
A22: 16 | B22: Africa Avenue | C22: South AA | D22: Loan and Advances | K22: 3 | M22: Loan & Advances with Arrears:-BISRATA TAFA AND ISTANBUL TEXTILE PLC | N22: 19960881 | O22: =E22+F22+G22+H22+I22+J22+K22 -> 3
A23: 17 | B23: Africa Avenue | C23: South AA | D23: Deposit Accounts | H23: 35 | M23: Zero (0.00) balance Account Found at branch | N23: 0 | O23: =E23+F23+G23+H23+I23+J23+K23 -> 35
A24: 18 | B24: Africa Avenue | C24: South AA | I24: 2770 | M24: Dormant accounts Found at the branch | N24: 8148098.6 | O24: =E24+F24+G24+H24+I24+J24+K24 -> 2770
A25: 19 | B25: Africa Avenue | C25: South AA | D25: Fixed Asset Management | K25: 1 | M25: Defective/obsolete fixed assets found at the branch:- broken chair | N25: 0 | O25: =E25+F25+G25+H25+I25+J25+K25 -> 1
A26: 20 | B26: Africa Avenue | C26: South AA | D26: Card Banking | F26: 19 | M26: ATM cards & PIN mailers were not delivered to the respective account holders/ customers for a long period of time as presented below. ATM Card = 19 PIN Mailers = 11 | N26: 0 | O26: =E26+F26+G26+H26+I26+J26+K26 -> 19
A27: 21 | B27: Africa Avenue | C27: South AA | E27: 8 | M27: Mismatch Between ATM Card & Pin Mailers ATM Card =19 PIN Mailers = 12 | N27: 0 | O27: =E27+F27+G27+H27+I27+J27+K27 -> 8
A28: 22 | B28: Africa Avenue | C28: South AA | D28: Ticket Vouching | K28: 1 | L28: 46204 | M28: Fund Transfers were made without Customer's Signature:-DECHASSA WEYESSA TOLLA/7000021046758/ TO CBE | N28: 320000 | O28: =E28+F28+G28+H28+I28+J28+K28 -> 1
A29: 23 | B29: Africa Avenue | C29: South AA | K29: 1 | L29: 46204 | M29: Fund Transfers were made without Customer's Signature:- SEKET IMPORT AND EXPORT TRADING PLC /7000113962742/ TO CBE | N29: 2999700 | O29: =E29+F29+G29+H29+I29+J29+K29 -> 1
A30: 24 | B30: Africa Avenue | C30: South AA | K30: 1 | L30: 46206 | M30: Fund Transfers were made without Customer's Signature:-R AND M BUSINESS PLC /7000002626743/ TO AWASH BANK | N30: 250000 | O30: =E30+F30+G30+H30+I30+J30+K30 -> 1
A31: 25 | B31: Africa Avenue | C31: South AA | K31: 1 | L31: 46209 | M31: Fund Transfers were made without Customer's Signature:-R AND M BUSINESS PLC /7000002626743/ TO UNITED BANK | N31: 950000 | O31: =E31+F31+G31+H31+I31+J31+K31 -> 1
A32: 26 | B32: Africa Avenue | C32: South AA | K32: 1 | L32: 46217 | M32: Fund Transfers were made without Customer's Signature:- AMIR ZINABU TESSEMA/7000102473227/ TO CBE | N32: 100000 | O32: =E32+F32+G32+H32+I32+J32+K32 -> 1
A33: 27 | B33: Africa Avenue | C33: South AA | K33: 1 | L33: 46226 | M33: Fund Transfers were made without Customer's Signature:- ABIMELEK DANIEL BEKELE/7000053780534/ TO CBE | N33: 75000 | O33: =E33+F33+G33+H33+I33+J33+K33 -> 1
A34: 28 | B34: Africa Avenue | C34: South AA | K34: 1 | L34: 46232 | M34: Fund Transfers were made without Customer's Signature:- MULUKEN MOHAMMED AHMED/7000015183409/ TO ABISSINIYA BANK | N34: 77875 | O34: =E34+F34+G34+H34+I34+J34+K34 -> 1
A35: 29 | B35: AKAKI GEBEYA | C35: South AA | D35: Cash& cash items | K35: 1 | M35: Difference observed on ATM cash balance.(The physical cash count balance of ATM have shown a difference of Birr 14,300.00 Excess compared with the general ledger balance on July31, 2026 . ) | N35: 14300 | O35: =E35+F35+G35+H35+I35+J35+K35 -> 1
A36: 30 | B36: AKAKI GEBEYA | C36: South AA | M36: Absence of source documents. | O36: =E36+F36+G36+H36+I36+J36+K36 -> 0
A37: 31 | B37: AKAKI GEBEYA | C37: South AA | D37: Account Management | G37: 1 | M37: Total fixed asset | N37: -2004355.7 | O37: =E37+F37+G37+H37+I37+J37+K37 -> 1
A38: 32 | B38: AKAKI GEBEYA | C38: South AA | G38: 1 | M38: Inter branch T-24 R10 - | N38: -12308761 | O38: =E38+F38+G38+H38+I38+J38+K38 -> 1
A39: 33 | B39: AKAKI GEBEYA | C39: South AA | G39: 1 | M39: Migration suspense accounts | N39: 349.55 | O39: =E39+F39+G39+H39+I39+J39+K39 -> 1
A40: 34 | B40: AKAKI GEBEYA | C40: South AA | G40: 1 | M40: Gain on A/L revaluation | N40: 13342.17 | O40: =E40+F40+G40+H40+I40+J40+K40 -> 1
A41: 35 | B41: AKAKI GEBEYA | C41: South AA | G41: 1 | M41: Catch all asset and liability | N41: 401.56 | O41: =E41+F41+G41+H41+I41+J41+K41 -> 1
A42: 36 | B42: AKAKI GEBEYA | C42: South AA | M42: Abnormal Balance | O42: =E42+F42+G42+H42+I42+J42+K42 -> 0
A43: 37 | B43: AKAKI GEBEYA | C43: South AA | K43: 1 | M43: Abnormal Tem loan repayment balance | N43: 3649.85 | O43: =E43+F43+G43+H43+I43+J43+K43 -> 1
A44: 38 | B44: AKAKI GEBEYA | C44: South AA | K44: 1 | M44: Undisbursed term loan | N44: -3695149.1 | O44: =E44+F44+G44+H44+I44+J44+K44 -> 1
A45: 39 | B45: AKAKI GEBEYA | C45: South AA | G45: 1 | M45: Catch All - Unassigned PL | N45: 399321.64 | O45: =E45+F45+G45+H45+I45+J45+K45 -> 1
A46: 40 | B46: AKAKI GEBEYA | C46: South AA | G46: 1 | M46: Difference in Non Contingent | N46: 15 | O46: =E46+F46+G46+H46+I46+J46+K46 -> 1
A47: 41 | B47: AKAKI GEBEYA | C47: South AA | M47: Long outstanding items. | O47: =E47+F47+G47+H47+I47+J47+K47 -> 0
A48: 42 | B48: AKAKI GEBEYA | C48: South AA | K48: 1 | M48: Sundry creditors/Cash in ATM | N48: 41199.29 | O48: =E48+F48+G48+H48+I48+J48+K48 -> 1
A49: 43 | B49: AKAKI GEBEYA | C49: South AA | K49: 1 | L49: 45958 | M49: Sundry creditors/cash in pos | N49: 4051 | O49: =E49+F49+G49+H49+I49+J49+K49 -> 1
A50: 44 | B50: AKAKI GEBEYA | C50: South AA | K50: 1 | L50: 45957 | M50: Sundry creditors/rent payable | N50: 141418.44 | O50: =E50+F50+G50+H50+I50+J50+K50 -> 1
A51: 45 | B51: AKAKI GEBEYA | C51: South AA | K51: 1 | M51: Sundry creditors/Staff loan repayment by court order | N51: 15014.79 | O51: =E51+F51+G51+H51+I51+J51+K51 -> 1
A52: 46 | B52: AKAKI GEBEYA | C52: South AA | K52: 3 | L52: 44973 | M52: Sundry creditors/suspictous acc clossed amount | N52: 714.18 | O52: =E52+F52+G52+H52+I52+J52+K52 -> 3
A53: 47 | B53: AKAKI GEBEYA | C53: South AA | D53: Loan and Advance | K53: 1 | M53: loan balance correction income | N53: 1093.34 | O53: =E53+F53+G53+H53+I53+J53+K53 -> 1
A54: 48 | B54: AKAKI GEBEYA | C54: South AA | K54: 2 | M54: Loan & Advances with Arrears | N54: 7743.08 | O54: =E54+F54+G54+H54+I54+J54+K54 -> 2
A55: 49 | B55: AKAKI GEBEYA | C55: South AA | D55: Deposit Accounts | H55: 330 | M55: Zero (0.00) balance Account Found at branch | N55: 0 | O55: =E55+F55+G55+H55+I55+J55+K55 -> 330
A56: 50 | B56: AKAKI GEBEYA | C56: South AA | I56: 6471 | M56: Dormant accounts Found at the branch | N56: 4776384.4 | O56: =E56+F56+G56+H56+I56+J56+K56 -> 6471
A57: 51 | B57: AKAKI GEBEYA | C57: South AA | D57: Fixed ASSET Management | K57: 3 | M57: Defective/obsolete fixed assets found at the branch | N57: 4586.61 | O57: =E57+F57+G57+H57+I57+J57+K57 -> 3
A58: 52 | B58: AKAKI GEBEYA | C58: South AA | D58: Card Banking | F58: 931 | M58: ATM cards & PIN mailers were not delivered to the respective account holders/ customers for a long period of time as presented belowATM Card = 931 Pin Mailers = 666 | N58: 80959.76 | O58: =E58+F58+G58+H58+I58+J58+K58 -> 931
A59: 53 | B59: AKAKI GEBEYA | C59: South AA | E59: 265 | M59: Mismatch Between ATM Card & Pin Mailers. ATM Card= 931 PIN Mailers =666 | N59: 23044.4 | O59: =E59+F59+G59+H59+I59+J59+K59 -> 265
A60: 54 | B60: Alemgena | C60: South AA | D60: Cash& cash items | K60: 1 | M60: Long-term unconsolidated POS cash advance(POS Cash advance of Birr 30,741.99 Excess left over in the General Ledger for a long time without being deposited) | N60: 30741.99 | O60: =E60+F60+G60+H60+I60+J60+K60 -> 1
A61: 55 | B61: Alemgena | C61: South AA | K61: 1 | M61: Difference observed on ATM cash balance.(The physical cash count balance of ATM have shown a difference of Birr (340,138.00) shortagecompared with the general ledger balance ) | N61: -340138 | O61: =E61+F61+G61+H61+I61+J61+K61 -> 1
A62: 56 | B62: Alemgena | C62: South AA | D62: Account Management | M62: Absence of source documents. | O62: =E62+F62+G62+H62+I62+J62+K62 -> 0
A63: 57 | B63: Alemgena | C63: South AA | G63: 1 | M63: Total fixed asset | N63: -3485381.8 | O63: =E63+F63+G63+H63+I63+J63+K63 -> 1
A64: 58 | B64: Alemgena | C64: South AA | G64: 1 | M64: Inter branch T-24 R10 | N64: -5963721.7 | O64: =E64+F64+G64+H64+I64+J64+K64 -> 1
A65: 59 | B65: Alemgena | C65: South AA | G65: 1 | M65: System Suspense AA | N65: 45.71 | O65: =E65+F65+G65+H65+I65+J65+K65 -> 1
A66: 60 | B66: Alemgena | C66: South AA | G66: 1 | M66: Migration suspense accounts | N66: 0.53 | O66: =E66+F66+G66+H66+I66+J66+K66 -> 1
A67: 61 | B67: Alemgena | C67: South AA | G67: 1 | M67: loss on A/L Revaluation | N67: -674171.48 | O67: =E67+F67+G67+H67+I67+J67+K67 -> 1
A68: 62 | B68: Alemgena | C68: South AA | M68: Abnormal Balance | O68: =E68+F68+G68+H68+I68+J68+K68 -> 0
A69: 63 | B69: Alemgena | C69: South AA | G69: 1 | M69: Catch All - Unassigned PL | N69: 348.82 | O69: =E69+F69+G69+H69+I69+J69+K69 -> 1
A70: 64 | B70: Alemgena | C70: South AA | G70: 1 | M70: Difference in Non-Contingent | N70: 181.75 | O70: =E70+F70+G70+H70+I70+J70+K70 -> 1
A71: 65 | B71: Alemgena | C71: South AA | M71: Long outstanding items. | O71: =E71+F71+G71+H71+I71+J71+K71 -> 0
A72: 66 | B72: Alemgena | C72: South AA | K72: 1 | M72: Uncleared Interbranch pymts | N72: -5000 | O72: =E72+F72+G72+H72+I72+J72+K72 -> 1
A73: 67 | B73: Alemgena | C73: South AA | K73: 1 | M73: Money Bags | N73: -4 | O73: =E73+F73+G73+H73+I73+J73+K73 -> 1
A74: 68 | B74: Alemgena | C74: South AA | K74: 1 | M74: Money Box | N74: -24 | O74: =E74+F74+G74+H74+I74+J74+K74 -> 1
A75: 69 | B75: Alemgena | C75: South AA | K75: 1 | M75: Sundry debtors (RTGS Receivable) | N75: -1500 | O75: =E75+F75+G75+H75+I75+J75+K75 -> 1
A76: 70 | B76: Alemgena | C76: South AA | K76: 1 | M76: Loan Balance CorrectionExpense | N76: -3434.74 | O76: =E76+F76+G76+H76+I76+J76+K76 -> 1
A77: 71 | B77: Alemgena | C77: South AA | K77: 3 | M77: Sundry creditors/Collected from closed account,penality and unpaid salary | N77: 18729.82 | O77: =E77+F77+G77+H77+I77+J77+K77 -> 3
A78: 72 | B78: Alemgena | C78: South AA | D78: Loan&Advance | K78: 6 | M78: Loan with arrears | N78: 3150370.8 | O78: =E78+F78+G78+H78+I78+J78+K78 -> 6
A79: 73 | B79: Alemgena | C79: South AA | D79: Deposit Accounts | M79: Irregularities in connection with deposit account openings. | O79: =E79+F79+G79+H79+I79+J79+K79 -> 0
A80: 74 | B80: Alemgena | C80: South AA | H80: 12 | M80: Zero (0.00) balance Account Found at branch | N80: 0 | O80: =E80+F80+G80+H80+I80+J80+K80 -> 12
A81: 75 | B81: Alemgena | C81: South AA | I81: 2326 | M81: Dormant accounts Found at the branch | N81: 10194623 | O81: =E81+F81+G81+H81+I81+J81+K81 -> 2326
A82: 76 | B82: Alemgena | C82: South AA | D82: Fixed Asset Management | K82: 1 | M82: Defective fixed assets NIB/ALGB/02/001 ( Note Counting Machine Heavy 8650 | N82: 30000 | O82: =E82+F82+G82+H82+I82+J82+K82 -> 1
A83: 77 | B83: Alemgena | C83: South AA | D83: Fixed Asset Management | K83: 1 | M83: Defective fixed assets NIB/ALGB/02/018 (Note Counting Machine Heavy 8650 | N83: 22766.99 | O83: =E83+F83+G83+H83+I83+J83+K83 -> 1
A84: 78 | B84: Alemgena | C84: South AA | D84: Card Banking | F84: 154 | M84: ATM cards & PIN mailers were not delivered to the respective account holders/ customers for a long period of time as presented below. ATM=81 PIN=154 | N84: 0 | O84: =E84+F84+G84+H84+I84+J84+K84 -> 154
A85: 79 | B85: Alemgena | C85: South AA | E85: 73 | M85: Mismatch Between ATM Card & Pin MailersATM=81 PIN=154 | N85: 0 | O85: =E85+F85+G85+H85+I85+J85+K85 -> 73
A86: 80 | B86: Beklobet | C86: South AA | D86: cash & cash items | K86: 1 | M86: Abnormal balances concerning physical cash difference of birr 1300.00 shortage compared with GL Balance | N86: -1300 | O86: =E86+F86+G86+H86+I86+J86+K86 -> 1
A87: 81 | B87: Beklobet | C87: South AA | K87: 1 | M87: Long-term unconsolidated POS cash advance(POS Cash advance of Birr (2,200.00) Shortage left over in the General Ledger for a long time without being deposited) | N87: -2200 | O87: =E87+F87+G87+H87+I87+J87+K87 -> 1
A88: 82 | B88: Beklobet | C88: South AA | K88: 1 | M88: Difference observed on ATM cash balance.(The physical cash count balance of ATM have shown a difference of Birr 47,366.1 Excess compared with the general ledger balance . ) | N88: 47366.1 | O88: =E88+F88+G88+H88+I88+J88+K88 -> 1
A89: 83 | B89: Beklobet | C89: South AA | M89: Absence of source documents. | O89: =E89+F89+G89+H89+I89+J89+K89 -> 0
A90: 84 | B90: Beklobet | C90: South AA | D90: Account Management | G90: 1 | M90: Total fixed asset | N90: -2289603.3 | O90: =E90+F90+G90+H90+I90+J90+K90 -> 1
A91: 85 | B91: Beklobet | C91: South AA | D91: Account Management | G91: 1 | M91: Inter branch T-24 R10 | N91: 14631751 | O91: =E91+F91+G91+H91+I91+J91+K91 -> 1
A92: 86 | B92: Beklobet | C92: South AA | D92: Account Management | G92: 1 | M92: Migration suspense accounts | N92: -281510.57 | O92: =E92+F92+G92+H92+I92+J92+K92 -> 1
A93: 87 | B93: Beklobet | C93: South AA | D93: Account Management | G93: 1 | M93: Gain on A/L Revaluation | N93: 752118.86 | O93: =E93+F93+G93+H93+I93+J93+K93 -> 1
A94: 88 | B94: Beklobet | C94: South AA | D94: Cash and Cash Items | M94: Abnormal Balance | O94: =E94+F94+G94+H94+I94+J94+K94 -> 0
A95: 89 | B95: Beklobet | C95: South AA | D95: Account Management | G95: 1 | M95: Catch All - Unassigned PL | N95: 33810.14 | O95: =E95+F95+G95+H95+I95+J95+K95 -> 1
A96: 90 | B96: Beklobet | C96: South AA | D96: Account Management | K96: 1 | M96: Undisbursed Term Loans | N96: -65 | O96: =E96+F96+G96+H96+I96+J96+K96 -> 1
A97: 91 | B97: Beklobet | C97: South AA | D97: Account Management | G97: 1 | M97: Difference in Non-Contingent | N97: 39 | O97: =E97+F97+G97+H97+I97+J97+K97 -> 1
A98: 92 | B98: Beklobet | C98: South AA | D98: Account Management | M98: Long outstanding items. | O98: =E98+F98+G98+H98+I98+J98+K98 -> 0
A99: 93 | B99: Beklobet | C99: South AA | D99: Account Management | K99: 1 | M99: Loan & Advances with Arrears | N99: 99175.06 | O99: =E99+F99+G99+H99+I99+J99+K99 -> 1 | P99: 1
A100: 94 | B100: Beklobet | C100: South AA | D100: Deposit Accounts | H100: 25 | M100: Zero (0.00) balance Account Found at branch | N100: 0 | O100: =E100+F100+G100+H100+I100+J100+K100 -> 25
...

Sheet West
A1: NIB International Bank S.C
A2: West District
A3: Detailed Monthly internal Control Reports
A4: As of -July 31,2026
A5: SN | D5: Operation area | E5: ATM | G5: It | H5: Zero Balance | I5: Inactive/Dormant | J5: Ck book stock | K5: Other Cases | L5: Posting date | M5: Types of Irregularities/problems | N5: Amount involved in Birr | O5: Status of the irregularities
E6: Mismatch | F6: Long outstanding | N6: Amount involved | O6: Unrectified | P6: Rectified | Q6: Unrectified In Amount
B7: Branch | C7: District | D7: Operation area | K7: finding NO. | M7: Finding
A8: 1 | B8: Abdi Nono | C8: West | D8: Account Management | G8: 1 | M8: Total fixed asset | N8: -2279042.3 | O8: =E8+F8+G8+H8+I8+J8+K8-P8 -> 1
A9: 2 | B9: Abdi Nono | C9: West | G9: 1 | M9: Inter branch T-24 R10 | N9: -12136111 | O9: =E9+F9+G9+H9+I9+J9+K9-P9 -> 1
A10: 3 | B10: Abdi Nono | C10: West | K10: 1 | M10: Transfer from Tulu Jemo branch on date of 23/09/2025 w/ro Birhane Mekonnen accont number 7000018128147 until uncollected loan | N10: -39309.21 | O10: =E10+F10+G10+H10+I10+J10+K10-P10 -> 1
A11: 4 | B11: Abdi Nono | C11: West | H11: 6 | M11: Zero (0.00) balance Account Found at branch | O11: =E11+F11+G11+H11+I11+J11+K11-P11 -> 6
A12: 5 | B12: Abdi Nono | C12: West | I12: 1734 | M12: Dormant accounts Found at the branch | O12: =E12+F12+G12+H12+I12+J12+K12-P12 -> 1734
A13: 6 | B13: Abdi Nono | C13: West | D13: Card Banking | F13: 90 | M13: ATM cards & PIN mailers were not delivered to the respective account holders/ customers for a long period of time as presented below.ATM 90 PIN 28 | O13: =E13+F13+G13+H13+I13+J13+K13-P13 -> 90
A14: 7 | B14: Abdi Nono | C14: West | E14: 62 | M14: Mismatch of ATM and PIN | O14: =E14+F14+G14+H14+I14+J14+K14-P14 -> 62
A15: 8 | B15: Ambo | C15: West | D15: Cash and Cash Items | K15: 1 | M15: Difference observed on ATM cash balance.(The physical cash count252,350 balance of ATM have shown a difference of Birr 1,050 compared with the general ledger balance 253,400) | N15: 1050 | O15: =E15+F15+G15+H15+I15+J15+K15-P15 -> 1
A16: 9 | B16: Ambo | C16: West | D16: Account Management | G16: 1 | M16: Total fixed asset | N16: 947228.67 | O16: =E16+F16+G16+H16+I16+J16+K16-P16 -> 1
A17: 10 | B17: Ambo | C17: West | G17: 1 | M17: Inter branch T-24 R10 | N17: 9472903.1 | O17: =E17+F17+G17+H17+I17+J17+K17-P17 -> 1
A18: 11 | B18: Ambo | C18: West | G18: 1 | M18: Migration suspense accounts | N18: -1089.24 | O18: =E18+F18+G18+H18+I18+J18+K18-P18 -> 1
A19: 12 | B19: Ambo | C19: West | D19: Loan and Advances | K19: 1 | M19: Sundry debtors (Gemechu Defar ,date 09/04/2019EX staff fraud case) | N19: 120492.56 | O19: =E19+F19+G19+H19+I19+J19+K19-P19 -> 1
A20: 13 | B20: Ambo | C20: West | K20: 1 | M20: Loan under loss category Abebe Melese EX staff Emergancy loan | N20: 40334.98 | O20: =E20+F20+G20+H20+I20+J20+K20-P20 -> 1
A21: 14 | B21: Ambo | C21: West | D21: Deposit Accounts | I21: 4887 | M21: Dormant accounts Found at the branch | N21: 1348868.6 | O21: =E21+F21+G21+H21+I21+J21+K21-P21 -> 4887
A22: 15 | B22: Ambo | C22: West | D22: Fixed Asset Management | K22: 1 | M22: managerial swivel chair 1/2 lather tag number NIB/AMBOB/01/016 | O22: =E22+F22+G22+H22+I22+J22+K22-P22 -> 1
A23: 16 | B23: Ambo | C23: West | K23: 1 | M23: Cleriical swivel chair tag nuber AMBOOB/01/018 | O23: =E23+F23+G23+H23+I23+J23+K23-P23 -> 1
A24: 17 | B24: Ambo | C24: West | D24: Card Banking | F24: 229 | M24: ATM cards & PIN mailers were not delivered to the respective account holders/ customers for a long period of time as presented below.(ATM carde 229 & PIN 119 | O24: =E24+F24+G24+H24+I24+J24+K24-P24 -> 229
A25: 18 | B25: Ambo | C25: West | D25: Card Banking | E25: 110 | M25: Mismatch of ATM and PIN | O25: =E25+F25+G25+H25+I25+J25+K25-P25 -> 110
A26: 19 | B26: Alem Bank Tro | C26: West | D26: Account Management | G26: 1 | M26: Catch all asset & liabilty | N26: 10215 | O26: =E26+F26+G26+H26+I26+J26+K26-P26 -> 1
A27: 20 | B27: Alem Bank Tro | C27: West | G27: 1 | M27: Migration suspense accounts | N27: 0.27 | O27: =E27+F27+G27+H27+I27+J27+K27-P27 -> 1
A28: 21 | B28: Alem Bank Tro | C28: West | D28: Loan and Advances | K28: 1 | M28: MUSTEFA ABDELLA SHIFA STATUS SUB ARR-DAYS 160 EX staff Emergency loan | N28: 41659.8 | O28: =E28+F28+G28+H28+I28+J28+K28-P28 -> 1
A29: 22 | B29: Alem Bank Tro | C29: West | D29: Card Banking | F29: 123 | M29: ATM cards & PIN mailers were not delivered to the respective account holders/ customers for a long period of time as presented below.ATM 123 PIN 22 | O29: =E29+F29+G29+H29+I29+J29+K29-P29 -> 123
A30: 23 | B30: Alem Bank Tro | C30: West | D30: Card Banking | E30: 101 | M30: Mismatch of ATM and PIN | O30: =E30+F30+G30+H30+I30+J30+K30-P30 -> 101
A31: 24 | B31: Addisu Mikael | C31: West | D31: Cash and Cash Items | K31: 1 | M31: Cash in teller showed on GL but the cash is not found in our vault | N31: 10.01 | O31: =E31+F31+G31+H31+I31+J31+K31-P31 -> 1
A32: 25 | B32: Addisu Mikael | C32: West | K32: 1 | M32: Difference observed on ATM cash balance.(The physical cash count 283,800 balance of ATM have shown a difference of Birr 67,631.93 compared with the general ledger balance 216,168.07) | N32: 67631.93 | O32: =E32+F32+G32+H32+I32+J32+K32-P32 -> 1
A33: 26 | B33: Addisu Mikael | C33: West | G33: 1 | M33: Total fixed asset | N33: -2761532.5 | O33: =E33+F33+G33+H33+I33+J33+K33-P33 -> 1
A34: 27 | B34: Addisu Mikael | C34: West | G34: 1 | M34: Inter branch T-24 R10 | N34: -72826784 | O34: =E34+F34+G34+H34+I34+J34+K34-P34 -> 1
A35: 28 | B35: Addisu Mikael | C35: West | G35: 1 | M35: Migration suspense accounts | N35: 20.42 | O35: =E35+F35+G35+H35+I35+J35+K35-P35 -> 1
A36: 29 | B36: Addisu Mikael | C36: West | D36: Deposit Accounts | H36: 6 | M36: Zero (0.00) balance Account Found at branch | O36: =E36+F36+G36+H36+I36+J36+K36-P36 -> 6
A37: 30 | B37: Addisu Mikael | C37: West | I37: 1069 | M37: Dormant accounts Found at the branch | O37: =E37+F37+G37+H37+I37+J37+K37-P37 -> 1069
A38: 31 | B38: Addisu Mikael | C38: West | D38: Card Banking | F38: 264 | M38: ATM cards & PIN mailers were not delivered to the respective account holders/ customers for a long period of time as presented below.(ATM card 264 & PIN 234) | O38: =E38+F38+G38+H38+I38+J38+K38-P38 -> 264
A39: 32 | B39: Addisu Mikael | C39: West | D39: Card Banking | E39: 30 | M39: Mismatch of ATM and PIN | O39: =E39+F39+G39+H39+I39+J39+K39-P39 -> 30
A40: 33 | B40: Adarash | C40: West | D40: Account Management | G40: 1 | M40: Inter branch T-24 R10 | N40: -1912138266 | O40: =E40+F40+G40+H40+I40+J40+K40-P40 -> 1
A41: 34 | B41: Adarash | C41: West | G41: 1 | M41: Migration suspense accounts | N41: -79826.61 | O41: =E41+F41+G41+H41+I41+J41+K41-P41 -> 1
A42: 35 | B42: Adarash | C42: West | G42: 1 | M42: loss on A/L Revaluation | N42: -25169572 | O42: =E42+F42+G42+H42+I42+J42+K42-P42 -> 1
A43: 36 | B43: Adarash | C43: West | K43: 1 | M43: Accrued interest on gov.t bond & dep | N43: -15840.87 | O43: =E43+F43+G43+H43+I43+J43+K43-P43 -> 1
A44: 37 | B44: Adarash | C44: West | K44: 1 | M44: loan balance correction expense | N44: -25041.42 | O44: =E44+F44+G44+H44+I44+J44+K44-P44 -> 1
A45: 38 | B45: Adarash | C45: West | D45: Loan and Advances | K45: 1 | M45: yared nibret Loss status | N45: 1018068.5 | O45: =E45+F45+G45+H45+I45+J45+K45-P45 -> 1
A46: 39 | B46: Adarash | C46: West | I46: 3227 | M46: Dormant accounts Found at the branch | O46: =E46+F46+G46+H46+I46+J46+K46-P46 -> 3227
A47: 40 | B47: Adarash | C47: West | D47: Card Banking | F47: 747 | M47: ATM cards & PIN mailers were not delivered to the respective account holders/ customers for a long period of time as presented below.ATM 747 PIN 373 | O47: =E47+F47+G47+H47+I47+J47+K47-P47 -> 747
A48: 41 | B48: Adarash | C48: West | D48: Card Banking | E48: 374 | M48: Mismatch of ATM and PIN | O48: =E48+F48+G48+H48+I48+J48+K48-P48 -> 374
A49: 42 | B49: Abinet Adebabay | C49: West | D49: Account Management | G49: 1 | M49: Total fixed asset | N49: -1838626.2 | O49: =E49+F49+G49+H49+I49+J49+K49-P49 -> 1
A50: 43 | B50: Abinet Adebabay | C50: West | G50: 1 | M50: Inter branch T-24 R10 | N50: -16666436 | O50: =E50+F50+G50+H50+I50+J50+K50-P50 -> 1
A51: 44 | B51: Abinet Adebabay | C51: West | G51: 1 | M51: Migration suspense accounts | N51: -240.09 | O51: =E51+F51+G51+H51+I51+J51+K51-P51 -> 1
A52: 45 | B52: Abinet Adebabay | C52: West | K52: 1 | M52: Loan Balance Correction Expense | N52: -12541.17 | O52: =E52+F52+G52+H52+I52+J52+K52-P52 -> 1
A53: 46 | B53: Abinet Adebabay | C53: West | D53: Deposit Accounts | I53: 1294 | M53: Dormant accounts Found at the branch | O53: =E53+F53+G53+H53+I53+J53+K53-P53 -> 1294
A54: 47 | B54: Abinet Adebabay | C54: West | D54: Card Banking | F54: 1289 | M54: ATM cards & PIN mailers were not delivered to the respective account holders/ customers for a long period of time as presented below.(ATM carde 1289 & PIN 1272 | O54: =E54+F54+G54+H54+I54+J54+K54-P54 -> 1289
A55: 48 | B55: Abinet Adebabay | C55: West | D55: Card Banking | E55: 17 | M55: Mismatch of ATM and PIN | O55: =E55+F55+G55+H55+I55+J55+K55-P55 -> 17
A56: 49 | B56: Asfa Wossen | C56: West | D56: Cash and Cash Items | K56: 1 | M56: Difference observed on ATM cash balance.(The physical cash count 177,500 balance of ATM have shown a difference of Birr 41,600 compared with the general ledger balance 219,100) | N56: 41600 | O56: =E56+F56+G56+H56+I56+J56+K56-P56 -> 1
A57: 50 | B57: Asfa Wossen | C57: West | D57: Account Management | G57: 1 | M57: Total fixed asset | N57: -2006473.2 | O57: =E57+F57+G57+H57+I57+J57+K57-P57 -> 1
A58: 51 | B58: Asfa Wossen | C58: West | G58: 1 | M58: Inter branch T-24 R10 | N58: -1.3503201e+08 | O58: =E58+F58+G58+H58+I58+J58+K58-P58 -> 1
A59: 52 | B59: Asfa Wossen | C59: West | G59: 1 | M59: Migration suspense accounts | N59: 600.68 | O59: =E59+F59+G59+H59+I59+J59+K59-P59 -> 1
A60: 53 | B60: Asfa Wossen | C60: West | G60: 1 | M60: loss on A/L Revaluation | N60: -21734777 | O60: =E60+F60+G60+H60+I60+J60+K60-P60 -> 1
A61: 54 | B61: Asfa Wossen | C61: West | H61: 8 | M61: Zero (0.00) balance Account Found at branch | O61: =E61+F61+G61+H61+I61+J61+K61-P61 -> 8
A62: 55 | B62: Asfa Wossen | C62: West | I62: 923 | M62: Dormant accounts Found at the branch | N62: 3911654.4 | O62: =E62+F62+G62+H62+I62+J62+K62-P62 -> 923
A63: 56 | B63: Asfa Wossen | C63: West | D63: Card Banking | F63: 866 | M63: ATM cards & PIN mailers were not delivered to the respective account holders/ customers for a long period of time as presented below.(ATM card 787 & PIN 866 | O63: =E63+F63+G63+H63+I63+J63+K63-P63 -> 866
A64: 57 | B64: Asfa Wossen | C64: West | D64: Card Banking | E64: 79 | M64: Mismatch of ATM and PIN | O64: =E64+F64+G64+H64+I64+J64+K64-P64 -> 79
A65: 58 | B65: Asfa Wossen | C65: West | D65: Ticket Vouching | K65: 1 | L65: 31/7/2026 | M65: TRANSFER Without signature from acc. No. 124IFW541 GIZEALEW HABTE TO 700029265408OF DENCHIZA NERI | N65: 10000 | O65: =E65+F65+G65+H65+I65+J65+K65-P65 -> 0 | P65: 1
A66: 59 | B66: Asfa Wossen | C66: West | K66: 1 | L66: 16/7/2026 | M66: CPO Without signature from acc. No. 124CUR169 THREE H-FOME TRADING PLCTO ETHIOPNA SHIPPING LINSE | N66: 85556.7 | O66: =E66+F66+G66+H66+I66+J66+K66-P66 -> 0 | P66: 1
A67: 60 | B67: Alert | C67: West | D67: Cash and Cash Items | K67: 1 | M67: Difference observed on ATM cash balance.(The physical cash count 138,900 balance of ATM have shown a difference of Birr 63,190.06 compared with the general ledger balance 75,709.94) | N67: 63190.06 | O67: =E67+F67+G67+H67+I67+J67+K67-P67 -> 1
A68: 61 | B68: Alert | C68: West | G68: 1 | M68: Total fixed asset | N68: -2438929.8 | O68: =E68+F68+G68+H68+I68+J68+K68-P68 -> 1
A69: 62 | B69: Alert | C69: West | G69: 1 | M69: Inter branch T-24 R10 | N69: -8604330.2 | O69: =E69+F69+G69+H69+I69+J69+K69-P69 -> 1
A70: 63 | B70: Alert | C70: West | G70: 1 | M70: Migration suspense accounts | N70: 47.23 | O70: =E70+F70+G70+H70+I70+J70+K70-P70 -> 1
A71: 64 | B71: Alert | C71: West | G71: 1 | M71: Catch allun assigned PL | N71: 128.5 | O71: =E71+F71+G71+H71+I71+J71+K71-P71 -> 1
A72: 65 | B72: Alert | C72: West | D72: Deposit Accounts | I72: 69 | M72: Dormant accounts Found at the branch | N72: 455010.37 | O72: =E72+F72+G72+H72+I72+J72+K72-P72 -> 69
A73: 66 | B73: Alert | C73: West | D73: Card Banking | F73: 314 | M73: ATM cards & PIN mailers were not delivered to the respective account holders/ customers for a long period of time as presented below.(ATM card 314 & PIN 85 | O73: =E73+F73+G73+H73+I73+J73+K73-P73 -> 314
A74: 67 | B74: Alert | C74: West | D74: Card Banking | E74: 229 | M74: Mismatch of ATM and PIN | O74: =E74+F74+G74+H74+I74+J74+K74-P74 -> 229
A75: 68 | B75: Anfo | C75: West | D75: Cash and Cash Items | K75: 1 | M75: Difference observed on ATM cash balance.(The physical cash count balance of ATM have shown 210,400 a difference of Birr 40,886.81 compared with the general ledger balance 169,513.19) | N75: 40886.81 | O75: =E75+F75+G75+H75+I75+J75+K75-P75 -> 1
A76: 69 | B76: Anfo | C76: West | D76: Account Management | G76: 1 | M76: Inter branch T-24 R10 | N76: -10090252 | O76: =E76+F76+G76+H76+I76+J76+K76-P76 -> 1
A77: 70 | B77: Anfo | C77: West | G77: 1 | M77: Migration suspense accounts | N77: 1969.43 | O77: =E77+F77+G77+H77+I77+J77+K77-P77 -> 1
A78: 71 | B78: Anfo | C78: West | G78: 1 | M78: Inter branch Account Legacy | N78: -299732.71 | O78: =E78+F78+G78+H78+I78+J78+K78-P78 -> 1
A79: 72 | B79: Anfo | C79: West | G79: 1 | M79: Catch All-Un assigned PL | N79: 75 | O79: =E79+F79+G79+H79+I79+J79+K79-P79 -> 1
A80: 73 | B80: Anfo | C80: West | D80: Deposit Accounts | H80: 12 | M80: Zero (0.00) balance Account Found at branch | O80: =E80+F80+G80+H80+I80+J80+K80-P80 -> 12
A81: 74 | B81: Anfo | C81: West | I81: 1192 | M81: Dormant accounts Found at the branch | O81: =E81+F81+G81+H81+I81+J81+K81-P81 -> 1192
A82: 75 | B82: Anfo | C82: West | D82: Fixed Asset Management | K82: 1 | M82: dis functioanl Fax machine Found at branch | O82: =E82+F82+G82+H82+I82+J82+K82-P82 -> 0 | P82: 1
A83: 76 | B83: Anfo | C83: West | K83: 2 | M83: dis functioanl Olympia calculators Found at branch | O83: =E83+F83+G83+H83+I83+J83+K83-P83 -> 0 | P83: 2
A84: 77 | B84: Anfo | C84: West | D84: Card Banking | F84: 350 | M84: ATM cards & PIN mailers were not delivered to the respective account holders/ customers for a long period of time as presented below.(ATM card 350 & PIN 233 | O84: =E84+F84+G84+H84+I84+J84+K84-P84 -> 350
A85: 78 | B85: Anfo | C85: West | D85: Card Banking | E85: 117 | M85: Mismatch of ATM and PIN | O85: =E85+F85+G85+H85+I85+J85+K85-P85 -> 117
A86: 79 | B86: Abinet | C86: West | D86: Cash and Cash Items | K86: 1 | M86: Difference observed on ATM cash balance 261,700.(The physical cash count balance of ATM have shown a difference of Birr 190,651 compared with the general ledger balance (-452,351.10) | N86: 190651 | O86: =E86+F86+G86+H86+I86+J86+K86-P86 -> 1
A87: 80 | B87: Abinet | C87: West | D87: Account Management | G87: 1 | M87: Inter branch T-24 R10 | N87: 6516018628 | O87: =E87+F87+G87+H87+I87+J87+K87-P87 -> 1
A88: 81 | B88: Abinet | C88: West | G88: 1 | M88: System suspense account AA | N88: 42716.87 | O88: =E88+F88+G88+H88+I88+J88+K88-P88 -> 1
A89: 82 | B89: Abinet | C89: West | G89: 1 | M89: Migration suspense accounts | N89: -60191.1 | O89: =E89+F89+G89+H89+I89+J89+K89-P89 -> 1
A90: 83 | B90: Abinet | C90: West | G90: 1 | M90: Catch All - Unassigned PL | N90: 97.9 | O90: =E90+F90+G90+H90+I90+J90+K90-P90 -> 1
A91: 84 | B91: Abinet | C91: West | K91: 1 | M91: legal case of Ato Gtahun Arefayne | N91: -19668.06 | O91: =E91+F91+G91+H91+I91+J91+K91-P91 -> 1
A92: 85 | B92: Abinet | C92: West | K92: 2 | M92: 130,853.34 intrest & 6,781.78 sales income tax collected from saving account of Tewodros Tamiru Kassadue to court case 5,145.96 blocking CK kept until further investigation | N92: 142781.08 | O92: =E92+F92+G92+H92+I92+J92+K92-P92 -> 2
A93: 86 | B93: Abinet | C93: West | K93: 1 | M93: Loan Balance CorrectionExpense | N93: -6233143.6 | O93: =E93+F93+G93+H93+I93+J93+K93-P93 -> 1
A94: 87 | B94: Abinet | C94: West | D94: Deposit Accounts | I94: 614 | M94: Dormant accounts Found at the branch | O94: =E94+F94+G94+H94+I94+J94+K94-P94 -> 614
A95: 88 | B95: Abinet | C95: West | D95: Security Management | K95: 1 | M95: The branch doesn't have female assessor | O95: =E95+F95+G95+H95+I95+J95+K95-P95 -> 1
A96: 89 | B96: Abinet | C96: West | D96: Card Banking | F96: 22 | M96: ATM cards & PIN mailers were not delivered to the respective account holders/ customers for a long period of time as presented below.(ATM card 8 & PIN 22 | O96: =E96+F96+G96+H96+I96+J96+K96-P96 -> 22
A97: 90 | B97: Abinet | C97: West | D97: Card Banking | E97: 14 | M97: Mismatch of ATM and PIN | O97: =E97+F97+G97+H97+I97+J97+K97-P97 -> 14
A98: 91 | B98: Addis Ketema | C98: West | D98: Account Management | G98: 1 | M98: Migration suspense accounts | N98: -282.17 | O98: =E98+F98+G98+H98+I98+J98+K98-P98 -> 1
A99: 92 | B99: Addis Ketema | C99: West | G99: 1 | M99: Catch all asset and liability | N99: 5 | O99: =E99+F99+G99+H99+I99+J99+K99-P99 -> 1
A100: 93 | B100: Addis Ketema | C100: West | G100: 1 | M100: Catch all Unassigned PL | N100: 0.61 | O100: =E100+F100+G100+H100+I100+J100+K100-P100 -> 1
...

Sheet Hawassa
A1: NIB International Bank S.C
A2: Hawassa District
A3: Detailed Monthly internal Control Reports
A4: As of JULY 31, 2026 | C4: as of march 31,2025
A5: SN | B5: Branch | C5: District | D5: Transaction date | E5: Operation Area | F5: Types of irregularities | G5: ATM Cases | I5: IT Case | J5: Zero balance | K5: Dormant A/c | L5: Cheque Bokk case | M5: Other Case | N5: Amount involved | O5: Status of the irregularities
G6: Mismatch | H6: Long outstanding | O6: Unrectified | P6: Rectified | Q6: Unrectified In Amount
A7: 1 | B7: Adola Woyu | C7: Hawassa | E7: Cash & Cash Item | F7: Difference observed on ATM cash balance.(The physical cash count balance of ATM have shown a difference of Birr compared with the general ledger balance . ) ATM GL - ATM THE PHYSICAL CASH --- | G7: 0 | H7: 0 | I7: 0 | J7: 0 | K7: 0 | L7: 0 | M7: 1 | N7: 21685.99 | O7: =G7+H7+I7+J7+K7+L7+M7 -> 1 | P7: 0 | Q7: 0
A8: 2 | B8: Adola Woyu | C8: Hawassa | E8: Deposit Account | F8: Dormant accounts Found at the branch | G8: 0 | H8: 0 | I8: 0 | J8: 0 | K8: 200 | L8: 0 | M8: 0 | N8: 25016.17 | O8: =G8+H8+I8+J8+K8+L8+M8 -> 200 | P8: 0 | Q8: 0
A9: 3 | B9: Adola Woyu | C9: Hawassa | E9: Ticket Vouching | F9: WITHDRAWAL done without cutomer signature | G9: 0 | H9: 0 | I9: 0 | J9: 0 | K9: 0 | L9: 0 | M9: 2 | N9: 60000 | O9: =G9+H9+I9+J9+K9+L9+M9 -> 2 | P9: 0 | Q9: 0
A10: 4 | B10: Adola Woyu | C10: Hawassa | E10: Ticket Vouching | F10: Transfer done without cutomer signature | G10: 0 | H10: 0 | I10: 0 | J10: 0 | K10: 0 | L10: 0 | M10: 3 | N10: 450000 | O10: =G10+H10+I10+J10+K10+L10+M10 -> 3 | P10: 0 | Q10: 0
A11: 5 | B11: Aleta Chuko | C11: Hawassa | E11: Deposit Account | F11: Dormant accounts Found at the branch | G11: 0 | H11: 0 | I11: 0 | J11: 0 | K11: 141 | L11: 0 | M11: 0 | N11: 70373.66 | O11: =G11+H11+I11+J11+K11+L11+M11 -> 141 | P11: 0 | Q11: 0
A12: 6 | B12: Aleta Chuko | C12: Hawassa | E12: Account Management | F12: GAIN on A/L Revaluation | G12: 0 | H12: 0 | I12: 1 | J12: 0 | K12: 0 | L12: 0 | M12: 0 | N12: 7757.41 | O12: =G12+H12+I12+J12+K12+L12+M12 -> 1 | P12: 0 | Q12: 0
A13: 7 | B13: Aleta Chuko | C13: Hawassa | E13: Account Management | F13: Catch all asset and liability | G13: 0 | H13: 0 | I13: 1 | J13: 0 | K13: 0 | L13: 0 | M13: 0 | N13: 10184.84 | O13: =G13+H13+I13+J13+K13+L13+M13 -> 1 | P13: 0 | Q13: 0
A14: 8 | B14: Aleta Chuko | C14: Hawassa | E14: Card Banking | F14: ATM cards & PIN mailers were not delivered to the respective account holders/ customers for a long period of time as presented below. | G14: 0 | H14: 736 | I14: 0 | J14: 0 | K14: 0 | L14: 0 | M14: 0 | N14: 36800 | O14: =G14+H14+I14+J14+K14+L14+M14 -> 736 | P14: 0 | Q14: 0
A15: 9 | B15: Aleta Chuko | C15: Hawassa | E15: Card Banking | F15: Mismatch Between ATM Card & Pinmailers | G15: 160 | H15: 0 | O15: =G15+H15+I15+J15+K15+L15+M15 -> 160
A16: 10 | B16: Aleta Chuko | C16: Hawassa | E16: Ticket Vouching | F16: Cash Withdrawal done without cutomer signature | G16: 0 | H16: 0 | I16: 0 | J16: 0 | K16: 0 | L16: 0 | M16: 4 | N16: 160000 | O16: =G16+H16+I16+J16+K16+L16+M16 -> 4 | P16: 0 | Q16: 0
A17: 11 | B17: Aleta Chuko | C17: Hawassa | D17: JULY 15,17,20,23,24,26,27,28,29 2026 | E17: Ticket Vouching | F17: Transfer done without cutomer signature | G17: 0 | H17: 0 | I17: 0 | J17: 0 | K17: 0 | L17: 0 | M17: 15 | N17: 1978200 | O17: =G17+H17+I17+J17+K17+L17+M17 -> 15 | P17: 0 | Q17: 0
A18: 12 | B18: Aleta Wondo | C18: Hawassa | D18: 31/07/2026 | E18: Cash & Cash Item | F18: Difference observed on ATM cash balance.(The physical cash count balance of ATM have shown a difference of Birr compared with the general ledger balance . ) ATM GL - ATM THE PHYSICAL CASH --- | G18: 0 | H18: 0 | I18: 0 | J18: 0 | K18: 0 | L18: 0 | M18: 1 | N18: 5085.48 | O18: =G18+H18+I18+J18+K18+L18+M18 -> 1 | P18: 0 | Q18: 0
A19: 13 | B19: Aleta Wondo | C19: Hawassa | E19: Account Management | F19: Inter branch T-24 R10 | G19: 0 | H19: 0 | I19: 1 | J19: 0 | K19: 0 | L19: 0 | M19: 0 | N19: 27764690 | O19: =G19+H19+I19+J19+K19+L19+M19 -> 1 | P19: 0 | Q19: 0
A20: 14 | B20: Aleta Wondo | C20: Hawassa | E20: Account Management | F20: Migration suspense accounts | G20: 0 | H20: 0 | I20: 1 | J20: 0 | K20: 0 | L20: 0 | M20: 0 | N20: 6814.44 | O20: =G20+H20+I20+J20+K20+L20+M20 -> 1 | P20: 0 | Q20: 0
A21: 15 | B21: Aleta Wondo | C21: Hawassa | E21: Loan & Advance | F21: Arrears inconnection With loan collection | G21: 0 | H21: 0 | I21: 0 | J21: 0 | K21: 0 | L21: 0 | M21: 4 | N21: 763377.31 | O21: =G21+H21+I21+J21+K21+L21+M21 -> 4 | P21: 0 | Q21: 0
A22: 16 | B22: Aleta Wondo | C22: Hawassa | E22: Deposit Account | F22: Dormant accounts Found at the branch | G22: 0 | H22: 0 | I22: 0 | J22: 0 | K22: 351 | L22: 0 | M22: 0 | N22: 1655888.1 | O22: =G22+H22+I22+J22+K22+L22+M22 -> 351 | P22: 0 | Q22: 0
A23: 17 | B23: Aleta Wondo | C23: Hawassa | E23: Account Management | F23: GAIN on A/L Revaluation | G23: 0 | H23: 0 | I23: 1 | J23: 0 | K23: 0 | L23: 0 | M23: 0 | N23: 64829.81 | O23: =G23+H23+I23+J23+K23+L23+M23 -> 1 | P23: 0 | Q23: 0
A24: 18 | B24: Aleta Wondo | C24: Hawassa | E24: Account Management | F24: Catch all asset and liability | G24: 0 | H24: 0 | I24: 1 | J24: 0 | K24: 0 | L24: 0 | M24: 0 | N24: 6824.06 | O24: =G24+H24+I24+J24+K24+L24+M24 -> 1 | P24: 0 | Q24: 0
A25: 19 | B25: Aleta Wondo | C25: Hawassa | E25: Card Banking | F25: ATM cards & PIN mailers were not delivered to the respective account holders/ customers for a long period of time as presented below. Pin 1383 card 1439 | G25: 0 | H25: 1439 | I25: 0 | J25: 0 | K25: 0 | L25: 0 | M25: 0 | N25: 71950 | O25: =G25+H25+I25+J25+K25+L25+M25 -> 1439 | P25: 0 | Q25: 0
A26: 20 | B26: Aleta Wondo | C26: Hawassa | E26: Card Banking | F26: Mismatch Between ATM Card & Pinmailers | G26: =1439-1383 -> 56 | H26: 0 | I26: 0 | J26: 0 | K26: 0 | L26: 0 | M26: 0 | N26: 0 | O26: =G26+H26+I26+J26+K26+L26+M26 -> 56
A27: 21 | B27: Aleta Wondo | C27: Hawassa | E27: Negotiable Instrument | F27: Cheque books prepared but not delivered to customers for a long period of time. | G27: 0 | H27: 0 | I27: 0 | J27: 0 | K27: 0 | L27: 1 | M27: 0 | N27: 100 | O27: =G27+H27+I27+J27+K27+L27+M27 -> 1 | P27: 0 | Q27: 0
A28: 22 | B28: Aleta Wondo | C28: Hawassa | E28: Account Management | F28: Legacy inter branch account | G28: 0 | H28: 0 | I28: 1 | J28: 0 | K28: 0 | L28: 0 | M28: 0 | N28: 379025.3 | O28: =G28+H28+I28+J28+K28+L28+M28 -> 1 | P28: 0 | Q28: 0
A29: 23 | B29: Aleta Wondo | C29: Hawassa | E29: Account Management | F29: Difference in non contigent | G29: 0 | H29: 0 | I29: 1 | J29: 0 | K29: 0 | L29: 0 | M29: 0 | N29: 21.5 | O29: =G29+H29+I29+J29+K29+L29+M29 -> 1 | P29: 0 | Q29: 0
A30: 24 | B30: Aleta Wondo | C30: Hawassa | E30: Ticket Vouching | F30: Transfer done without cutomer signature | G30: 0 | H30: 0 | I30: 0 | J30: 0 | K30: 0 | L30: 0 | M30: 3 | N30: 821000 | O30: =G30+H30+I30+J30+K30+L30+M30 -> 3 | P30: 0 | Q30: 0
A31: 25 | B31: Arba Minch | C31: Hawassa | D31: 28-2-2028 | E31: Account Management | F31: Migration suspense accounts | G31: 0 | H31: 0 | I31: 1 | J31: 0 | K31: 0 | L31: 0 | N31: 9335.29 | O31: =G31+H31+I31+J31+K31+L31+M31 -> 1 | P31: 0 | Q31: 0
A32: 26 | B32: Arba Minch | C32: Hawassa | E32: Loan & Advance | F32: Arrears inconnection with loan collection | G32: 0 | H32: 0 | J32: 0 | K32: 0 | L32: 0 | M32: 5 | N32: 1201162.6 | O32: =G32+H32+I32+J32+K32+L32+M32 -> 5 | P32: 0 | Q32: 0
A33: 27 | B33: Arba Minch | C33: Hawassa | D33: 28-2-2026 | E33: Deposit Account | F33: Zero (0.00) balance Account Found at branch | G33: 0 | H33: 0 | I33: 0 | J33: 5 | K33: 0 | L33: 0 | M33: 0 | N33: 0 | O33: =G33+H33+I33+J33+K33+L33+M33 -> 5 | P33: 0 | Q33: 0
A34: 28 | B34: Arba Minch | C34: Hawassa | D34: 28-02-2026 | E34: Card Banking | F34: ATM cards & PIN mailers were not delivered to the respective account holders/ customers for a long period of time as presented below. | G34: 0 | H34: 3109 | I34: 0 | J34: 0 | K34: 0 | L34: 0 | M34: 0 | N34: 155450 | O34: =G34+H34+I34+J34+K34+L34+M34 -> 3109 | P34: 0 | Q34: 0
A35: 29 | B35: Arba Minch | C35: Hawassa | D35: 28-2-2026 | E35: Account Management | F35: Legacy inter branch account | G35: 0 | H35: 0 | I35: 1 | J35: 0 | K35: 0 | L35: 0 | M35: 0 | N35: 674393.07 | O35: =G35+H35+I35+J35+K35+L35+M35 -> 1 | P35: 0 | Q35: 0
A36: 30 | B36: Arba Minch | C36: Hawassa | D36: 21&25&21/7/2026 | E36: Ticket Vouching | F36: Transfer done without cutomer signature | G36: 0 | H36: 0 | I36: 0 | J36: 0 | K36: 0 | L36: 0 | M36: 3 | N36: 605650 | O36: =G36+H36+I36+J36+K36+L36+M36 -> 3 | P36: 0 | Q36: 0
A37: 31 | B37: Arba Minch | C37: Hawassa | D37: 21/7/26 | E37: Ticket Vouching | F37: cash withdrawal done with out customer signature | G37: 0 | H37: 0 | I37: 0 | J37: 0 | K37: 0 | L37: 0 | M37: 1 | N37: 50000 | O37: =G37+H37+I37+J37+K37+L37+M37 -> 1 | P37: 0 | Q37: 0
A38: 32 | B38: Arba Minch | C38: Hawassa | D38: 31/07/2026 | E38: Account Management | F38: Sundry creditors:long outstanding inconnection with LMTS | G38: 0 | H38: 0 | I38: 0 | J38: 0 | K38: 0 | L38: 0 | M38: 1 | N38: 1000 | O38: =G38+H38+I38+J38+K38+L38+M38 -> 1 | P38: 0 | Q38: 0
A39: 33 | B39: Arba Minch | C39: Hawassa | D39: 46241 | E39: Cash & Cash Item | F39: Cash Shortage Report | G39: 0 | H39: 0 | I39: 0 | J39: 0 | K39: 0 | L39: 0 | M39: 1 | N39: 900 | O39: =G39+H39+I39+J39+K39+L39+M39 -> 1 | P39: 0 | Q39: 0
A40: 34 | B40: Arba Minch Gebeya | C40: Hawassa | E40: Cash & Cash Item | F40: Difference observed on ATM cash balance.(The physical cash count balance of ATM 87,800 have shown a difference of Birr 56,831.61 compared with the general ledger balance OF 30,968.39 | G40: 0 | H40: 0 | I40: 0 | J40: 0 | K40: 0 | L40: 0 | M40: 1 | N40: 56831.61 | O40: =G40+H40+I40+J40+K40+L40+M40 -> 1 | P40: 0 | Q40: 0
A41: 35 | B41: Arba Minch Gebeya | C41: Hawassa | E41: Deposit Account | F41: Zero (0.00) balance Account Found at branch | G41: 0 | H41: 0 | I41: 0 | J41: 4 | K41: 0 | L41: 0 | M41: 0 | N41: 0 | O41: =G41+H41+I41+J41+K41+L41+M41 -> 4 | P41: 0 | Q41: 0
A42: 36 | B42: Arba Minch Gebeya | C42: Hawassa | E42: Deposit Account | F42: Dormant accounts Found at the branch | G42: 0 | H42: 0 | I42: 0 | J42: 0 | K42: 348 | L42: 0 | M42: 0 | N42: 29080.88 | O42: =G42+H42+I42+J42+K42+L42+M42 -> 348 | P42: 0 | Q42: 0
A43: 37 | B43: Arba Minch Gebeya | C43: Hawassa | E43: Card Banking | F43: ATM cards & PIN mailers were not delivered to the respective account holders/ customers for a long period of time as presented below.ATM CARD 67 PIN MAILERS 61 | G43: 0 | H43: 67 | I43: 0 | J43: 0 | K43: 0 | L43: 0 | M43: 0 | N43: 3350 | O43: =G43+H43+I43+J43+K43+L43+M43 -> 67 | P43: 0 | Q43: 0
A44: 38 | B44: Arba Minch Gebeya | C44: Hawassa | E44: Card Banking | F44: Mismatch Between ATM Card & Pinmailers | G44: 6 | H44: 0 | I44: 0 | J44: 0 | K44: 0 | L44: 0 | M44: 0 | N44: 0 | O44: =G44+H44+I44+J44+K44+L44+M44 -> 6
A45: 39 | B45: Arba Minch Gebeya | C45: Hawassa | E45: Ticket Vouching | F45: Withdrawal done without cutomer signature | G45: 0 | H45: 0 | I45: 0 | J45: 0 | K45: 0 | L45: 0 | M45: 10 | N45: 227700 | O45: =G45+H45+I45+J45+K45+L45+M45 -> 10 | P45: 0 | Q45: 0
A46: 40 | B46: Arba Minch Gebeya | C46: Hawassa | E46: Ticket Vouching | F46: Transfer done without cutomer signature | G46: 0 | H46: 0 | I46: 0 | J46: 0 | K46: 0 | L46: 0 | M46: 10 | N46: 774000 | O46: =G46+H46+I46+J46+K46+L46+M46 -> 10 | P46: 0 | Q46: 0
A47: 41 | B47: Areb Sefer | C47: Hawassa | D47: 46239 | E47: Cash & Cash Item | F47: Difference observed on ATM cash balance.(The physical cash count balance of ATM have shown a difference of Birr compared with the general ledger balance . ) ATM GL - ATM THE PHYSICAL CASH --- | G47: 0 | H47: 0 | I47: 0 | J47: 0 | K47: 0 | L47: 0 | M47: 1 | N47: 12694.02 | O47: =G47+H47+I47+J47+K47+L47+M47 -> 1 | P47: 0 | Q47: 0
A48: 42 | B48: Areb Sefer | C48: Hawassa | D48: 0 | E48: Account Management | F48: Inter branch T-24 R10 | G48: 0 | H48: 0 | I48: 1 | J48: 0 | K48: 0 | L48: 0 | N48: 4223356.5 | O48: =G48+H48+I48+J48+K48+L48+M48 -> 1 | P48: 0 | Q48: 0
A49: 43 | B49: Areb Sefer | C49: Hawassa | D49: 0 | E49: Account Management | F49: Migration suspense accounts | G49: 0 | H49: 0 | I49: 1 | J49: 0 | K49: 0 | L49: 0 | N49: 27.69 | O49: =G49+H49+I49+J49+K49+L49+M49 -> 1 | P49: 0 | Q49: 0
A50: 44 | B50: Areb Sefer | C50: Hawassa | D50: 0 | E50: Deposit Account | F50: Zero (0.00) balance Account Found at branch | G50: 0 | H50: 0 | I50: 0 | J50: 4 | K50: 0 | L50: 0 | M50: 0 | N50: 0 | O50: =G50+H50+I50+J50+K50+L50+M50 -> 4 | P50: 0 | Q50: 0
A51: 45 | B51: Areb Sefer | C51: Hawassa | D51: 0 | E51: Deposit Account | F51: Dormant accounts Found at the branch | G51: 0 | H51: 0 | I51: 0 | J51: 0 | K51: 2872 | L51: 0 | M51: 0 | N51: 0 | O51: =G51+H51+I51+J51+K51+L51+M51 -> 2872 | P51: 0 | Q51: 0
A52: 46 | B52: Areb Sefer | C52: Hawassa | E52: Account Management | F52: Cpo Diffrence | G52: 0 | H52: 0 | I52: 0 | J52: 0 | K52: 0 | L52: 0 | M52: 1 | N52: 3000 | O52: =G52+H52+I52+J52+K52+L52+M52 -> 1 | P52: 0 | Q52: 0
A53: 47 | B53: Areb Sefer | C53: Hawassa | E53: Ticket Vouching | F53: Transfer done without cutomer signature | G53: 0 | H53: 0 | I53: 0 | J53: 0 | K53: 0 | L53: 0 | M53: 7 | N53: 3865000 | O53: =G53+H53+I53+J53+K53+L53+M53 -> 7 | P53: 0 | Q53: 0
A54: 48 | B54: Arsi Negele | C54: Hawassa | D54: 31/07/2026 | E54: Cash & Cash Item | F54: Difference observed on ATM cash balance.(The physical cash count balance of ATM have shown a difference of Birr compared with the general ledger balance . ) ATM GL - ATM THE PHYSICAL CASH --- | G54: 0 | H54: 0 | I54: 0 | J54: 0 | K54: 0 | L54: 0 | M54: 1 | N54: 20950 | O54: =G54+H54+I54+J54+K54+L54+M54 -> 1 | P54: 0 | Q54: 0
A55: 49 | B55: Arsi Negele | C55: Hawassa | D55: 44866 | E55: Account Management | F55: Inter branch T-24 R10 | G55: 0 | H55: 0 | I55: 1 | J55: 0 | K55: 0 | L55: 0 | M55: 0 | N55: -19601206 | O55: =G55+H55+I55+J55+K55+L55+M55 -> 1 | P55: 0 | Q55: 0
A56: 50 | B56: Arsi Negele | C56: Hawassa | D56: 44866 | E56: Account Management | F56: Migration suspense accounts | G56: 0 | H56: 0 | I56: 1 | J56: 0 | K56: 0 | L56: 0 | M56: 0 | N56: 0.96 | O56: =G56+H56+I56+J56+K56+L56+M56 -> 1 | P56: 0 | Q56: 0
A57: 51 | B57: Arsi Negele | C57: Hawassa | D57: 31/07/2026 | E57: Deposit Account | F57: Dormant accounts Found at the branch | G57: 0 | H57: 0 | I57: 0 | J57: 0 | K57: 178 | L57: 0 | M57: 0 | N57: 78377.97 | O57: =G57+H57+I57+J57+K57+L57+M57 -> 178 | P57: 0 | Q57: 0
A58: 52 | B58: Arsi Negele | C58: Hawassa | D58: 31/07/2026 | E58: Account Management | F58: Catch all asset and liability | G58: 0 | H58: 0 | I58: 1 | J58: 0 | K58: 0 | L58: 0 | M58: 0 | N58: 33.5 | O58: =G58+H58+I58+J58+K58+L58+M58 -> 1 | P58: 0 | Q58: 0
A59: 53 | B59: Arsi Negele | C59: Hawassa | D59: 31/07/2026 | E59: Card Banking | F59: ATM cards & PIN mailers were not delivered to the respective account holders/ customers for a long period of time as presented below. | H59: 1647 | I59: 0 | J59: 0 | K59: 0 | L59: 0 | M59: 0 | N59: 82350 | O59: =G59+H59+I59+J59+K59+L59+M59 -> 1647 | P59: 0 | Q59: 0
A60: 54 | B60: Arsi Negele | C60: Hawassa | E60: Card Banking | F60: Mismatch Between ATM Card & Pinmailers | G60: 17 | H60: 0 | I60: 0 | J60: 0 | K60: 0 | O60: =G60+H60+I60+J60+K60+L60+M60 -> 17
A61: 55 | B61: Awasho | C61: Hawassa | E61: Account Management | F61: Inter branch T-24 R10 | G61: 0 | H61: 0 | I61: 1 | J61: 0 | K61: 0 | L61: 0 | M61: 0 | N61: 9329623.2 | O61: =G61+H61+I61+J61+K61+L61+M61 -> 1 | P61: 0 | Q61: 0
A62: 56 | B62: Awasho | C62: Hawassa | E62: Account Management | F62: Migration suspense accounts | G62: 0 | H62: 0 | I62: 1 | J62: 0 | K62: 0 | L62: 0 | M62: 0 | N62: 1618.45 | O62: =G62+H62+I62+J62+K62+L62+M62 -> 1 | P62: 0 | Q62: 0
A63: 57 | B63: Awasho | C63: Hawassa | E63: Account Management | F63: Catch all asset and liability | G63: 0 | H63: 0 | I63: 1 | J63: 0 | K63: 0 | L63: 0 | M63: 0 | N63: 122.32 | O63: =G63+H63+I63+J63+K63+L63+M63 -> 1 | P63: 0 | Q63: 0
A64: 58 | B64: Awasho | C64: Hawassa | E64: Ticket Vouching | F64: Transfer done without cutomer signature | G64: 0 | H64: 0 | I64: 0 | J64: 0 | K64: 0 | L64: 0 | M64: 6 | N64: 760000 | O64: =G64+H64+I64+J64+K64+L64+M64 -> 6 | P64: 0 | Q64: 0
A65: 59 | B65: Birbir | C65: Hawassa | D65: 44291 | E65: Account Management | F65: Inter branch T-24 R10 | G65: 0 | H65: 0 | I65: 1 | J65: 0 | K65: 0 | L65: 0 | M65: 0 | N65: 3045920.7 | O65: =G65+H65+I65+J65+K65+L65+M65 -> 1 | P65: 0 | Q65: 0
A66: 60 | B66: Birbir | C66: Hawassa | D66: 28/06/26 | E66: Deposit Account | F66: Zero (0.00) balance Account Found at branch | G66: 0 | H66: 0 | I66: 0 | J66: 4 | K66: 0 | L66: 0 | M66: 0 | N66: 200 | O66: =G66+H66+I66+J66+K66+L66+M66 -> 4 | P66: 0 | Q66: 0
A67: 61 | B67: Birbir | C67: Hawassa | E67: Deposit Account | F67: Dormant accounts Found at the branch | G67: 0 | H67: 0 | I67: 0 | J67: 0 | K67: 110 | L67: 0 | M67: 0 | N67: 0 | O67: =G67+H67+I67+J67+K67+L67+M67 -> 110 | P67: 0 | Q67: 0
A68: 62 | B68: Birbir | C68: Hawassa | E68: Card Banking | F68: ATM cards & PIN mailers were not delivered to the respective account holders/ customers for a long period of time as presented below. 542 &517 ATM cards & PIN mailers were not delivered to the respective account holders respectibily | H68: 542 | I68: 0 | J68: 0 | K68: 0 | L68: 0 | M68: 0 | N68: 27100 | O68: =G68+H68+I68+J68+K68+L68+M68 -> 542 | P68: 0 | Q68: 0
A69: 63 | B69: Birbir | C69: Hawassa | E69: Card Banking | F69: Mismatch Between ATM Card & Pinmailers | G69: 25 | H69: 0 | I69: 0 | J69: 0 | K69: 0 | O69: =G69+H69+I69+J69+K69+L69+M69 -> 25
A70: 64 | B70: Birbir | C70: Hawassa | E70: Deposit Account | F70: Approved account image cannot loaded to T24 system . | G70: 0 | H70: 0 | I70: 0 | J70: 0 | K70: 0 | L70: 0 | M70: 25 | N70: 2500 | O70: =G70+H70+I70+J70+K70+L70+M70 -> 25 | P70: 0 | Q70: 0
A71: 65 | B71: Birbir | C71: Hawassa | D71: 26/6/26 | E71: Ticket Vouching | F71: Transfer done without cutomer signature | G71: 0 | H71: 0 | I71: 0 | J71: 0 | K71: 0 | L71: 0 | M71: 2 | N71: 160000 | O71: =G71+H71+I71+J71+K71+L71+M71 -> 2 | P71: 0 | Q71: 0
A72: 66 | B72: Bore | C72: Hawassa | E72: Account Management | F72: Inter branch T-24 R10 | G72: 0 | H72: 0 | I72: 1 | J72: 0 | K72: 0 | L72: 0 | M72: 0 | N72: 6831269.6 | O72: =G72+H72+I72+J72+K72+L72+M72 -> 1 | P72: 0 | Q72: 0
A73: 67 | B73: Bore | C73: Hawassa | E73: Account Management | F73: Migration suspense accounts | G73: 0 | H73: 0 | I73: 1 | J73: 0 | K73: 0 | L73: 0 | M73: 0 | N73: 2.27 | O73: =G73+H73+I73+J73+K73+L73+M73 -> 1 | P73: 0 | Q73: 0
A74: 68 | B74: Bore | C74: Hawassa | E74: Deposit Account | F74: Dormant accounts Found at the branch | G74: 0 | H74: 0 | I74: 0 | J74: 0 | K74: 179 | L74: 0 | M74: 0 | N74: 32273.8 | O74: =G74+H74+I74+J74+K74+L74+M74 -> 179 | P74: 0 | Q74: 0
A75: 69 | B75: Bore | C75: Hawassa | E75: Account Management | F75: Catch all asset and liability | G75: 0 | H75: 0 | I75: 1 | J75: 0 | K75: 0 | L75: 0 | M75: 0 | N75: 23.87 | O75: =G75+H75+I75+J75+K75+L75+M75 -> 1 | P75: 0 | Q75: 0
A76: 70 | B76: Bore | C76: Hawassa | E76: Card Banking | F76: ATM cards & PIN mailers were not delivered to the respective account holders/ customers for a long period of time as presented below. 1011-2 =1009 (1009*50) | H76: 1001 | I76: 0 | J76: 0 | K76: 0 | L76: 0 | M76: 0 | N76: 50050 | O76: =G76+H76+I76+J76+K76+L76+M76 -> 1001 | P76: 0 | Q76: 0
A77: 71 | B77: Bore | C77: Hawassa | E77: Card Banking | F77: Mismatch Between ATM Card & Pinmailers | G77: 41 | H77: 0 | I77: 0 | J77: 0 | K77: 0 | L77: 0 | M77: 0 | N77: 0 | O77: =G77+H77+I77+J77+K77+L77+M77 -> 41
A78: 72 | B78: Bule Hora | C78: Hawassa | D78: 46174 | E78: Cash & Cash Item | F78: Difference observed on ATM cash balance.(The physical cash count balance of ATM have shown a difference of Birr 160,742.19 compared with the general ledger balance . ) ATM GL - 626,857.81 ATM THE PHYSICAL CASH 787,600 | G78: 0 | H78: 0 | I78: 0 | J78: 0 | K78: 0 | L78: 0 | M78: 1 | N78: 160742.2 | O78: =G78+H78+I78+J78+K78+L78+M78 -> 1 | P78: 0 | Q78: 0
A79: 73 | B79: Bule Hora | C79: Hawassa | E79: Account Management | F79: Inter branch T-24 R10 | G79: 0 | H79: 0 | I79: 1 | J79: 0 | K79: 0 | L79: 0 | M79: 0 | N79: 7050605 | O79: =G79+H79+I79+J79+K79+L79+M79 -> 1 | P79: 0 | Q79: 0
A80: 74 | B80: Bule Hora | C80: Hawassa | E80: Account Management | F80: Migration suspense accounts | G80: 0 | H80: 0 | I80: 1 | J80: 0 | K80: 0 | L80: 0 | M80: 0 | N80: 0.24 | O80: =G80+H80+I80+J80+K80+L80+M80 -> 1 | P80: 0 | Q80: 0
A81: 75 | B81: Bule Hora | C81: Hawassa | E81: Account Management | F81: DIFRERENCE IN NON-CONTINGENT | G81: 0 | H81: 0 | I81: 1 | J81: 0 | K81: 0 | L81: 0 | M81: 0 | N81: 161.5 | O81: =G81+H81+I81+J81+K81+L81+M81 -> 1 | P81: 0 | Q81: 0
A82: 76 | B82: Bule Hora | C82: Hawassa | E82: Deposit Account | F82: Dormant accounts Found at the branch | G82: 0 | H82: 0 | I82: 0 | J82: 0 | K82: 9044 | L82: 0 | M82: 0 | N82: 3147423.1 | O82: =G82+H82+I82+J82+K82+L82+M82 -> 9044 | P82: 0 | Q82: 0
A83: 77 | B83: Bule Hora | C83: Hawassa | E83: Account Management | F83: Catch all asset and liability | G83: 0 | H83: 0 | I83: 1 | J83: 0 | K83: 0 | L83: 0 | M83: 0 | N83: 157.54 | O83: =G83+H83+I83+J83+K83+L83+M83 -> 1 | P83: 0 | Q83: 0
A84: 78 | B84: Bule Hora | C84: Hawassa | E84: Card Banking | F84: ATM cards & PIN mailers were not delivered to the respective account holders/ customers for a long period of time as presented below. | G84: 0 | H84: 1191 | I84: 0 | J84: 0 | K84: 0 | L84: 0 | M84: 0 | N84: 59550 | O84: =G84+H84+I84+J84+K84+L84+M84 -> 1191 | P84: 0 | Q84: 0
A85: 79 | B85: Bole Hora | C85: Hawassa | E85: Card Banking | F85: Mismatch Between ATM Card & Pinmailers | G85: 70 | H85: 0 | I85: 0 | J85: 0 | K85: 0 | L85: 0 | M85: 0 | N85: 0 | O85: =G85+H85+I85+J85+K85+L85+M85 -> 70
A86: 80 | B86: Daye | C86: Hawassa | E86: Cash & Cash Item | F86: Difference observed on ATM cash balance.(The physical cash count balance of ATM have shown a difference of Birr compared with the general ledger balance . ) ATM GL - ATM THE PHYSICAL CASH --- | G86: 0 | H86: 0 | I86: 0 | J86: 0 | K86: 0 | L86: 0 | M86: 1 | N86: 40215.54 | O86: =G86+H86+I86+J86+K86+L86+M86 -> 1 | P86: 0 | Q86: 0
A87: 81 | B87: Daye | C87: Hawassa | E87: Account Management | F87: System suspense account AC | G87: 0 | H87: 0 | I87: 1 | J87: 0 | K87: 0 | L87: 0 | M87: 0 | N87: 0.01 | O87: =G87+H87+I87+J87+K87+L87+M87 -> 1 | P87: 0 | Q87: 0
A88: 82 | B88: Daye | C88: Hawassa | E88: Deposit Account | F88: Dormant accounts Found at the branch | G88: 0 | H88: 0 | I88: 0 | J88: 0 | K88: 142 | L88: 0 | M88: 0 | N88: 29719.96 | O88: =G88+H88+I88+J88+K88+L88+M88 -> 142 | P88: 0 | Q88: 0
A89: 83 | B89: Daye | C89: Hawassa | E89: Card Banking | F89: ATM cards were not delivered to the respective account holders/ customers for a long period of time as presented below. | G89: 0 | H89: 822 | I89: 0 | J89: 0 | K89: 0 | L89: 0 | M89: 0 | N89: 41100 | O89: =G89+H89+I89+J89+K89+L89+M89 -> 822 | P89: 0 | Q89: 0
A90: 84 | B90: Daye | C90: Hawassa | E90: Card Banking | F90: Mismatch Between ATM Card & Pinmailers | G90: 46 | H90: 0 | I90: 0 | J90: 0 | K90: 0 | L90: 0 | M90: 0 | N90: 0 | O90: =G90+H90+I90+J90+K90+L90+M90 -> 46 | P90: 0 | Q90: 0
A91: 85 | B91: Daye | C91: Hawassa | D91: 22/07/2026 | E91: Ticket Vouching | F91: Cash withdrawal done without customer signature & stamp | G91: 0 | H91: 0 | I91: 0 | J91: 0 | K91: 0 | L91: 0 | M91: 1 | N91: 50000 | O91: =G91+H91+I91+J91+K91+L91+M91 -> 1 | P91: 0 | Q91: 0
A92: 86 | B92: Daye | C92: Hawassa | D92: 17/07/2026 21/07/2026 24/072026 30/07/2026 | E92: Ticket Vouching | F92: Transfer done without cutomer signature | G92: 0 | H92: 0 | I92: 0 | J92: 0 | K92: 0 | L92: 0 | M92: 4 | N92: 915000 | O92: =G92+H92+I92+J92+K92+L92+M92 -> 4 | P92: 0 | Q92: 0
A93: 87 | B93: Dilla | C93: Hawassa | E93: Cash & Cash Item | F93: Difference observed on ATM cash balance.(The physical cash count balance of ATM have shown a difference of Birr compared with the general ledger balance. ) ATM GL - ATM THE PHYSICAL CASH | G93: 0 | H93: 0 | I93: 0 | J93: 0 | K93: 0 | L93: 0 | M93: 1 | N93: 210854.92 | O93: =G93+H93+I93+J93+K93+L93+M93 -> 1 | P93: 0 | Q93: 0
A94: 88 | B94: Dilla | C94: Hawassa | E94: Account Management | F94: Inter branch T-24 R10 | G94: 0 | H94: 0 | I94: 1 | J94: 0 | K94: 0 | L94: 0 | M94: 0 | N94: 5138080 | O94: =G94+H94+I94+J94+K94+L94+M94 -> 1 | P94: 0 | Q94: 0
A95: 89 | B95: Dilla | C95: Hawassa | E95: Deposit Account | F95: Dormant accounts Found at the branch | G95: 0 | H95: 0 | I95: 0 | J95: 0 | K95: 544 | L95: 0 | M95: 0 | N95: 449163.84 | O95: =G95+H95+I95+J95+K95+L95+M95 -> 544 | P95: 0 | Q95: 0
A96: 90 | B96: Dilla | C96: Hawassa | E96: Card Banking | F96: ATM cards & PIN mailers were not delivered to the respective account holders/ customers for a long period of time as presented below. | G96: 0 | H96: 1208 | I96: 0 | J96: 0 | K96: 0 | L96: 0 | M96: 0 | N96: 60400 | O96: =G96+H96+I96+J96+K96+L96+M96 -> 1208 | P96: 0 | Q96: 0
A97: 91 | B97: Dilla | C97: Hawassa | E97: Card Banking | F97: Mismatch Between ATM Card & Pinmailers | G97: 178 | H97: 0 | I97: 0 | J97: 0 | K97: 0 | L97: 0 | M97: 0 | N97: 0 | O97: =G97+H97+I97+J97+K97+L97+M97 -> 178
A98: 92 | B98: Dilla | C98: Hawassa | E98: Ticket Vouching | F98: Transfer done without cutomer signature | G98: 0 | H98: 0 | I98: 0 | J98: 0 | K98: 0 | L98: 0 | M98: 15 | N98: 1878518 | O98: =G98+H98+I98+J98+K98+L98+M98 -> 15 | P98: 0 | Q98: 0
A99: 93 | B99: Dilla | C99: Hawassa | E99: Ticket Vouching | F99: Withdrawal without Customer signature | G99: 0 | H99: 0 | I99: 0 | J99: 0 | K99: 0 | L99: 0 | M99: 6 | N99: 193000 | O99: =G99+H99+I99+J99+K99+L99+M99 -> 6 | P99: 0 | Q99: 0
A100: 94 | B100: Dilla Edget | C100: Hawassa | E100: Account Management | F100: Inter branch T-24 R10 | G100: 0 | H100: 0 | I100: 1 | J100: 0 | K100: 0 | L100: 0 | M100: 0 | N100: 23467130 | O100: =G100+H100+I100+J100+K100+L100+M100 -> 1 | P100: 0 | Q100: 0
...

Sheet B-Dar
A1: NIB International Bank S.C
A2: Name of Departments/NAAD
A3: Detailed Monthly internal Control Reports
A4: As of JULY 31 2026 month report | C4: as of march 31,2025
A5: SN | B5: Branch | C5: District | E5: Types of irregularities | F5: ATM Cases | L5: Other Case No. | M5: Amount involved | N5: Status of the irregularities
D6: Transaction Date | F6: Mismatch | G6: Long O/S | H6: IT Cases | I6: Zero Bal. | J6: Dormant A/C | K6: CK Book stock | N6: Unrectified | O6: Rectified | P6: Unrectified In Amount
A7: 1 | B7: Debre Tabor | C7: Bahir Dar | D7: Various Date | E7: Dormant accounts found at the branch | F7: 0 | G7: 0 | H7: 0 | I7: 0 | J7: 122 | K7: 0 | L7: 0 | M7: 26996.52 | N7: =F7+G7+H7+I7+J7+K7+L7-O7 -> 0 | O7: 122 | P7: 122
A8: 2 | B8: Debre Tabor | C8: Bahir Dar | D8: Various Date | E8: Absence of FCY License | F8: 0 | G8: 0 | H8: 0 | I8: 0 | J8: 0 | K8: 0 | L8: 1 | M8: 0 | N8: =F8+G8+H8+I8+J8+K8+L8-O8 -> 1
A9: 3 | B9: Debre Tabor | C9: Bahir Dar | D9: Various Date | E9: Defective/Obsolete fixed assets found at the branch (note counter machine & casio calculator) | F9: 0 | G9: 0 | H9: 0 | I9: 0 | J9: 0 | K9: 0 | L9: 4 | M9: 60383.93 | N9: =F9+G9+H9+I9+J9+K9+L9-O9 -> 4
A10: 4 | B10: Debre Tabor | C10: Bahir Dar | D10: Various Date | E10: ATM cards were not delivered to the respective account holders for a long period of time | F10: 0 | G10: 85 | H10: 0 | I10: 0 | J10: 0 | K10: 0 | L10: 0 | M10: 7391.6 | N10: =F10+G10+H10+I10+J10+K10+L10-O10 -> 85
A11: 5 | B11: Debre Tabor | C11: Bahir Dar | D11: Various Date | E11: ATM cards and PIN Difference | F11: 54 | G11: 0 | H11: 0 | I11: 0 | J11: 0 | K11: 0 | L11: 0 | M11: 0 | N11: =F11+G11+H11+I11+J11+K11+L11-O11 -> 54
A12: 6 | B12: Nifas Mewucha | C12: Bahir Dar | D12: branch oppening | E12: Absence of FCY license | F12: 0 | G12: 0 | H12: 0 | I12: 0 | J12: 0 | K12: 0 | L12: 1 | M12: 0 | N12: =F12+G12+H12+I12+J12+K12+L12-O12 -> 1
A13: 7 | B13: Nifas Mewucha | C13: Bahir Dar | D13: Dormat account | E13: Dormant accounts Found at the branch | F13: 0 | G13: 0 | H13: 0 | I13: 0 | J13: 31 | K13: 0 | L13: 0 | M13: 4769.01 | N13: =F13+G13+H13+I13+J13+K13+L13-O13 -> 0 | O13: 31 | P13: 31
A14: 8 | B14: Nifas Mewucha | C14: Bahir Dar | D14: various | E14: ATM cards & PIN mailers were not delivered to the respective account holders/ customers for a long period of time as presented below. | F14: 0 | G14: 11 | H14: 0 | I14: 0 | J14: 0 | K14: 0 | L14: 0 | M14: 1100 | N14: =F14+G14+H14+I14+J14+K14+L14-O14 -> 11
A15: 9 | B15: Nifas Mewucha | C15: Bahir Dar | D15: various | E15: ATM cards and pin Difernce | F15: 4 | G15: 0 | H15: 0 | I15: 0 | J15: 0 | K15: 0 | L15: 0 | M15: 0 | N15: =F15+G15+H15+I15+J15+K15+L15-O15 -> 4
A16: 10 | B16: Nifas Mewucha | C16: Bahir Dar | D16: various | E16: our branch security guards do not have any weaponse to protect the branch from attack | F16: 0 | G16: 0 | H16: 0 | I16: 0 | J16: 0 | K16: 0 | L16: 1 | M16: 0 | N16: =F16+G16+H16+I16+J16+K16+L16-O16 -> 1
A17: 11 | B17: Humera | C17: Bahir Dar | D17: migration date | E17: Inter branch T-24 R10 | F17: 0 | G17: 0 | H17: 1 | I17: 0 | J17: 0 | K17: 0 | L17: 0 | M17: 2.8784275e+08 | N17: =F17+G17+H17+I17+J17+K17+L17-O17 -> 1
A18: 12 | B18: Humera | C18: Bahir Dar | D18: migration date | E18: System suspense account AC | F18: 0 | G18: 0 | H18: 1 | I18: 0 | J18: 0 | K18: 0 | L18: 0 | M18: 69 | N18: =F18+G18+H18+I18+J18+K18+L18-O18 -> 0 | O18: 1 | P18: 1
A19: 13 | B19: Humera | C19: Bahir Dar | D19: migration date | E19: Migration suspense accounts | F19: 0 | G19: 0 | H19: 1 | I19: 0 | J19: 0 | K19: 0 | L19: 0 | M19: 79 | N19: =F19+G19+H19+I19+J19+K19+L19-O19 -> 1
A20: 14 | B20: Humera | C20: Bahir Dar | D20: Varied dates | E20: Dormant accounts Found at the branch | F20: 0 | G20: 0 | H20: 0 | I20: 0 | J20: 1886 | K20: 0 | L20: 0 | M20: 2510017.2 | N20: =F20+G20+H20+I20+J20+K20+L20-O20 -> 1673 | O20: 213 | P20: 213
A21: 15 | B21: Humera | C21: Bahir Dar | D21: Dec/27/2025 | E21: Temporarey loan Repaiment | F21: 0 | G21: 0 | H21: 0 | I21: 0 | J21: 0 | K21: 0 | L21: 12 | M21: -87790.2 | N21: =F21+G21+H21+I21+J21+K21+L21-O21 -> 12
A22: 16 | B22: Humera | C22: Bahir Dar | D22: various date | E22: Sundry debtors /Accrued interest receivable from different customers (19,218,683.87) 17 cases /Insurace renew recivabel from different customers (37,678.06)28 cases | F22: 0 | G22: 0 | H22: 0 | I22: 0 | J22: 0 | K22: 0 | L22: 46 | M22: -19256362 | N22: =F22+G22+H22+I22+J22+K22+L22-O22 -> 46
A23: 17 | B23: Ghion | C23: Bahir Dar | D23: 31/07/2026 | E23: Unauthorised Accounts Found at Branch with any roason. | F23: 0 | G23: 0 | H23: =SUM(I39) -> 0 | I23: =SUM(J39) -> 0 | J23: =SUM(K39) -> 0 | K23: =SUM(L39) -> 0 | L23: 11 | M23: 850 | N23: =F23+G23+H23+I23+J23+K23+L23-O23 -> 0 | O23: 11 | P23: 11
A24: 18 | B24: Ghion | C24: Bahir Dar | D24: 31/07/2026 | E24: Un delivered Advanced(04741-04760),bid bond(12081-12100).preformance(05101-05120) &letter of guarantee(02841-02860) at branch with each of 1 pad(20 in number) (letter written by branch to district for maney times to deliver it but voulanter to recive at district Office). | F24: 0 | G24: 0 | H24: 0 | I24: 0 | J24: 0 | K24: 0 | L24: 60 | M24: 6600 | N24: =F24+G24+H24+I24+J24+K24+L24-O24 -> 60
A25: 19 | B25: Ghion | C25: Bahir Dar | D25: 1/1/2023-28/02/2026 | E25: Difference observed on ATM cash balance.(The physical cash count balance of ATM have shown ashortage of Birr 400 From The screen. ) | F25: 0 | G25: 0 | H25: 0 | I25: 0 | J25: 0 | K25: 0 | L25: 1 | M25: 400 | N25: =F25+G25+H25+I25+J25+K25+L25-O25 -> 0 | O25: 1 | P25: 1
A26: 20 | B26: Ghion | C26: Bahir Dar | D26: 31/07/2026 | E26: PassBook Registered Is not Handled on safe way ,Erased &deliver without filling of passbook number,Date &delivered by . | F26: 0 | G26: 0 | H26: 0 | I26: 0 | J26: 0 | K26: 0 | L26: 1 | N26: =F26+G26+H26+I26+J26+K26+L26-O26 -> 0 | O26: 1 | P26: 1
A27: 21 | B27: Ghion | C27: Bahir Dar | D27: 1/1/2023-28/02/2026 | E27: Difference observed on ATM cash balance.(The physical cash count balance of ATM have shown a difference of Birr over compared with the general ledger balance . ) due to non dispute apperance of other bank customer ATM user. | F27: 0 | G27: 0 | H27: 1 | I27: 0 | J27: 0 | K27: 0 | L27: 0 | M27: 31000 | N27: =F27+G27+H27+I27+J27+K27+L27-O27 -> 1
A28: 22 | B28: Ghion | C28: Bahir Dar | D28: 44851 | E28: LONG UNSETTLED CLAIM FOR PERDIEM &TRANSPORTATION EXPENSE OF BAHIR DAR DISTRICT DIRECTOR ATO HAIMANOT YIRGA (Claim unsettled by H.O Due To orginal file not found) | F28: 0 | G28: 0 | H28: 0 | I28: 0 | J28: 0 | K28: 0 | L28: 1 | M28: 18215.25 | N28: =F28+G28+H28+I28+J28+K28+L28-O28 -> 1
A29: 23 | B29: Ghion | C29: Bahir Dar | D29: 45658 | E29: Long outstanding CPO ISSUED FOR MSA YENIGID SIRAWOCH BUSSINES GROUP 1247395 | F29: 0 | G29: 0 | H29: 0 | I29: 0 | J29: 0 | K29: 0 | L29: 1 | M29: 5000 | N29: =F29+G29+H29+I29+J29+K29+L29-O29 -> 0 | O29: 1 | P29: 1
A30: 24 | B30: Ghion | C30: Bahir Dar | D30: 25/05/2023 | E30: Long outstanding ATM Cards&PIN (331)With charge not collected Found at Branch . | F30: 0 | G30: 334 | H30: 0 | I30: 0 | J30: 0 | K30: 0 | L30: 0 | M30: 33400 | N30: =F30+G30+H30+I30+J30+K30+L30-O30 -> 334
A31: 25 | B31: Ghion | C31: Bahir Dar | D31: 30/05/2026 | E31: Irregularities in connection with branches cash areas E.g. unsafe conditions (broken keys at window KG and Wooden lockers) and still too many tickets and and other files on voult areas. | F31: 0 | G31: 0 | H31: 0 | I31: 0 | J31: 0 | K31: 0 | L31: 3 | M31: 0 | N31: =F31+G31+H31+I31+J31+K31+L31-O31 -> 0 | O31: 3 | P31: 3
A32: 26 | B32: Ghion | C32: Bahir Dar | D32: 01/05/2026-30/06/2026 | E32: Irregularities observed on transactions tickets like: - without customer signature FT *ZEMENU GENET(POA:DESTA) 7000109130578 485,000.00 ON 4/4/2026 TO 7000110000745(SAHILEMIHRET) FT | F32: 0 | G32: 0 | H32: 0 | I32: 0 | J32: 0 | K32: 0 | L32: 1 | M32: 485000 | N32: =F32+G32+H32+I32+J32+K32+L32-O32 -> 0 | O32: 1 | P32: 1
A33: 27 | B33: Ghion | C33: Bahir Dar | D33: 31/07/2026 | E33: INACTIVE ACCOUNT LIST | F33: 0 | G33: 0 | H33: 0 | I33: 0 | J33: 529 | K33: 0 | L33: 0 | M33: 142942.27 | N33: =F33+G33+H33+I33+J33+K33+L33-O33 -> 462 | O33: 67 | P33: 67
A34: 28 | B34: Ghion | C34: Bahir Dar | D34: 30/06/2026 | E34: Failure to re-estimate collaterals : *ABEBE GETNET SHIBABAW Mortgage Loan for Staff 1,837,000.00 Granted date on 03/05/2023 *HABTAMU AYENGEDA AZMERA Mortgage Loan for Staff 1,778,000.00 G/ Dated on 03/05/2023 | F34: 0 | G34: 0 | H34: 0 | I34: 0 | J34: 0 | K34: 0 | L34: 2 | M34: 3,615,000‬ | N34: =F34+G34+H34+I34+J34+K34+L34-O34 -> 2
A35: 29 | B35: Ghion | C35: Bahir Dar | D35: 03/06/2026-30/06/2026 | E35: Unable to settle claim request of last years district expense by H.O finance without sufficent reason ETB 12,496.18 OUTSTANDING EXPENSE INCURRED SALARY&ALLOWANCE DISTRICT LEGAL STAFF *ETB 16,575.49 OUTSTANDING EXPENSE INCURRED SALARY&ALLOWANCE OF RELEASED STAFF | F35: 0 | G35: 0 | H35: 0 | I35: 0 | J35: 0 | K35: 0 | L35: 2 | M35: =12496.18+16575.49 -> 29071.67 | N35: =F35+G35+H35+I35+J35+K35+L35-O35 -> 2
A36: 30 | B36: Ghion | C36: Bahir Dar | D36: 30/06/2026 | E36: Unjustified balance kept on profit and loss account(Catch All - Unassigned PL related to loan sector adjestment ) | F36: 0 | G36: 0 | H36: 0 | I36: 0 | J36: 0 | K36: 0 | L36: 1 | M36: 4398.31 | N36: =F36+G36+H36+I36+J36+K36+L36-O36 -> 0 | O36: 1 | P36: 1
A37: 31 | B37: Injibara | C37: Bahir Dar | D37: 44206 | E37: System suspense account AC | F37: 0 | G37: 0 | H37: 1 | I37: 0 | J37: 0 | K37: 0 | L37: 0 | M37: 21.6 | N37: =F37+G37+H37+I37+J37+K37+L37-O37 -> 0 | O37: 1 | P37: 1
A38: 32 | B38: Injibara | C38: Bahir Dar | D38: 44206 | E38: Migration suspense accounts | F38: 0 | G38: 0 | H38: 1 | I38: 0 | J38: 0 | K38: 0 | L38: 0 | M38: 0.35 | N38: =F38+G38+H38+I38+J38+K38+L38-O38 -> 1
A39: 33 | B39: Injibara | C39: Bahir Dar | D39: 44206 | E39: Catch all asset and liability | F39: 0 | G39: 0 | H39: 1 | I39: 0 | J39: 0 | K39: 0 | L39: 0 | M39: 154.4 | N39: =F39+G39+H39+I39+J39+K39+L39-O39 -> 1
A40: 34 | B40: Injibara | C40: Bahir Dar | D40: DEC04,2025 UP TO DEC23,2025 | E40: Sundry Creditors - Misc( estimation fee) | F40: 0 | G40: 0 | H40: 0 | I40: 0 | J40: 0 | K40: 0 | L40: 2 | M40: 8700 | N40: =F40+G40+H40+I40+J40+K40+L40-O40 -> 0 | O40: 2 | P40: 2
A41: 35 | B41: Injibara | C41: Bahir Dar | D41: 46129 | E41: Account Rec.Miscellaneous(RTGS Transfer Payable) | F41: 0 | G41: 0 | H41: 0 | I41: 0 | J41: 0 | K41: 0 | L41: 1 | M41: 1350 | N41: =F41+G41+H41+I41+J41+K41+L41-O41 -> 0 | O41: 1 | P41: 1
A42: 36 | B42: Injibara | C42: Bahir Dar | D42: various | E42: ATM Cash balance(difference) | F42: 0 | G42: 0 | H42: 0 | I42: 0 | J42: 0 | K42: 0 | L42: 1 | M42: 7,861.51‬ | N42: =F42+G42+H42+I42+J42+K42+L42-O42 -> 1
A43: 37 | B43: Injibara | C43: Bahir Dar | D43: various | E43: Loan Balance CorrectionExpense | F43: 0 | G43: 0 | H43: 0 | I43: 0 | J43: 0 | K43: 0 | L43: 1 | M43: 725.97 | N43: =F43+G43+H43+I43+J43+K43+L43-O43 -> 1
A44: 38 | B44: Injibara | C44: Bahir Dar | D44: 44206 | E44: Inter Branch Account - T24 R10 | F44: 0 | G44: 0 | H44: 1 | I44: 0 | J44: 0 | K44: 0 | L44: 0 | M44: 1044655.5 | N44: =F44+G44+H44+I44+J44+K44+L44-O44 -> 1
A45: 39 | B45: Injibara | C45: Bahir Dar | D45: various | E45: Dormant accounts Found at the branch | F45: 0 | G45: 0 | H45: 0 | I45: 0 | J45: 2091 | K45: 0 | L45: 0 | M45: 268800 | N45: =F45+G45+H45+I45+J45+K45+L45-O45 -> 2068 | O45: 23 | P45: 23
A46: 40 | B46: Injibara | C46: Bahir Dar | D46: various | E46: ATM cards were not delivered to the respective account holders for a long period of time | F46: 0 | G46: 190 | H46: 0 | I46: 0 | J46: 0 | K46: 0 | L46: 0 | M46: 0 | N46: =F46+G46+H46+I46+J46+K46+L46-O46 -> 190
A47: 41 | B47: Injibara | C47: Bahir Dar | D47: various | E47: ATM cards and pin Difernce | F47: 71 | G47: 0 | H47: 0 | I47: 0 | J47: 0 | K47: 0 | L47: 0 | M47: 0 | N47: =F47+G47+H47+I47+J47+K47+L47-O47 -> 71
A48: 42 | B48: D/Markos | C48: Bahir Dar | E48: Difference observed on ATM cash balance with the general ledger balance . | F48: 0 | G48: 0 | H48: 0 | I48: 0 | J48: 0 | K48: 0 | L48: 1 | M48: 58068.5 | N48: =F48+G48+H48+I48+J48+K48+L48-O48 -> 1
A49: 43 | B49: D/Markos | C49: Bahir Dar | D49: 44206 | E49: Inter branch T-24 R10 | F49: 0 | G49: 0 | H49: 1 | I49: 0 | J49: 0 | K49: 0 | L49: 0 | M49: 3812298.2 | N49: =F49+G49+H49+I49+J49+K49+L49-O49 -> 1
A50: 44 | B50: D/Markos | C50: Bahir Dar | D50: 16/10/2021 | E50: Difference In non contingent | F50: 0 | G50: 0 | H50: 1 | I50: 0 | J50: 0 | K50: 0 | L50: 0 | M50: 7500 | N50: =F50+G50+H50+I50+J50+K50+L50-O50 -> 1
A51: 45 | B51: D/Markos | C51: Bahir Dar | D51: 44206 | E51: Migration suspense accounts | F51: 0 | G51: 0 | H51: 1 | I51: 0 | J51: 0 | K51: 0 | L51: 0 | M51: 298.81 | N51: =F51+G51+H51+I51+J51+K51+L51-O51 -> 1
A52: 46 | B52: D/Markos | C52: Bahir Dar | E52: Dormant accounts Found at the branch | F52: 0 | G52: 0 | H52: 0 | I52: 0 | J52: 1821 | K52: 0 | L52: 0 | M52: 1740573.3 | N52: =F52+G52+H52+I52+J52+K52+L52-O52 -> 1821
A53: 47 | B53: D/Markos | C53: Bahir Dar | D53: 24/11/2025 | E53: zero balance(7000107440068)D/Markos City Edir Council Charity) | F53: 0 | G53: 0 | H53: 0 | I53: 1 | J53: 0 | K53: 0 | L53: 0 | M53: 50 | N53: =F53+G53+H53+I53+J53+K53+L53-O53 -> 0 | O53: 1 | P53: 1
A54: 48 | B54: D/Markos | C54: Bahir Dar | E54: Defective/obsolete fixed assets found at the branch(THINCLLENTBWITH MONITORS/N-CZC5120G5Z,TELLER STOOL,2(GUEST CHAIR 4 LEGS) | F54: 0 | G54: 0 | H54: 0 | I54: 0 | J54: 0 | K54: 0 | L54: 5 | M54: 297021.49 | N54: =F54+G54+H54+I54+J54+K54+L54-O54 -> 5
A55: 49 | B55: D/Markos | C55: Bahir Dar | E55: ATM cards were not delivered to the respective account holders for a long period of time(427)CARD (250) PIN | F55: 0 | G55: 330 | H55: 0 | I55: 0 | J55: 0 | K55: 0 | L55: 0 | M55: 33300 | N55: =F55+G55+H55+I55+J55+K55+L55-O55 -> 330
A56: 50 | B56: D/Markos | C56: Bahir Dar | E56: ATM cards and pin Difernce | F56: 80 | G56: 0 | H56: 0 | I56: 0 | J56: 0 | K56: 0 | L56: 0 | N56: =F56+G56+H56+I56+J56+K56+L56-O56 -> 80
A57: 51 | B57: D/Markos | C57: Bahir Dar | D57: 46029 | E57: Fund Transfer From account No 7000066141883 (Belsty Tilaye) With out signature Of Birr 350,000 | F57: 0 | G57: 0 | H57: 0 | I57: 0 | J57: 0 | K57: 0 | L57: 1 | M57: 350000 | N57: =F57+G57+H57+I57+J57+K57+L57-O57 -> 0 | O57: 1 | P57: 1
A58: 52 | B58: D/Markos | C58: Bahir Dar | D58: 14/07/2026 | E58: Fund Transfer From account No 7000066141883 (Belsty Tilaye) With out signature Of Birr 350,000 | F58: 0 | G58: 0 | H58: 0 | I58: 0 | J58: 0 | K58: 0 | L58: 1 | M58: 350000 | N58: =F58+G58+H58+I58+J58+K58+L58-O58 -> 0 | O58: 1 | P58: 1
A59: 53 | B59: D/Markos | C59: Bahir Dar | D59: 45940 | E59: YESHAMBEL MENGESHA LIYIH(7000105799859 OR SPS 103) DOCUMENTS, POA Do not Authenticated And This POA NOT Allowed for account oppening | F59: 0 | G59: 0 | H59: 0 | I59: 0 | J59: 0 | K59: 0 | L59: 1 | M59: 53.02 | N59: =F59+G59+H59+I59+J59+K59+L59-O59 -> 1
A60: 54 | B60: D/Markos | C60: Bahir Dar | E60: Passbook no 2384074 2384080 not register on account registration book | F60: 0 | G60: 0 | H60: 0 | I60: 0 | J60: 0 | K60: 0 | L60: 1 | M60: 100 | N60: =F60+G60+H60+I60+J60+K60+L60-O60 -> 0 | O60: 1 | P60: 1
A61: 55 | B61: Bahir Dar | C61: Bahir Dar | D61: various | E61: Difference observed on ATM cash balance. with the general ledger balance . | F61: 0 | G61: 0 | H61: 0 | I61: 0 | J61: 0 | K61: 0 | L61: 1 | M61: 78894 | N61: =F61+G61+H61+I61+J61+K61+L61-O61 -> 1
A62: 56 | B62: Bahir Dar | C62: Bahir Dar | D62: various | E62: Cheque books prepared but not delivered to customers for a long period of time. | F62: 0 | G62: 0 | H62: 0 | I62: 0 | J62: 0 | K62: 337 | L62: 0 | M62: 14741 | N62: =F62+G62+H62+I62+J62+K62+L62-O62 -> 337
A63: 57 | B63: Bahir Dar | C63: Bahir Dar | D63: 44206 | E63: Inter branch T-24 R10 | F63: 0 | G63: 0 | H63: 1 | I63: 0 | J63: 0 | K63: 0 | L63: 0 | M63: 31714470 | N63: =F63+G63+H63+I63+J63+K63+L63-O63 -> 1
A64: 58 | B64: Bahir Dar | C64: Bahir Dar | D64: 44206 | E64: System suspense AA | F64: 0 | G64: 0 | H64: 1 | I64: 0 | J64: 0 | K64: 0 | L64: 0 | M64: 84314 | N64: =F64+G64+H64+I64+J64+K64+L64-O64 -> 1
A65: 59 | B65: Bahir Dar | C65: Bahir Dar | D65: 44206 | E65: Migration suspense accounts | F65: 0 | G65: 0 | H65: 1 | I65: 0 | J65: 0 | K65: 0 | L65: 0 | M65: 22970 | N65: =F65+G65+H65+I65+J65+K65+L65-O65 -> 1
A66: 60 | B66: Bahir Dar | C66: Bahir Dar | E66: catch allassets and liability | F66: 0 | G66: 0 | H66: 1 | I66: 0 | J66: 0 | K66: 0 | L66: 0 | M66: 3106 | N66: =F66+G66+H66+I66+J66+K66+L66-O66 -> 1
A67: 62 | B67: Bahir Dar | C67: Bahir Dar | D67: 17/04/2026 | E67: RTGS SERVICE CHARGE RTGS SERVICE CHARGE WHICH WILL Not COLLECTED FROM 50 CUSTOMER | F67: 0 | G67: 0 | H67: 0 | I67: 0 | J67: 0 | K67: 0 | L67: =2500/50 -> 50 | M67: 2500 | N67: =F67+G67+H67+I67+J67+K67+L67-O67 -> 50
A68: 63 | B68: Bahir Dar | C68: Bahir Dar | D68: 46178 | E68: FUEL EXP FOR OUR BRANCH CAR WHICH WILL CL LAIMED TO DIFFERENT BRANCH | F68: 0 | G68: 0 | H68: 0 | I68: 0 | J68: 0 | K68: 0 | L68: 2 | M68: 16799.25 | N68: =F68+G68+H68+I68+J68+K68+L68-O68 -> 2
A69: 64 | B69: Bahir Dar | C69: Bahir Dar | D69: 17/04/2026 | E69: GAS OIL EXPANSE FOR ENGINER YONAS WHICH WILL BECOLLECTED FROM YOHANNES GETNET | F69: 0 | G69: 0 | H69: 0 | I69: 0 | J69: 0 | K69: 0 | L69: 1 | M69: 359.6 | N69: =F69+G69+H69+I69+J69+K69+L69-O69 -> 1
A70: 65 | B70: Bahir Dar | C70: Bahir Dar | D70: 17/04/2026 | E70: GAS OIL EXPANSE FOR ENGINER YONAS WHICH WILL BECOLLECTED FROM ALEMENH FENTAHUN | F70: 0 | G70: 0 | H70: 0 | I70: 0 | J70: 0 | K70: 0 | L70: 1 | M70: 359.6 | N70: =F70+G70+H70+I70+J70+K70+L70-O70 -> 1
A71: 66 | B71: Bahir Dar | C71: Bahir Dar | D71: 17/04/2026 | E71: GAS OIL EXP FOR ENGINER YONAS WHICH WILL BE COLLECTED FROM WORKIE KINDYE | F71: 0 | G71: 0 | H71: 0 | I71: 0 | J71: 0 | K71: 0 | L71: 1 | M71: 359.6 | N71: =F71+G71+H71+I71+J71+K71+L71-O71 -> 1
A72: 68 | B72: Bahir Dar | C72: Bahir Dar | D72: 24/02/2026 | E72: (ACCOUNT CLOSER OF YESHIWAS NIBERTU BY THE ORDER OF NBE ) | F72: 0 | G72: 0 | H72: 0 | I72: 0 | J72: 0 | K72: 0 | L72: 1 | M72: 447.92 | N72: =F72+G72+H72+I72+J72+K72+L72-O72 -> 1
A73: 69 | B73: Bahir Dar | C73: Bahir Dar | D73: 21/01/2026 | E73: (ACCOUNT CLOSER OF Abirham Ademasu BY THE ORDER OF NBE ) | F73: 0 | G73: 0 | H73: 0 | I73: 0 | J73: 0 | K73: 0 | L73: 1 | M73: 1587.54 | N73: =F73+G73+H73+I73+J73+K73+L73-O73 -> 1
A74: 70 | B74: Bahir Dar | C74: Bahir Dar | D74: 21/01/2025 | E74: ( ACCOUNT CLOSER OF MIGANAW CHEKOL BY THE ORDER OF NBE) | F74: 0 | G74: 0 | H74: 0 | I74: 0 | J74: 0 | K74: 0 | L74: 1 | M74: 298.78 | N74: =F74+G74+H74+I74+J74+K74+L74-O74 -> 1
A75: 71 | B75: Bahir Dar | C75: Bahir Dar | D75: 24/12/2024 | E75: (ACCONUT CLOSER OF HAILE MELAK BY THE ORDER OF NBE) | F75: 0 | G75: 0 | H75: 0 | I75: 0 | J75: 0 | K75: 0 | L75: 1 | M75: 153.8 | N75: =F75+G75+H75+I75+J75+K75+L75-O75 -> 1
A76: 72 | B76: Bahir Dar | C76: Bahir Dar | D76: 24/12/2024 | E76: ( ACCOUNT CLOSER OF HAILE MELAK AND KOKEB MEKETE BY THE ORDER OF NBE) | F76: 0 | G76: 0 | H76: 0 | I76: 0 | J76: 0 | K76: 0 | L76: 1 | M76: 136.46 | N76: =F76+G76+H76+I76+J76+K76+L76-O76 -> 1
A77: 73 | B77: Bahir Dar | C77: Bahir Dar | D77: 17/10/2024 | E77: (ACCOUNT CLOSER OF ALEMSEFED KASSAHUN BY THE ORDER OF NBE) | F77: 0 | G77: 0 | H77: 0 | I77: 0 | J77: 0 | K77: 0 | L77: 1 | M77: 7312.55 | N77: =F77+G77+H77+I77+J77+K77+L77-O77 -> 1
A78: 74 | B78: Bahir Dar | C78: Bahir Dar | D78: 45388 | E78: ACCOUNT CLOSER OF MESERET TESFAHUN BY THE ORDER OF NBE) | F78: 0 | G78: 0 | H78: 0 | I78: 0 | J78: 0 | K78: 0 | L78: 1 | M78: 1099.63 | N78: =F78+G78+H78+I78+J78+K78+L78-O78 -> 1
A79: 75 | B79: Bahir Dar | C79: Bahir Dar | D79: 43232 | E79: (AMOUNT KEEPT FOR COURPTED LOAN BY THE TADESSE YIMAM) | F79: 0 | G79: 0 | H79: 0 | I79: 0 | J79: 0 | K79: 0 | L79: 1 | M79: 16416.55 | N79: =F79+G79+H79+I79+J79+K79+L79-O79 -> 1
B80: Bahir Dar | C80: Bahir Dar | D80: 20/12/2023 | E80: Long outstanding CPO ISSUED | F80: 0 | G80: 0 | H80: 0 | I80: 0 | J80: 0 | K80: 0 | L80: 1 | M80: 4860.23 | N80: =F80+G80+H80+I80+J80+K80+L80-O80 -> 1
A81: 76 | B81: Bahir Dar | C81: Bahir Dar | E81: Dormant accounts Found at the branch | F81: 0 | G81: 0 | H81: 0 | I81: 0 | J81: 8475 | K81: 0 | L81: 0 | M81: 6091210.5 | N81: =F81+G81+H81+I81+J81+K81+L81-O81 -> 8412 | O81: 63 | P81: 63
A82: 77 | B82: Bahir Dar | C82: Bahir Dar | D82: various | E82: ATM cards were not delivered to the respective account holders for a long period of time | F82: 0 | G82: 1003 | H82: 0 | I82: 0 | J82: 0 | K82: 0 | L82: 0 | M82: 10300 | N82: =F82+G82+H82+I82+J82+K82+L82-O82 -> 1003
A83: 78 | B83: Bahir Dar | C83: Bahir Dar | D83: various | E83: ATM cards and pin Difernce | F83: 110 | G83: 0 | H83: 0 | I83: 0 | J83: 0 | K83: 0 | L83: 0 | N83: =F83+G83+H83+I83+J83+K83+L83-O83 -> 110
A84: 79 | B84: Finote Selam | C84: Bahir Dar | D84: from branch oppening | E84: Absence of fixed assets source document. | F84: 0 | G84: 0 | H84: 0 | I84: 0 | J84: 0 | K84: 0 | L84: 1 | N84: =F84+G84+H84+I84+J84+K84+L84-O84 -> 0 | O84: 1 | P84: 1
A85: 80 | B85: Finote Selam | C85: Bahir Dar | D85: various | E85: Absence of Accepted For Deposit pending Stamp. | F85: 0 | G85: 0 | H85: 0 | I85: 0 | J85: 0 | K85: 0 | L85: 1 | N85: =F85+G85+H85+I85+J85+K85+L85-O85 -> 0 | O85: 1 | P85: 1
A86: 81 | B86: Finote Selam | C86: Bahir Dar | D86: various | E86: Difference observed on ATM cash balance. with the general ledger balance . | F86: 0 | G86: 0 | H86: 0 | I86: 0 | J86: 0 | K86: 0 | L86: 1 | M86: 34454 | N86: =F86+G86+H86+I86+J86+K86+L86-O86 -> 1
A87: 82 | B87: Finote Selam | C87: Bahir Dar | D87: various | E87: Sundry creditors (Vat collected from Branch Building Owner) | F87: 0 | G87: 0 | H87: 0 | I87: 0 | J87: 0 | K87: 0 | L87: 1 | M87: 136800 | N87: =F87+G87+H87+I87+J87+K87+L87-O87 -> 1
A88: 83 | B88: Finote Selam | C88: Bahir Dar | D88: various | E88: Migration suspense accounts | F88: 0 | G88: 0 | H88: 1 | I88: 0 | J88: 0 | K88: 0 | L88: 0 | M88: 0.55 | N88: =F88+G88+H88+I88+J88+K88+L88-O88 -> 1
A89: 84 | B89: Finote Selam | C89: Bahir Dar | D89: various | E89: Dormant accounts Found at the branch | F89: 0 | G89: 0 | H89: 0 | I89: 0 | J89: 1273 | K89: 0 | L89: 0 | M89: 281149.43 | N89: =F89+G89+H89+I89+J89+K89+L89-O89 -> 1246 | O89: 27 | P89: 27
A90: 85 | B90: Finote Selam | C90: Bahir Dar | D90: various | E90: ATM cards & PIN mailers were not delivered to the respective account holders/ customers for a long period of time as presented below. | F90: 0 | G90: 643 | H90: 0 | I90: 0 | J90: 0 | K90: 0 | L90: 0 | M90: 64300 | N90: =F90+G90+H90+I90+J90+K90+L90-O90 -> 641 | O90: 2 | P90: 2
A91: 86 | B91: Finote Selam | C91: Bahir Dar | D91: various | E91: ATM cards and pin Difernce | F91: 427 | G91: 0 | H91: 0 | I91: 0 | J91: 0 | K91: 0 | L91: 0 | N91: =F91+G91+H91+I91+J91+K91+L91-O91 -> 425 | O91: 2 | P91: 2
A92: 87 | B92: Finote Selam | C92: Bahir Dar | D92: various | E92: Defective/obsolete fixed assets found at the branch(note counting machin teller Type) | F92: 0 | G92: 0 | H92: 0 | I92: 0 | J92: 0 | K92: 0 | L92: 2 | M92: 36729.98 | N92: =F92+G92+H92+I92+J92+K92+L92-O92 -> 0 | O92: 2 | P92: 2
A93: 88 | B93: Finote Selam | C93: Bahir Dar | D93: various | E93: One of the strong room(cash room) key is not functional.so the cash room is opend by the managers single key.not Jointly with the BBM. | F93: 0 | G93: 0 | H93: 0 | I93: 0 | J93: 0 | K93: 0 | L93: 1 | N93: =F93+G93+H93+I93+J93+K93+L93-O93 -> 0 | O93: 1 | P93: 1
A94: 89 | B94: Wereta | C94: Bahir Dar | D94: various days | E94: Difference observed on ATM cash balance.(The physical cash count balance of ATM have shown a difference of Birr22,200compared with the general ledger balance . ) | F94: 0 | G94: 0 | H94: 0 | I94: 0 | J94: 0 | K94: 0 | L94: 1 | M94: 22200 | N94: =F94+G94+H94+I94+J94+K94+L94-O94 -> 1
A95: 90 | B95: Wereta | C95: Bahir Dar | D95: occured in system migrationT24R10 to T4R20 | E95: Inter branch T-24 R10 | F95: 0 | G95: 0 | H95: 1 | I95: 0 | J95: 0 | K95: 0 | L95: 0 | M95: 6568859 | N95: =F95+G95+H95+I95+J95+K95+L95-O95 -> 1
A96: 91 | B96: Wereta | C96: Bahir Dar | E96: Migration suspense accounts | F96: 0 | G96: 0 | H96: 1 | I96: 0 | J96: 0 | K96: 0 | L96: 0 | M96: 0.27 | N96: =F96+G96+H96+I96+J96+K96+L96-O96 -> 1
A97: 92 | B97: Wereta | C97: Bahir Dar | D97: various days | E97: Cash stamps and branch crossing are dameged needs change | F97: 0 | G97: 0 | H97: 0 | I97: 0 | J97: 0 | K97: 0 | L97: 3 | N97: =F97+G97+H97+I97+J97+K97+L97-O97 -> 3
A98: 93 | B98: Wereta | C98: Bahir Dar | D98: various days | E98: Dormant accounts Found at the branch | F98: 0 | G98: 0 | H98: 0 | I98: 0 | J98: 321 | K98: 0 | L98: 0 | M98: 10394799 | N98: =F98+G98+H98+I98+J98+K98+L98-O98 -> 254 | O98: 67 | P98: 67
A99: 94 | B99: Wereta | C99: Bahir Dar | D99: various days | E99: 380 post no debit(17) accounts are found at the branch | F99: 0 | G99: 0 | H99: 0 | I99: 0 | J99: 0 | K99: 0 | L99: 380 | M99: 63295 | N99: =F99+G99+H99+I99+J99+K99+L99-O99 -> 380
A100: 95 | B100: Wereta | C100: Bahir Dar | D100: 30/07/2026 | E100: Total cash in vault is greater than the allowed cash holding limit of the bracnh | F100: 0 | G100: 0 | H100: 0 | I100: 0 | J100: 0 | K100: 0 | L100: 1 | M100: 2064696 | N100: =F100+G100+H100+I100+J100+K100+L100-O100 -> 1
...

Sheet Adama
A1: NIB International Bank S.C
A2: Adama District
A3: Detailed Monthly internal Control Reports
A4: As of -July 31,2026
A5: SN | D5: Operation area | E5: ATM | G5: It | H5: Zero Balance | I5: Inactive/Dormant | J5: Ck book stock | K5: Other Cases | L5: Posting date | M5: Types of Irregularities/problems | N5: Amount involved in Birr | O5: Status of the irregularities
E6: Mismatch | F6: Long outstanding | N6: Amount involved | O6: Unrectified | P6: Rectified | Q6: Unrectified In Amount
B7: Branch | C7: District | D7: Operation area | K7: finding NO. | M7: Finding
A8: 1 | B8: Adama | C8: Adama | D8: Cash and Cash Items | K8: 1 | L8: 20260731 | M8: Difference observed on ATM cash balance.(The physical cash count balance of ATM have shown a difference of Birr ……….. compared with the general ledger balance . ) | N8: 101296.54 | O8: =E8+F8+G8+H8+I8+J8+K8-P8 -> 1
A9: 2 | B9: Adama | C9: Adama | G9: 1 | M9: Total fixed asset | N9: -4836149.2 | O9: =E9+F9+G9+H9+I9+J9+K9-P9 -> 1
A10: 3 | B10: Adama | C10: Adama | D10: Account Management | G10: 1 | M10: Inter branch T-24 R10 | N10: 3.030623e+08 | O10: =E10+F10+G10+H10+I10+J10+K10-P10 -> 1
A11: 4 | B11: Adama | C11: Adama | G11: 1 | M11: System suspense account AA | N11: 4.27 | O11: =E11+F11+G11+H11+I11+J11+K11-P11 -> 1
A12: 5 | B12: Adama | C12: Adama | G12: 1 | M12: Migration suspense accounts | N12: -1318972 | O12: =E12+F12+G12+H12+I12+J12+K12-P12 -> 1
A13: 6 | B13: Adama | C13: Adama | G13: 1 | M13: Catch all asset and liability | N13: 192.81 | O13: =E13+F13+G13+H13+I13+J13+K13-P13 -> 1
A14: 7 | B14: Adama | C14: Adama | K14: 1 | M14: Accr interest on Gov't bond &Dep | N14: 60,304.35 2 | O14: =E14+F14+G14+H14+I14+J14+K14-P14 -> 1
A15: 8 | B15: Adama | C15: Adama | K15: 1 | M15: temp loan repayment acct | N15: 105532.34 | O15: =E15+F15+G15+H15+I15+J15+K15-P15 -> 1
A16: 9 | B16: Adama | C16: Adama | K16: 1 | M16: Loan Balance correctionExpense | N16: 18223.54 | O16: =E16+F16+G16+H16+I16+J16+K16-P16 -> 1
A17: 10 | B17: Adama | C17: Adama | K17: 1 | M17: Deposit act in process in opening | N17: 190.86 | O17: =E17+F17+G17+H17+I17+J17+K17-P17 -> 0 | P17: 1
A18: 11 | B18: Adama | C18: Adama | K18: 1 | M18: Loan Balance Correction Income | N18: 13701.9 | O18: =E18+F18+G18+H18+I18+J18+K18-P18 -> 1
A19: 12 | B19: Adama | C19: Adama | K19: 1 | M19: COURT CASE PYMT | N19: 3529.26 | O19: =E19+F19+G19+H19+I19+J19+K19-P19 -> 1
A20: 13 | B20: Adama | C20: Adama | K20: 1 | M20: LMTS SettlemenPymt | N20: 700 | O20: =E20+F20+G20+H20+I20+J20+K20-P20 -> 0 | P20: 1
A21: 14 | B21: Adama | C21: Adama | I21: 10631 | M21: Dormant accounts Found at the branch | N21: 0 | O21: =E21+F21+G21+H21+I21+J21+K21-P21 -> 10631
A22: 15 | B22: Adama | C22: Adama | K22: 15 | M22: Defective/obsolete fixed assets found at the branch | N22: 0 | O22: =E22+F22+G22+H22+I22+J22+K22-P22 -> 15
A23: 16 | B23: Adama | C23: Adama | D23: Card Banking | F23: 834 | M23: ATM cards & PIN mailers were not delivered to the respective account holders/ customers for a long period of time as presented below.Total PIN834& ATM Card 769 | N23: 0 | O23: =E23+F23+G23+H23+I23+J23+K23-P23 -> 834
A24: 17 | B24: Adama | C24: Adama | E24: 65 | M24: Mismatch of ATM and PIN | O24: =E24+F24+G24+H24+I24+J24+K24-P24 -> 65
A25: 18 | B25: Adama | C25: Adama | D25: Ticket Vouching | K25: 1 | M25: TICKET not Signed By Customer | N25: 100000 | O25: =E25+F25+G25+H25+I25+J25+K25-P25 -> 0 | P25: 1
A26: 19 | B26: Adama Men | C26: Adama | D26: Cash and Cash Items | K26: 1 | M26: Abnormal balances of ATM cash | N26: -14950 | O26: =E26+F26+G26+H26+I26+J26+K26-P26 -> 1
A27: 20 | B27: Adama Men | C27: Adama | K27: 1 | M27: Difference observed on ATM cash balance.(The physical cash count balance of ATM have shown a difference of Birr 14,950 compared with the general ledger balance . ) | O27: =E27+F27+G27+H27+I27+J27+K27-P27 -> 1
A28: 21 | B28: Adama Men | C28: Adama | G28: 1 | M28: Inter branch T-24 R10 | N28: 3,628,749.1 | O28: =E28+F28+G28+H28+I28+J28+K28-P28 -> 1
A29: 22 | B29: Adama Men | C29: Adama | G29: 1 | M29: Migration suspense accounts | N29: 1 | O29: =E29+F29+G29+H29+I29+J29+K29-P29 -> 1
A30: 23 | B30: Adama Men | C30: Adama | G30: 1 | M30: Catch all asset and liability | N30: 153.85 | O30: =E30+F30+G30+H30+I30+J30+K30-P30 -> 1
A31: 24 | B31: Adama Men | C31: Adama | K31: 1 | M31: Sundry debtors | N31: 5654.51 | O31: =E31+F31+G31+H31+I31+J31+K31-P31 -> 1
A32: 25 | B32: Adama Men | C32: Adama | K32: 1 | M32: Sundry creditors | N32: 2648.23 | O32: =E32+F32+G32+H32+I32+J32+K32-P32 -> 1
A33: 26 | B33: Adama Men | C33: Adama | D33: Loan and Advances | K33: 1 | M33: Undisbursed term loan | N33: 1,286,899 | O33: =E33+F33+G33+H33+I33+J33+K33-P33 -> 1
A34: 27 | B34: Adama Men | C34: Adama | I34: 4030 | M34: Dormant accounts Found at the branch | O34: =E34+F34+G34+H34+I34+J34+K34-P34 -> 4030
A35: 28 | B35: Adama Men | C35: Adama | D35: Card Banking | K35: 1 | M35: ATM cards 482 & PIN 475 mailers were not delivered to the respective account holders/ customers for a long period of time as presented below. | O35: =E35+F35+G35+H35+I35+J35+K35-P35 -> 1
A36: 29 | B36: Adama Boset | C36: Adama | D36: Cash and Cash Items | K36: 1 | L36: 31/07/2026 | M36: Abnormal balances of ATM cash | N36: 101984.44 | O36: =E36+F36+G36+H36+I36+J36+K36-P36 -> 1
A37: 30 | B37: Adama Boset | C37: Adama | K37: 1 | L37: 31/07/2026 | M37: Difference observed on ATM cash balance.(The physical cash count balance of ATM have shown a difference of Cash overage Birr 101,984.44 compared with the general ledger balance . ) | O37: =E37+F37+G37+H37+I37+J37+K37-P37 -> 1
A38: 31 | B38: Adama Boset | C38: Adama | G38: 1 | L38: Feb 15,2022 | M38: Inter branch T-24 R10 | N38: 20575944 | O38: =E38+F38+G38+H38+I38+J38+K38-P38 -> 1
A39: 32 | B39: Adama Boset | C39: Adama | G39: 1 | L39: In Mar 18,2022it was 241.99 on mar 19,2022 the HO debited the account by 241.73the remaining 0.26 left on migration suspense accounts. | M39: Migration suspense accounts | N39: 0.26 | O39: =E39+F39+G39+H39+I39+J39+K39-P39 -> 1
A40: 33 | B40: Adama Boset | C40: Adama | I40: 3141 | L40: 31/07/2026 | M40: Dormant accounts Found at the branch | O40: =E40+F40+G40+H40+I40+J40+K40-P40 -> 3141
A41: 34 | B41: Adama Boset | C41: Adama | K41: 1 | L41: 31/07/2026 | M41: Defective/obsolete fixed assets found at the branch | N41: 2 guard chair | O41: =E41+F41+G41+H41+I41+J41+K41-P41 -> 1
A42: 35 | B42: Adama Boset | C42: Adama | D42: Card Banking | F42: 68 | L42: 31/07/2026 | M42: ATM cards 61 & PIN 68 mailers were not delivered to the respective account holders/ customers for a long period of time as presented below. | O42: =E42+F42+G42+H42+I42+J42+K42-P42 -> 68
A43: 36 | B43: Arerti | C43: Adama | K43: 1 | M43: Difference observed on ATM cash balance.(The physical cash count balance of ATM have shown a difference of Birr -9600 compared with the general ledger balance . ) | N43: -10000 | O43: =E43+F43+G43+H43+I43+J43+K43-P43 -> 1
A44: 37 | B44: Arerti | C44: Adama | G44: 1 | M44: Inter branch T-24 R10 | N44: -10600950 | O44: =E44+F44+G44+H44+I44+J44+K44-P44 -> 1
A45: 38 | B45: Arerti | C45: Adama | G45: 1 | M45: Migration suspense accounts | N45: 4896.36 | O45: =E45+F45+G45+H45+I45+J45+K45-P45 -> 1
A46: 39 | B46: Arerti | C46: Adama | I46: 464 | M46: Dormant accounts Found at the branch | O46: =E46+F46+G46+H46+I46+J46+K46-P46 -> 464
A47: 40 | B47: Arerti | C47: Adama | K47: 1 | M47: Defective/obsolete fixed assets found at the branch | O47: =E47+F47+G47+H47+I47+J47+K47-P47 -> 1
A48: 41 | B48: Arerti | C48: Adama | D48: Card Banking | F48: 53 | M48: 0ATM cards &53 PIN mailers were not delivered to the respective account holders/ customers for a long period of time as presented below. | N48: 0 | O48: =E48+F48+G48+H48+I48+J48+K48-P48 -> 53
A49: 42 | B49: Arerti | C49: Adama | E49: 53 | M49: Mismatch of ATM and PIN | O49: =E49+F49+G49+H49+I49+J49+K49-P49 -> 53
A50: 43 | B50: Arerti | C50: Adama | K50: 2 | M50: Fund Transfers were made without Customer's Signature | O50: =E50+F50+G50+H50+I50+J50+K50-P50 -> 2
A51: 44 | B51: Aseela | C51: Adama | D51: Cash and Cash Items | K51: 1 | M51: Abnormal balances of ATM cash | N51: 199913 | O51: =E51+F51+G51+H51+I51+J51+K51-P51 -> 1
A52: 45 | B52: Aseela | C52: Adama | K52: 1 | M52: Long-term unconsolidated POS cash advance(POS Cash advance of Bir left over in the General Ledger for a long time without being deposited) | N52: -97 | O52: =E52+F52+G52+H52+I52+J52+K52-P52 -> 1
A53: 46 | B53: Aseela | C53: Adama | K53: 1 | M53: Difference observed on ATM cash balance.(The physical cash count balance of ATM have shown a difference of Birr ……….. compared with the general ledger balance . ) | N53: 199913 | O53: =E53+F53+G53+H53+I53+J53+K53-P53 -> 1
A54: 47 | B54: Aseela | C54: Adama | G54: 1 | M54: Inter branch T-24 R10 | N54: 83247373 | O54: =E54+F54+G54+H54+I54+J54+K54-P54 -> 1
A55: 48 | B55: Aseela | C55: Adama | G55: 1 | M55: Migration suspense accounts | N55: -1171.55 | O55: =E55+F55+G55+H55+I55+J55+K55-P55 -> 1
A56: 49 | B56: Aseela | C56: Adama | K56: 1 | M56: customer (M.E FLOUR Factory ) birr not paid loan fully because of court case. | N56: 463656.23 | O56: =E56+F56+G56+H56+I56+J56+K56-P56 -> 1
A57: 50 | B57: Aseela | C57: Adama | K57: 3 | M57: customers are closed loan file but the leaft unpaid amount of birr is recorded on receivable Acc. | N57: 16517.01 | O57: =E57+F57+G57+H57+I57+J57+K57-P57 -> 3
A58: 51 | B58: Aseela | C58: Adama | K58: 1 | M58: Sundry creditors-cost of Check until claim is deliverd | N58: 4608.41 | O58: =E58+F58+G58+H58+I58+J58+K58-P58 -> 1
A59: 52 | B59: Aseela | C59: Adama | K59: 1 | M59: cost of Check until claim is deliverd | N59: 1739.2 | O59: =E59+F59+G59+H59+I59+J59+K59-P59 -> 1
A60: 53 | B60: Aseela | C60: Adama | K60: 1 | M60: 1 % DISASTER BIRR | N60: 105000 | O60: =E60+F60+G60+H60+I60+J60+K60-P60 -> 1
A61: 54 | B61: Aseela | C61: Adama | H61: 205 | M61: Dormant accounts Found at the branch | O61: =E61+F61+G61+H61+I61+J61+K61-P61 -> 205
A62: 55 | B62: Aseela | C62: Adama | D62: Card Banking | F62: 294 | M62: 294 ATM cards & 270 PIN mailers were not delivered to the respective account holders/ customers for a long period of time as presented below. | O62: =E62+F62+G62+H62+I62+J62+K62-P62 -> 294
A63: 56 | B63: Aseela | C63: Adama | E63: 24 | M63: Mismatch of ATM and PIN | O63: =E63+F63+G63+H63+I63+J63+K63-P63 -> 24
A64: 57 | B64: Awash 7 | C64: Adama | K64: 1 | L64: 31/01/2025 | M64: Difference observed on ATM cash balance.(The physical cash count balance of ATM have shown a difference of Birr 10,800.00 Compared with the general ledger balance . ) | N64: 10800 | O64: =E64+F64+G64+H64+I64+J64+K64-P64 -> 1
A65: 58 | B65: Awash 7 | C65: Adama | G65: 1 | L65: 30/12/2021 | M65: Inter branch T-24 R10 | N65: 5526750.7 | O65: =E65+F65+G65+H65+I65+J65+K65-P65 -> 1
A66: 59 | B66: Awash 7 | C66: Adama | G66: 1 | L66: 45272 | M66: Catch all asset and liability | N66: 10 | O66: =E66+F66+G66+H66+I66+J66+K66-P66 -> 1
A67: 60 | B67: Awash 7 | C67: Adama | K67: 1 | L67: 17/04/2026 | M67: Sundry debtors Account Rec.Miscellaneous-ETB 12548 (For RTGS Transfer Payable HO Transfer to GL at the date of April,17,2026 | N67: 750 | O67: =E67+F67+G67+H67+I67+J67+K67-P67 -> 1
A68: 61 | B68: Awash 7 | C68: Adama | K68: 1 | M68: Sundry creditors sundry creditors-Misc ETB17568 Staff PF and untile approved cash indeminity account | N68: 7963.22 | O68: =E68+F68+G68+H68+I68+J68+K68-P68 -> 1
A69: 62 | B69: Awash 7 | C69: Adama | I69: 5180 | M69: Dormant accounts Found at the branch | N69: 0 | O69: =E69+F69+G69+H69+I69+J69+K69-P69 -> 5180
A70: 63 | B70: Awash 7 | C70: Adama | K70: 1 | M70: Fire Extingushier | O70: =E70+F70+G70+H70+I70+J70+K70-P70 -> 0 | P70: 1
A71: 64 | B71: Awash 7 | C71: Adama | K71: 2 | M71: Defective/obsolete fixed assets found at the branch | O71: =E71+F71+G71+H71+I71+J71+K71-P71 -> 2
A72: 65 | B72: Awash 7 | C72: Adama | D72: Card Banking | F72: 988 | M72: ATM cards & PIN mailers were not delivered to the respective account holders/ customers for a long period of time as presented below. No.of ATM =988 and PIN=809 | N72: 0 | O72: =E72+F72+G72+H72+I72+J72+K72-P72 -> 988
A73: 66 | B73: Awash 7 | C73: Adama | E73: 179 | M73: Mismatch of ATM and PIN | O73: =E73+F73+G73+H73+I73+J73+K73-P73 -> 179
A74: 67 | B74: Awash 7 | C74: Adama | D74: Ticket Vouching | K74: 1 | L74: 11,07,2026 | M74: Without of Customer Signature Withdrawl | N74: 50000 | O74: =E74+F74+G74+H74+I74+J74+K74-P74 -> 1
A75: 68 | B75: Awash 7 | C75: Adama | K75: 1 | L75: 10,07,2026 | M75: Without of Customer Signature Account to Account Transfer | N75: 250000 | O75: =E75+F75+G75+H75+I75+J75+K75-P75 -> 1
A76: 69 | B76: Awash 7 | C76: Adama | D76: Others | K76: 1 | M76: The issuing, surrendering, sorting and wrapping of cash notes takes place in an area that has no separate or partitioned room designed to serve of its own. | O76: =E76+F76+G76+H76+I76+J76+K76-P76 -> 1
A77: 70 | B77: Awash 7 | C77: Adama | K77: 1 | M77: The cash room has been used to keep stationery items and all Ticket as a result the room was accessible to those employees demanding these items for operational use. | O77: =E77+F77+G77+H77+I77+J77+K77-P77 -> 1
A78: 71 | B78: Awash 7 | C78: Adama | K78: 1 | M78: Our branch ATM and Tally passbook printer no Function | O78: =E78+F78+G78+H78+I78+J78+K78-P78 -> 1
A79: 72 | B79: Ada Bishoftu | C79: Adama | D79: Cash and Cash Items | K79: 1 | M79: Abnormal balances of ATM cash | N79: 207360.49 | O79: =E79+F79+G79+H79+I79+J79+K79-P79 -> 1
A80: 73 | B80: Ada Bishoftu | C80: Adama | K80: 1 | M80: Difference observed on ATM cash balance.(The physical cash count balance of ATM have shown a difference of Birr -167,711.01. compared with the general ledger balance . ) | N80: 207360.49 | O80: =E80+F80+G80+H80+I80+J80+K80-P80 -> 1
A81: 74 | B81: Ada Bishoftu | C81: Adama | G81: 1 | M81: Inter branch T-24 R10 | N81: 8578220.6 | O81: =E81+F81+G81+H81+I81+J81+K81-P81 -> 1
A82: 75 | B82: Ada Bishoftu | C82: Adama | G82: 1 | M82: Migration suspense accounts | N82: 25.65 | O82: =E82+F82+G82+H82+I82+J82+K82-P82 -> 1
A83: 76 | B83: Ada Bishoftu | C83: Adama | G83: 1 | M83: Catch all asset and liability | N83: 0.02 | O83: =E83+F83+G83+H83+I83+J83+K83-P83 -> 1
A84: 77 | B84: Ada Bishoftu | C84: Adama | D84: Loan and Advances | K84: 1 | M84: Holiday Salary Advance | N84: 3000 | O84: =E84+F84+G84+H84+I84+J84+K84-P84 -> 1
A85: 78 | B85: Ada Bishoftu | C85: Adama | K85: 1 | M85: Accrured interest on Gov`tBond&Dep | N85: 7992 | O85: =E85+F85+G85+H85+I85+J85+K85-P85 -> 1
A86: 79 | B86: Ada Bishoftu | C86: Adama | I86: 3721 | M86: Dormant accounts Found at the branch | O86: =E86+F86+G86+H86+I86+J86+K86-P86 -> 3721
A87: 80 | B87: Ada Bishoftu | C87: Adama | D87: Card Banking | F87: 792 | M87: 704 ATM cards & 792 PIN mailers were not delivered to the respective account holders/ customers for a long period of time as presented below. | O87: =E87+F87+G87+H87+I87+J87+K87-P87 -> 792
A88: 81 | B88: Ada Bishoftu | C88: Adama | E88: 88 | M88: Mismatch of ATM and PIN | O88: =E88+F88+G88+H88+I88+J88+K88-P88 -> 88
A89: 82 | B89: Ada Bishoftu | C89: Adama | K89: 1 | L89: 25-07-2026 | M89: Fund Transfers were made without Customer's Signature | N89: 65000 | O89: =E89+F89+G89+H89+I89+J89+K89-P89 -> 1
A90: 83 | B90: Bale Robe | C90: Adama | D90: Cash and Cash Items | K90: 1 | L90: 31/07/2026 | M90: Abnormal balances of ATM cash | N90: 1450.79 | O90: =E90+F90+G90+H90+I90+J90+K90-P90 -> 1
A91: 84 | B91: Bale Robe | C91: Adama | K91: 1 | L91: 31/07/2026 | M91: Difference observed on ATM cash balance.(The physical cash count balance of ATM have shown a difference of Birr ……….. compared with the general ledger balance . ) | N91: 1450.79 | O91: =E91+F91+G91+H91+I91+J91+K91-P91 -> 1
A92: 85 | B92: Bale Robe | C92: Adama | G92: 1 | M92: Inter branch T-24 R10 | N92: 57169872 | O92: =E92+F92+G92+H92+I92+J92+K92-P92 -> 1
A93: 86 | B93: Bale Robe | C93: Adama | G93: 2 | M93: Migration suspense accounts | N93: 1365.12 | O93: =E93+F93+G93+H93+I93+J93+K93-P93 -> 2
A94: 87 | B94: Bale Robe | C94: Adama | G94: 2 | M94: Catch all asset and liability | N94: 0.75 | O94: =E94+F94+G94+H94+I94+J94+K94-P94 -> 2
A95: 88 | B95: Bale Robe | C95: Adama | I95: 7294 | L95: 31/07/26 | M95: Dormant accounts Found at the branch | O95: =E95+F95+G95+H95+I95+J95+K95-P95 -> 7294
A96: 89 | B96: Bale Robe | C96: Adama | D96: Card Banking | F96: 1008 | M96: 993 ATM cards &1008 PIN mailers were not delivered to the respective account holders/ customers for a long period of time as presented below. | O96: =E96+F96+G96+H96+I96+J96+K96-P96 -> 1008
A97: 90 | B97: Bale Robe | C97: Adama | E97: 15 | M97: Mismatch of ATM and PIN | O97: =E97+F97+G97+H97+I97+J97+K97-P97 -> 15
A98: 91 | B98: Bale Robe | C98: Adama | K98: 1 | L98: JULY 04/07/26 | M98: Fund Transfers were made without Customer's Signature | N98: 173000 | O98: =E98+F98+G98+H98+I98+J98+K98-P98 -> 1
A99: 92 | B99: Batu | C99: Adama | D99: Cash and Cash Items | K99: 1 | M99: Abnormal balances of ATM cash | N99: 12200 | O99: =E99+F99+G99+H99+I99+J99+K99-P99 -> 1
A100: 94 | B100: Batu | C100: Adama | K100: 1 | M100: Difference observed on ATM cash balance.(The physical cash count balance of ATM have shown a difference of Birr ……….. compared with the general ledger balance . ) | N100: 12200 | O100: =E100+F100+G100+H100+I100+J100+K100-P100 -> 1
...

Sheet Hossaena
A1: NIB International Bank S.C
A2: Name of Departments/NAAD
A3: Detailed Monthly internal Control Reports
A4: As of JUly 31 2026 month report | C4: as of march 31,2025
A5: SN | B5: Branch | C5: District | E5: Types of irregularities | F5: ATM Cases | L5: Other Case No. | M5: Amount involved | N5: Status of the irregularities
D6: Transaction Date | F6: Mismatch | G6: Long O/S | H6: IT Cases | I6: Zero Bal. | J6: Dormant A/C | K6: CK Book stock | N6: Unrectified | O6: Rectified | P6: Unrectified In Amount
A7: 1 | B7: Adilo | C7: Hossaena | D7: 31/07/2026 | E7: Dormant accounts Found at the branch | F7: 0 | G7: 0 | H7: 0 | I7: 0 | J7: 806 | K7: 0 | L7: 0 | N7: =F7+G7+H7+I7+J7+K7+L7-O7 -> 806
A8: 2 | B8: Adilo | C8: Hossaena | D8: 31/07/2026 | E8: ATM cards & PIN mailers ‬ were not delivered to the respective account holders/ customers for a long period of time . | F8: 0 | G8: 660 | H8: 0 | I8: 0 | J8: 0 | K8: 0 | L8: 0 | N8: =F8+G8+H8+I8+J8+K8+L8-O8 -> 656 | O8: 4
A9: 3 | B9: Angacha | C9: Hossaena | D9: 44409 | E9: Abnormal balances concerning Foreign currency. | F9: 0 | G9: 0 | H9: 0 | I9: 0 | J9: 0 | K9: 0 | L9: 1 | M9: 6435.05 | N9: =F9+G9+H9+I9+J9+K9+L9-O9 -> 1
A10: 4 | B10: Angacha | C10: Hossaena | D10: 44409 | E10: long autsanding on Sundry creditors-misc | F10: 0 | G10: 0 | H10: 0 | I10: 0 | J10: 0 | K10: 0 | L10: 1 | M10: 6773.22 | N10: =F10+G10+H10+I10+J10+K10+L10-O10 -> 1
A11: 5 | B11: Angacha | C11: Hossaena | E11: Dormant accounts Found at the branch | F11: 0 | G11: 0 | H11: 0 | I11: 0 | J11: 2437 | K11: 0 | L11: 0 | N11: =F11+G11+H11+I11+J11+K11+L11-O11 -> 2434 | O11: 3
A12: 6 | B12: Angacha | C12: Hossaena | D12: 17/04/2019 | E12: ATM cards & PIN mailers were not delivered to the respective account holders/ customers for a long period of time as presented below. | F12: 0 | G12: 1148 | H12: 0 | I12: 0 | J12: 0 | K12: 0 | L12: 0 | N12: =F12+G12+H12+I12+J12+K12+L12-O12 -> 1148
A13: 7 | B13: Angacha | C13: Hossaena | E13: ATM cards (1148) & PIN mailers(1119) were differ | F13: 29 | G13: 0 | H13: 0 | I13: 0 | J13: 0 | K13: 0 | L13: 0 | N13: =F13+G13+H13+I13+J13+K13+L13-O13 -> 29
A14: 8 | B14: Ansho | C14: Hossaena | D14: 13/05/25 | E14: Perdiem&Travel expence | F14: 0 | G14: 0 | H14: 0 | I14: 0 | J14: 0 | K14: 0 | L14: 0 | M14: 6180 | N14: =F14+G14+H14+I14+J14+K14+L14-O14 -> 0
A15: 9 | B15: Ansho | C15: Hossaena | D15: 24/07/2026 | E15: FT withoout custemer signature | F15: 0 | G15: 0 | H15: 0 | I15: 0 | J15: 0 | K15: 0 | L15: 1 | M15: 450000 | N15: =F15+G15+H15+I15+J15+K15+L15-O15 -> 0 | O15: 1
A16: 10 | B16: Areka | C16: Hossaena | D16: 2021oct01 | E16: Migration suspense accounts | F16: 0 | G16: 0 | H16: 1 | I16: 0 | J16: 0 | K16: 0 | L16: 0 | M16: 284649.59 | N16: =F16+G16+H16+I16+J16+K16+L16-O16 -> 1
A17: 11 | B17: Areka | C17: Hossaena | D17: 45358 | E17: Catch all asset and liability | F17: 0 | G17: 0 | H17: 1 | I17: 0 | J17: 0 | K17: 0 | L17: 0 | M17: 20 | N17: =F17+G17+H17+I17+J17+K17+L17-O17 -> 1
A18: 12 | B18: Areka | C18: Hossaena | D18: 22,JULY,11 | E18: abnormal teller till balance | F18: 0 | G18: 0 | H18: 1 | I18: 0 | J18: 0 | K18: 0 | L18: 0 | M18: 7808.96 | N18: =F18+G18+H18+I18+J18+K18+L18-O18 -> 1
A19: 13 | B19: Areka | C19: Hossaena | D19: 31/07/2026 | E19: Dormant accounts Found at the branch | F19: 0 | G19: 0 | H19: 0 | I19: 0 | J19: 7996 | K19: 0 | L19: 0 | N19: =F19+G19+H19+I19+J19+K19+L19-O19 -> 7928 | O19: 68
A20: 14 | B20: Areka | C20: Hossaena | D20: 31/07/2026 | E20: ATM cards & PIN mailers were not delivered to the respective account holders/ customers for a long period of time as presented below. | F20: 0 | G20: 2333 | H20: 0 | I20: 0 | J20: 0 | K20: 0 | L20: 0 | N20: =F20+G20+H20+I20+J20+K20+L20-O20 -> 2333
A21: 15 | B21: Areka | C21: Hossaena | E21: ATM cards(2333) & PIN mailers(1834) were differ | F21: 499 | G21: 0 | H21: 0 | I21: 0 | J21: 0 | K21: 0 | L21: 0 | N21: =F21+G21+H21+I21+J21+K21+L21-O21 -> 499
A22: 16 | B22: Bele | C22: Hossaena | D22: 31/07/26 | E22: Difference observed on ATM cash balance.(The physical cash count balance of ATM has shown a difference of Birr 13,600.02compared with the general ledger balance . ) | F22: 0 | G22: 0 | H22: 0 | I22: 0 | J22: 0 | K22: 0 | L22: 1 | M22: 13600.02 | N22: =F22+G22+H22+I22+J22+K22+L22-O22 -> 0 | O22: 1
A23: 17 | B23: Bele | C23: Hossaena | E23: Cheque books by the name ASHENAF ALEMAYEHU HAYLU acount NO 7000024623101(382SPS1),check type BF and check no 6225151-6225200 ,50 leaves prepared but not delivered to customers for a long period of time. | F23: 0 | G23: 0 | H23: 0 | I23: 0 | J23: 0 | K23: 1 | L23: 0 | N23: =F23+G23+H23+I23+J23+K23+L23-O23 -> 0 | O23: 1
A24: 18 | B24: Bele | C24: Hossaena | D24: 31/07/26 | E24: Migration suspense accounts | F24: 0 | G24: 0 | H24: 1 | I24: 0 | J24: 0 | K24: 0 | L24: 0 | M24: 0.22 | N24: =F24+G24+H24+I24+J24+K24+L24-O24 -> 1
A25: 19 | B25: Bele | C25: Hossaena | D25: 31/07/26 | E25: deposit acount on process of oppening, long out stand accoun delayed for more than 5/7 days | F25: 0 | G25: 0 | H25: 0 | I25: 0 | J25: 0 | K25: 0 | L25: 1 | M25: 41247.99 | N25: =F25+G25+H25+I25+J25+K25+L25-O25 -> 1
A26: 20 | B26: Bele | C26: Hossaena | E26: Dormant accounts Found at the branch | F26: 0 | G26: 0 | H26: 0 | I26: 0 | J26: 282 | K26: 0 | L26: 0 | N26: =F26+G26+H26+I26+J26+K26+L26-O26 -> 262 | O26: 20
A27: 21 | B27: Bele | C27: Hossaena | D27: 31/07/26 | E27: ATM cards & PIN mailers were not delivered to the respective account holders/ customers for a long period of time and anyonomous not delevered to customer for for long period of time as presented below. | F27: 0 | G27: 1043 | H27: 0 | I27: 0 | J27: 0 | K27: 0 | L27: 0 | N27: =F27+G27+H27+I27+J27+K27+L27-O27 -> 1043
A28: 22 | B28: Bele | C28: Hossaena | E28: ATM cards(1043) & PIN mailers(621) were differ | F28: 422 | G28: 0 | H28: 0 | I28: 0 | J28: 0 | K28: 0 | L28: 0 | N28: =F28+G28+H28+I28+J28+K28+L28-O28 -> 422
A29: 23 | C29: Hossaena | D29: 46332 | E29: Cash withdrawal with out customer signiture/FT Abera Mitiku | F29: 0 | G29: 0 | H29: 0 | I29: 0 | J29: 0 | K29: 0 | L29: 1 | M29: 50000 | N29: =F29+G29+H29+I29+J29+K29+L29-O29 -> 0 | O29: 1
A30: 24 | B30: Boditi | C30: Hossaena | D30: 31/07/26 | E30: Difference observed on ATM cash balance.(The physical cash count balance of ATM have shown a difference of Birr 41,000 compared with the general ledger balance . ) | F30: 0 | G30: 0 | H30: 0 | I30: 0 | J30: 0 | K30: 0 | L30: 1 | M30: 41000 | N30: =F30+G30+H30+I30+J30+K30+L30-O30 -> 0 | O30: 1
A31: 25 | B31: Boditi | C31: Hossaena | D31: 31/07/2026 | E31: Migration suspense accounts | F31: 0 | G31: 0 | H31: 1 | I31: 0 | J31: 0 | K31: 0 | L31: 0 | M31: 0.34 | N31: =F31+G31+H31+I31+J31+K31+L31-O31 -> 1
A32: 26 | B32: Boditi | C32: Hossaena | D32: 31/07/2026 | E32: Long outstanding on Sundry debtors | F32: 0 | G32: 0 | H32: 0 | I32: 0 | J32: 0 | K32: 0 | L32: 1 | M32: 27430.96 | N32: =F32+G32+H32+I32+J32+K32+L32-O32 -> 1
A33: 27 | B33: Boditi | C33: Hossaena | D33: 31/07/2026 | E33: Dormant accounts Found at the branch | F33: 0 | G33: 0 | H33: 0 | I33: 0 | J33: 3763 | K33: 0 | L33: 0 | N33: =F33+G33+H33+I33+J33+K33+L33-O33 -> 3755 | O33: 8
A34: 28 | B34: Boditi | C34: Hossaena | D34: 31/07/2026 | E34: ATM cards 639 and PIN mailers 464 were not delivered to the respective account holders/ customers for a long period of time as presented below. | F34: 0 | G34: 639 | H34: 0 | I34: 0 | J34: 0 | K34: 0 | L34: 0 | N34: =F34+G34+H34+I34+J34+K34+L34-O34 -> 639
A35: 29 | B35: Boditi | C35: Hossaena | E35: ATM cards(639) & PIN mailers(464) were differ | F35: 175 | G35: 0 | H35: 0 | I35: 0 | J35: 0 | K35: 0 | L35: 0 | N35: =F35+G35+H35+I35+J35+K35+L35-O35 -> 175
A36: 30 | B36: Boditi | C36: Hossaena | D36: 31/07/2026 | E36: Fund transfer without customer signature | F36: 0 | G36: 0 | H36: 0 | I36: 0 | J36: 0 | K36: 0 | L36: 3 | M36: 143000 | N36: =F36+G36+H36+I36+J36+K36+L36-O36 -> 0 | O36: 3
A37: 31 | B37: Boditi | C37: Hossaena | D37: 31/07/2026 | E37: Cash withdrawal without customer signature | F37: 0 | G37: 0 | H37: 0 | I37: 0 | J37: 0 | K37: 0 | L37: 3 | M37: 120000 | N37: =F37+G37+H37+I37+J37+K37+L37-O37 -> 0 | O37: 3
A38: 32 | B38: Dalocha | C38: Hossaena | D38: 31/07/2026 | E38: Difference observed on ATM cash balance.(The physical cash count balance of ATM have shown a difference of Birr ……….. compared with the general ledger balance . ) | F38: 0 | G38: 0 | H38: 0 | I38: 0 | J38: 0 | K38: 0 | L38: 1 | M38: 13400 | N38: =F38+G38+H38+I38+J38+K38+L38-O38 -> 1
A39: 33 | B39: Dalocha | C39: Hossaena | D39: 31/07/26 | E39: Migration suspense accounts | F39: 0 | G39: 0 | H39: 1 | I39: 0 | J39: 0 | K39: 0 | L39: 0 | M39: 0.22 | N39: =F39+G39+H39+I39+J39+K39+L39-O39 -> 1
A40: 34 | B40: Dalocha | C40: Hossaena | D40: 45299 | E40: Catch all asset and liability | F40: 0 | G40: 0 | H40: 1 | I40: 0 | J40: 0 | K40: 0 | L40: 0 | M40: 0.75 | N40: =F40+G40+H40+I40+J40+K40+L40-O40 -> 1
A41: 35 | B41: Dalocha | C41: Hossaena | D41: 31/07/26 | E41: Dormant accounts Found at the branch | F41: 0 | G41: 0 | H41: 0 | I41: 0 | J41: 0 | K41: 0 | L41: 0 | M41: 1698 | N41: =F41+G41+H41+I41+J41+K41+L41-O41 -> 0
A42: 36 | B42: Dalocha | C42: Hossaena | D42: 31/07/2026 | E42: ATM cards 352 & PIN mailers 464 were not delivered to the respective account holders/ customers for a long period of time as presented below. | F42: 0 | G42: 464 | H42: 0 | I42: 0 | J42: 0 | K42: 0 | L42: 0 | N42: =F42+G42+H42+I42+J42+K42+L42-O42 -> 464
A43: 37 | B43: Dalocha | C43: Hossaena | E43: ATM cards(352) & PIN mailers(464) were differ | F43: 112 | G43: 0 | H43: 0 | I43: 0 | J43: 0 | K43: 0 | L43: 0 | N43: =F43+G43+H43+I43+J43+K43+L43-O43 -> 112
A44: 38 | B44: Damboya | C44: Hossaena | D44: 31/07/26 | E44: Migration suspense accounts | F44: 0 | G44: 0 | H44: 1 | I44: 0 | J44: 0 | K44: 0 | L44: 0 | M44: 59.65 | N44: =F44+G44+H44+I44+J44+K44+L44-O44 -> 1
A45: 39 | B45: Damboya | C45: Hossaena | D45: 31/07/26 | E45: Dormant accounts Found at the branch | F45: 0 | G45: 0 | H45: 0 | I45: 0 | J45: 391 | K45: 0 | L45: 0 | N45: =F45+G45+H45+I45+J45+K45+L45-O45 -> 375 | O45: 16
A46: 40 | B46: Damboya | C46: Hossaena | D46: 30/06/2026 | E46: ATM cards & PIN mailers were not delivered to the respective account holders/ customers for a long period of time as presented below. CARD(328) & PIN(474) | F46: 0 | G46: 474 | H46: 0 | I46: 0 | J46: 0 | K46: 0 | L46: 0 | N46: =F46+G46+H46+I46+J46+K46+L46-O46 -> 474
A47: 41 | B47: Damboya | C47: Hossaena | E47: ATM cards(328) & PIN mailers(474) were differ | F47: 146 | G47: 0 | H47: 0 | I47: 0 | J47: 0 | K47: 0 | L47: 0 | N47: =F47+G47+H47+I47+J47+K47+L47-O47 -> 146
A48: 42 | B48: Doyo Gena | C48: Hossaena | D48: 31/07/2026 | E48: Difference observed on ATM cash balance.(The physical cash count balance of ATM have shown a difference of Birr ‬ compared with the general ledger balance . ) | F48: 0 | G48: 0 | H48: 0 | I48: 0 | J48: 0 | K48: 0 | L48: 1 | M48: 19343.73 | N48: =F48+G48+H48+I48+J48+K48+L48-O48 -> 1
A49: 43 | B49: Doyo Gena | C49: Hossaena | D49: 31/03/2026 | E49: Cheque book stock balance difference with its GL balance | F49: 0 | G49: 0 | H49: 0 | I49: 0 | J49: 0 | K49: 0 | L49: 1 | M49: 4.18 | N49: =F49+G49+H49+I49+J49+K49+L49-O49 -> 0 | O49: 1
A50: 44 | B50: Doyo Gena | C50: Hossaena | D50: 31/07/2026 | E50: Catch all asset and liability | F50: 0 | G50: 0 | H50: 1 | I50: 0 | J50: 0 | K50: 0 | L50: 0 | M50: 94.1 | N50: =F50+G50+H50+I50+J50+K50+L50-O50 -> 1
A51: 45 | B51: Doyo Gena | C51: Hossaena | E51: long outstanding of Claims on Branchs & HO-ETB | F51: 0 | G51: 0 | H51: 0 | I51: 0 | J51: 0 | K51: 0 | L51: 1 | M51: 70734.68 | N51: =F51+G51+H51+I51+J51+K51+L51-O51 -> 1
A52: 46 | B52: Doyo Gena | C52: Hossaena | E52: on the Miscellaneous -LCY seen without source of document | F52: 0 | G52: 0 | H52: 0 | I52: 0 | J52: 0 | K52: 0 | L52: 1 | M52: 3180 | N52: =F52+G52+H52+I52+J52+K52+L52-O52 -> 1
A53: 47 | B53: Doyo Gena | C53: Hossaena | E53: Zero (0.00) balance Account Found at branch | F53: 0 | G53: 0 | H53: 0 | I53: 85 | J53: 0 | K53: 0 | L53: 0 | N53: =F53+G53+H53+I53+J53+K53+L53-O53 -> 0 | O53: 85
A54: 48 | B54: Doyo Gena | C54: Hossaena | E54: Dormant accounts Found at the branch | F54: 0 | G54: 0 | H54: 0 | I54: 0 | J54: 222 | K54: 0 | L54: 0 | N54: =F54+G54+H54+I54+J54+K54+L54-O54 -> 216 | O54: 6
A55: 49 | B55: Doyo Gena | C55: Hossaena | E55: ATM cards = 3,050 & PIN mailers 3,176‬ were not delivered to the respective account holders/ customers for a long period of time . | F55: 0 | G55: 3176 | H55: 0 | I55: 0 | J55: 0 | K55: 0 | L55: 0 | N55: =F55+G55+H55+I55+J55+K55+L55-O55 -> 3176
A56: 50 | B56: Doyo Gena | C56: Hossaena | E56: ATM cards(328) & PIN mailers(474) were differ | F56: 126 | G56: 0 | H56: 0 | I56: 0 | J56: 0 | K56: 0 | L56: 0 | N56: =F56+G56+H56+I56+J56+K56+L56-O56 -> 126
A57: 51 | B57: Doyo Gena | C57: Hossaena | E57: Cash withdrawal without customer signature | F57: 0 | G57: 0 | H57: 0 | I57: 0 | J57: 0 | K57: 0 | L57: 1 | M57: 10000 | N57: =F57+G57+H57+I57+J57+K57+L57-O57 -> 0 | O57: 1
A58: 52 | B58: Fonqo | C58: Hossaena | D58: 31/07/26 | E58: Difference observed on ATM cash balance.(The physical cash count balance of ATM have shown a difference of Birr compared with the general ledger balance . ) | F58: 0 | G58: 0 | H58: 0 | I58: 0 | J58: 0 | K58: 0 | L58: 1 | M58: 26489.24 | N58: =F58+G58+H58+I58+J58+K58+L58-O58 -> 1
A59: 53 | B59: Fonqo | C59: Hossaena | D59: 31/07/2026 | E59: Migration suspense accounts | F59: 0 | G59: 0 | H59: 1 | I59: 0 | J59: 0 | K59: 0 | L59: 0 | M59: 0.53 | N59: =F59+G59+H59+I59+J59+K59+L59-O59 -> 1
A60: 54 | B60: Fonqo | C60: Hossaena | D60: 31/07/2026 | E60: Catch all -Unassigned PL | F60: 0 | G60: 0 | H60: 1 | I60: 0 | J60: 0 | K60: 0 | L60: 0 | M60: 11 | N60: =F60+G60+H60+I60+J60+K60+L60-O60 -> 1
A61: 55 | B61: Fonqo | C61: Hossaena | D61: 31/07/2026 | E61: Dormant accounts Found at the branch /Inactive Accounts | F61: 0 | G61: 0 | H61: 0 | I61: 0 | J61: 7892 | K61: 0 | L61: 0 | N61: =F61+G61+H61+I61+J61+K61+L61-O61 -> 7892
A62: 56 | B62: Fonqo | C62: Hossaena | D62: 31/07/2026 | E62: ATM cards & PIN mailers were not delivered to the respective account holders/ customers for a long period of time as presented below. | F62: 0 | G62: 1138 | H62: 0 | I62: 0 | J62: 0 | K62: 0 | L62: 0 | N62: =F62+G62+H62+I62+J62+K62+L62-O62 -> 1138
A63: 57 | B63: Gimbichu | C63: Hossaena | D63: 31/07/2026 | E63: Dormant accounts/ Inactive accounts | F63: 0 | G63: 0 | H63: 0 | I63: 0 | J63: 1500 | K63: 0 | L63: 0 | N63: =F63+G63+H63+I63+J63+K63+L63-O63 -> 1500
A64: 58 | B64: Gimbichu | C64: Hossaena | D64: 22 up to 26 | E64: ATM cards 787 and PIN mailers 878 were not delivered to the respective account holders/ customers for a long period of time as presented below. | F64: 0 | G64: 878 | H64: 0 | I64: 0 | J64: 0 | K64: 0 | L64: 0 | N64: =F64+G64+H64+I64+J64+K64+L64-O64 -> 878
A65: 59 | B65: Gimbichu | C65: Hossaena | E65: ATM cards(787) & PIN mailers(878) were differ | F65: 91 | G65: 0 | H65: 0 | I65: 0 | J65: 0 | K65: 0 | L65: 0 | N65: =F65+G65+H65+I65+J65+K65+L65-O65 -> 91
A66: 60 | B66: H/Meneharia | C66: Hossaena | D66: 31/07/2026 | E66: Migration suspense accounts | F66: 0 | G66: 0 | H66: 1 | I66: 0 | J66: 0 | K66: 0 | L66: 0 | M66: 22616.41 | N66: =F66+G66+H66+I66+J66+K66+L66-O66 -> 1
A67: 61 | B67: H/Meneharia | C67: Hossaena | D67: 31/07/2026 | E67: Catch all asset and liability | F67: 0 | G67: 0 | H67: 1 | I67: 0 | J67: 0 | K67: 0 | L67: 0 | M67: 53.28 | N67: =F67+G67+H67+I67+J67+K67+L67-O67 -> 1
A68: 62 | B68: H/Meneharia | C68: Hossaena | D68: 31/07/2026 | E68: Dormant accounts Found at the branch | F68: 0 | G68: 0 | H68: 0 | I68: 0 | J68: 14700 | K68: 0 | L68: 0 | M68: 0 | N68: =F68+G68+H68+I68+J68+K68+L68-O68 -> 14700
A69: 63 | B69: H/Meneharia | C69: Hossaena | E69: ATM cards & PIN mailers were not delivered to the respective account holders/ customers for a long period of time as presented below. | F69: 0 | G69: 3839 | H69: 0 | I69: 0 | J69: 0 | K69: 0 | L69: 0 | N69: =F69+G69+H69+I69+J69+K69+L69-O69 -> 3839
A70: 64 | B70: H/Meneharia | C70: Hossaena | E70: ATM cards(3839) with respective PIN mailers(3824) on hand | F70: 15 | G70: 0 | H70: 0 | I70: 0 | J70: 0 | K70: 0 | L70: 0 | N70: =F70+G70+H70+I70+J70+K70+L70-O70 -> 15
A71: 65 | B71: H/Meneharia | C71: Hossaena | D71: 01/06/26-30/26 | E71: FT &Withdrawal pass wihtout customer signature | F71: 0 | G71: 0 | H71: 0 | I71: 0 | J71: 0 | K71: 0 | L71: 3 | M71: 2857000 | N71: =F71+G71+H71+I71+J71+K71+L71-O71 -> 1 | O71: 2
A72: 66 | B72: H/Arada | C72: Hossaena | D72: 31/08/25 | E72: Difference observed cash position on system balance 5,665,679.51 and GL balance made 5,665,566.51 and have shown a difference of Birr 113 br compared with the general ledger balance | F72: 0 | G72: 0 | H72: 0 | I72: 0 | J72: 0 | K72: 0 | L72: 1 | M72: 113 | N72: =F72+G72+H72+I72+J72+K72+L72-O72 -> 1
A73: 67 | B73: H/Arada | C73: Hossaena | D73: 31/08/26 | E73: Migration suspense accounts | F73: 0 | G73: 0 | H73: 1 | I73: 0 | J73: 0 | K73: 0 | L73: 0 | M73: 0.14 | N73: =F73+G73+H73+I73+J73+K73+L73-O73 -> 1
A74: 68 | B74: H/Arada | C74: Hossaena | D74: 31/7/2026 | E74: Dormant accounts Found at the branch /Inactive Accounts | F74: 0 | G74: 0 | H74: 0 | I74: 0 | J74: 7692 | K74: 0 | L74: 0 | N74: =F74+G74+H74+I74+J74+K74+L74-O74 -> 7687 | O74: 5
A75: 69 | B75: H/Arada | C75: Hossaena | E75: ATM cards & PIN mailers were not delivered to the respective account holders for a long period of time as presented below. | F75: 0 | G75: 3020 | H75: 0 | I75: 0 | J75: 0 | K75: 0 | L75: 0 | N75: =F75+G75+H75+I75+J75+K75+L75-O75 -> 3018 | O75: 2
A76: 70 | B76: H/Arada | C76: Hossaena | E76: ATM cards(3020) and PIN mailers(2463) were differe | F76: 557 | G76: 0 | H76: 0 | I76: 0 | J76: 0 | K76: 0 | L76: 0 | N76: =F76+G76+H76+I76+J76+K76+L76-O76 -> 557
A77: 71 | B77: H/Gebeya | C77: Hossaena | D77: 31/07/2026 | E77: Difference observed on ATM cash balance.(The physical cash count balance of ATM have shown a difference of Birr 24,479.79 compared with the general ledger balance . ) | F77: 0 | G77: 0 | H77: 0 | I77: 0 | J77: 0 | K77: 0 | L77: 1 | M77: 24479.79 | N77: =F77+G77+H77+I77+J77+K77+L77-O77 -> 0 | O77: 1
A78: 72 | B78: H/Gebeya | C78: Hossaena | D78: 31/07/2026 | E78: Long out standing on ATM card=4,114 | F78: 0 | G78: 4114 | H78: 0 | I78: 0 | J78: 0 | K78: 0 | L78: 0 | N78: =F78+G78+H78+I78+J78+K78+L78-O78 -> 4114
A79: 73 | B79: H/Gebeya | C79: Hossaena | D79: 31/07/2026 | E79: System suspense account DC | F79: 0 | G79: 0 | H79: 1 | I79: 0 | J79: 0 | K79: 0 | L79: 0 | M79: -199.56 | N79: =F79+G79+H79+I79+J79+K79+L79-O79 -> 1
A80: 74 | B80: H/Gebeya | C80: Hossaena | D80: 31/07/2026 | E80: Migration suspense accounts | F80: 0 | G80: 0 | H80: 1 | I80: 0 | J80: 0 | K80: 0 | L80: 0 | M80: -194.55 | N80: =F80+G80+H80+I80+J80+K80+L80-O80 -> 1
A81: 75 | B81: H/Gebeya | C81: Hossaena | D81: 31/07/2026 | E81: loan balance correction expense | F81: 0 | G81: 0 | H81: 1 | I81: 0 | J81: 0 | K81: 0 | L81: 0 | M81: -8718.1 | N81: =F81+G81+H81+I81+J81+K81+L81-O81 -> 1
A82: 76 | B82: H/Gebeya | C82: Hossaena | D82: 14/07/2026 | E82: Catch all Unassined PL | F82: 0 | G82: 0 | H82: 1 | I82: 0 | J82: 0 | K82: 0 | L82: 0 | M82: 43.75 | N82: =F82+G82+H82+I82+J82+K82+L82-O82 -> 1
A83: 77 | B83: H/Gebeya | C83: Hossaena | D83: 31/07/2026 | E83: Long outstanding on DEPOSIT ACC IN PROCESS OPENING | F83: 0 | G83: 0 | H83: 0 | I83: 0 | J83: 0 | K83: 0 | L83: 1 | M83: 3925 | N83: =F83+G83+H83+I83+J83+K83+L83-O83 -> 0 | O83: 1
A84: 78 | B84: H/Gebeya | C84: Hossaena | D84: 31/07/26 | E84: Dormant accounts Found at the branch | F84: 0 | G84: 0 | H84: 0 | I84: 0 | J84: 8791 | K84: 0 | L84: 0 | N84: =F84+G84+H84+I84+J84+K84+L84-O84 -> 8791
A85: 79 | B85: H/Gebeya | C85: Hossaena | D85: 31/07/2026 | E85: ATM cards & PIN mailers were not delivered to the respective account holders/ customers for a long period of time as presented below.ATM card =3,687 PIN mailers = 3,192 | F85: 0 | G85: 3687 | H85: 0 | I85: 0 | J85: 0 | K85: 0 | L85: 0 | N85: =F85+G85+H85+I85+J85+K85+L85-O85 -> 3687
A86: 80 | B86: H/Gebeya | C86: Hossaena | D86: 31/07/2026 | E86: Mismatch ATM card and pin mailer=495 | F86: 495 | G86: 0 | H86: 0 | I86: 0 | J86: 0 | K86: 0 | L86: 0 | N86: =F86+G86+H86+I86+J86+K86+L86-O86 -> 495
A87: 81 | B87: H/Gebeya | C87: Hossaena | D87: 30/04/2026 | E87: Cash withdrawal without customer signature | F87: 0 | G87: 0 | H87: 0 | I87: 0 | J87: 0 | K87: 0 | L87: 4 | M87: 125000 | N87: =F87+G87+H87+I87+J87+K87+L87-O87 -> 0 | O87: 4
A88: 82 | B88: H/Gebeya | C88: Hossaena | E88: Fund transfer without customer signature | F88: 0 | G88: 0 | H88: 0 | I88: 0 | J88: 0 | K88: 0 | L88: 15 | M88: 1235000 | N88: =F88+G88+H88+I88+J88+K88+L88-O88 -> 0 | O88: 15
A89: 83 | B89: H/Gombora | C89: Hossaena | D89: 31/07/2026 | E89: Difference observed on ATM cash balance.(The physical cash count balance of ATM have shown a difference of Birr 295,521.25compared with the general ledger balance . ) | F89: 0 | G89: 0 | H89: 0 | I89: 0 | J89: 0 | K89: 0 | L89: 1 | M89: 257421.25 | N89: =F89+G89+H89+I89+J89+K89+L89-O89 -> 1
A90: 84 | B90: H/Gombora | C90: Hossaena | D90: 31/07/2026 | E90: Migration suspense accounts | F90: 0 | G90: 0 | H90: 1 | I90: 0 | J90: 0 | K90: 0 | L90: 0 | M90: 68.81 | N90: =F90+G90+H90+I90+J90+K90+L90-O90 -> 1
A91: 85 | B91: H/Gombora | C91: Hossaena | D91: 13/05/25 | E91: Perdiem&Travel expence | F91: 0 | G91: 0 | H91: 0 | I91: 0 | J91: 0 | K91: 0 | L91: 1 | M91: 6180 | N91: =F91+G91+H91+I91+J91+K91+L91-O91 -> 0 | O91: 1
A92: 86 | B92: H/Gombora | C92: Hossaena | D92: 31/07/2026 | E92: Dormant accounts Found at the branch | F92: 0 | G92: 0 | H92: 0 | I92: 0 | J92: 8873 | K92: 0 | L92: 0 | N92: =F92+G92+H92+I92+J92+K92+L92-O92 -> 8863 | O92: 10
A93: 87 | B93: H/Gombora | C93: Hossaena | D93: 31/07/2026 | E93: ATM(893)cards &( 966)PIN mailers were not delivered to the respective account holders | F93: 0 | G93: 966 | H93: 0 | I93: 0 | J93: 0 | K93: 0 | L93: 0 | N93: =F93+G93+H93+I93+J93+K93+L93-O93 -> 966
A94: 88 | B94: H/Gombora | C94: Hossaena | E94: ATM cards(966) with respective PIN mailers(893) on hand | F94: 73 | G94: 0 | H94: 0 | I94: 0 | J94: 0 | K94: 0 | L94: 0 | N94: =F94+G94+H94+I94+J94+K94+L94-O94 -> 73
A95: 89 | B95: H/Gombora | C95: Hossaena | D95: 01/07/2026-31 | E95: Cash withdrawal witho out custemer signature | F95: 0 | G95: 0 | H95: 0 | I95: 0 | J95: 0 | K95: 0 | L95: 3 | M95: 87000 | N95: =F95+G95+H95+I95+J95+K95+L95-O95 -> 0 | O95: 3
A96: 90 | B96: H/Gombora | C96: Hossaena | D96: 01/07/2026-31 | E96: FT withoout custemer signature | F96: 0 | G96: 0 | H96: 0 | I96: 0 | J96: 0 | K96: 0 | L96: 16 | M96: 6367000 | N96: =F96+G96+H96+I96+J96+K96+L96-O96 -> 0 | O96: 16
A97: 91 | B97: Hadero | C97: Hossaena | D97: 30/06/26 | E97: Difference observed on ATM cash balance as of june 30-2026.(The physical cash count balance of ATM has shown a difference of shortage Birr 3000 compared with the general ledger balance .(i.e GL balance was birr 109,000 but physical cash count was birr 106,000) | F97: 0 | G97: 0 | H97: 0 | I97: 0 | J97: 0 | K97: 0 | L97: 1 | M97: 3000 | N97: =F97+G97+H97+I97+J97+K97+L97-O97 -> 0 | O97: 1
A98: 92 | B98: Hadero | C98: Hossaena | D98: 46119 | E98: Cash excess found on BBO Teshome Bedore 4000 birr at closing | F98: 0 | G98: 0 | H98: 0 | I98: 0 | J98: 0 | K98: 0 | L98: 1 | M98: 4000 | N98: =F98+G98+H98+I98+J98+K98+L98-O98 -> 0 | O98: 1
A99: 93 | B99: Hadero | C99: Hossaena | D99: 44692 | E99: Amount paid to cover accrued interest of Ersido Erkalo(FT2230925RSF) | F99: 0 | G99: 0 | H99: 0 | I99: 0 | J99: 0 | K99: 0 | L99: 1 | M99: 61776.96 | N99: =F99+G99+H99+I99+J99+K99+L99-O99 -> 1
A100: 94 | B100: Hadero | C100: Hossaena | D100: 2023 up to 2024 | E100: Longoutstanding Account Receivable Miscellaneous-ETB12548 which would be collected from different loan customers for legal case(i.e perdiem and Transportation paid for legal officer | F100: 0 | G100: 0 | H100: 0 | I100: 0 | J100: 0 | K100: 0 | L100: 1 | M100: 35112.03 | N100: =F100+G100+H100+I100+J100+K100+L100-O100 -> 1
...

Sheet Wolkite
A1: Nib international bank s.c
A2: Wolkite District
A3: Detailed Monthly internal Control Reports
A4: As of -July 31,2026
A5: SN | D5: Operation area | E5: ATM | G5: It | H5: Zero Balance | I5: Inactive/Dormant | J5: Ck book stock | K5: Other Cases | L5: Posting date | M5: Types of Irregularities/problems | N5: Amount involved in Birr | O5: Status of the irregularities
B6: Branches | E6: Mismatch | F6: Long outstanding | N6: Amount involved | O6: Unrectified | P6: Rectified | Q6: Unrectified In Amount
A7: 1 | B7: Agena | C7: Wolkite | D7: cash & cash item | K7: 1 | M7: Difference observed on ATM cash balance.(The physical cash count balance of ATM have shown a difference of Birr ……….. compared with the general ledger balance . ) | N7: 32292.5 | O7: =E7+F7+G7+H7+I7+J7+K7-P7 -> 1
A8: 2 | B8: Agena | C8: Wolkite | D8: Account Management | G8: 1 | M8: Migration suspense accounts | N8: 0.55 | O8: =E8+F8+G8+H8+I8+J8+K8-P8 -> 1
A9: 3 | B9: Agena | C9: Wolkite | G9: 1 | M9: Catch All unassigned PL | N9: 4 | O9: =E9+F9+G9+H9+I9+J9+K9-P9 -> 1
A10: 4 | I10: 229 | M10: Dormant account found in brfanch | O10: =E10+F10+G10+H10+I10+J10+K10-P10 -> 229
A11: 5 | B11: Agena | C11: Wolkite | D11: Card Banking | F11: 211 | M11: ATM cards & PIN mailers were not delivered to the respective account holders/ customers for a long period of time as presented below.211 car and 219 pin mailers | O11: =E11+F11+G11+H11+I11+J11+K11-P11 -> 211 | R11: non.
A12: 6 | B12: Areket | D12: cash & cash item | K12: 1 | M12: Difference observed on ATM cash balance.(The physical cash count balance of ATM have shown a difference of Birr ……….. compared with the general ledger balance . ) | N12: 24197.94 | O12: =E12+F12+G12+H12+I12+J12+K12-P12 -> 1
A13: 7 | B13: Areket | C13: Wolkite | D13: Account Management | G13: 1 | M13: Catch All unassigned PL | N13: 21.25 | O13: =E13+F13+G13+H13+I13+J13+K13-P13 -> 1
A14: 8 | B14: Areket | C14: Wolkite | K14: 4 | M14: CLAIMS ON HEAD OFFICE/BRANCHES PERDAIM AND FUEL EXPENCE ESTMATION FEE AND COFFE CERMONY FOR COUSTOMER DAY | N14: 8553 | O14: =E14+F14+G14+H14+I14+J14+K14-P14 -> 4
A15: 9 | B15: Areket | C15: Wolkite | K15: 1 | M15: E-birr Float Recievable | N15: 5420 | O15: =E15+F15+G15+H15+I15+J15+K15-P15 -> 1
A16: 10 | B16: Areket | C16: Wolkite | H16: 28 | M16: Zero balance | O16: =E16+F16+G16+H16+I16+J16+K16-P16 -> 28
A17: 11 | B17: Areket | C17: Wolkite | I17: 125 | M17: Dormant accounts Found at the branch | O17: =E17+F17+G17+H17+I17+J17+K17-P17 -> 93 | P17: 32
A18: 12 | B18: Areket | C18: Wolkite | D18: Card Banking | F18: 288 | M18: ATM cards & PIN mailers were not delivered to the respective account holders/ customers for a long period of time as presented below.(288 CARD & PIN) | O18: =E18+F18+G18+H18+I18+J18+K18-P18 -> 288
A19: 13 | B19: Buie | C19: Wolkite | D19: Account Management | G19: 1 | M19: Absence of source document ;-Inter branch T-24 R10 | N19: -20341502 | O19: =E19+F19+G19+H19+I19+J19+K19-P19 -> 1
A20: 14 | B20: Buie | G20: 1 | M20: Catch ALL-Unassigned -PL | N20: 11586.25 | O20: =E20+F20+G20+H20+I20+J20+K20-P20 -> 1
A21: 15 | B21: Buie | C21: Wolkite | I21: 468 | M21: Dormant accounts Found at the branch | N21: 135145.34 | O21: =E21+F21+G21+H21+I21+J21+K21-P21 -> 468
A22: 16 | B22: Buie | C22: Wolkite | D22: Card Banking | F22: 576 | M22: ATM cards & PIN mailers were not delivered to the respective account holders/ customers for a long period of time as presented below.(576CARD & 506 PIN) | O22: =E22+F22+G22+H22+I22+J22+K22-P22 -> 576
A23: 17 | B23: Butajira | C23: Wolkite | D23: cash & cash item | K23: 1 | M23: Difference observed on ATM cash balance.(The physical cash count balance of ATM have shown a difference of Birr--compared with the general ledger balance .) | N23: 95142.36 | O23: =E23+F23+G23+H23+I23+J23+K23-P23 -> 1
A24: 18 | B24: Butajira | C24: Wolkite | D24: Account Management | K24: 1 | M24: Cheque books stock difference against GL Balance | N24: 3004.29 | O24: =E24+F24+G24+H24+I24+J24+K24-P24 -> 1
A25: 19 | B25: Butajira | C25: Wolkite | G25: 1 | M25: System suspense account AA | N25: -99550.2 | O25: =E25+F25+G25+H25+I25+J25+K25-P25 -> 1
A26: 20 | B26: Butajira | C26: Wolkite | G26: 1 | M26: Migration suspense accounts | N26: 7525.78 | O26: =E26+F26+G26+H26+I26+J26+K26-P26 -> 1
A27: 21 | B27: Butajira | C27: Wolkite | G27: 1 | M27: Catch ALL-Unassigned -PL | N27: 34.75 | O27: =E27+F27+G27+H27+I27+J27+K27-P27 -> 1
A28: 22 | B28: Butajira | C28: Wolkite | G28: 1 | M28: Catch all asset and liability | N28: -8809.69 | O28: =E28+F28+G28+H28+I28+J28+K28-P28 -> 1
A29: 23 | B29: Butajira | C29: Wolkite | K29: 1 | M29: Sundry debtors (ex-staff mitike regards legal cost) | N29: 25416 | O29: =E29+F29+G29+H29+I29+J29+K29-P29 -> 1
A30: 24 | B30: Butajira | C30: Wolkite | K30: 1 | M30: Sundry Creditors ,Misellanous | N30: 102111.72 | O30: =E30+F30+G30+H30+I30+J30+K30-P30 -> 1
A31: 25 | B31: Butajira | C31: Wolkite | H31: 15 | M31: Zero(0.00) balance Account Found at branch | O31: =E31+F31+G31+H31+I31+J31+K31-P31 -> 15
A32: 26 | B32: Butajira | C32: Wolkite | I32: 9077 | M32: Dormant accounts Found at the branch | N32: 135145.34 | O32: =E32+F32+G32+H32+I32+J32+K32-P32 -> 9077
A33: 27 | B33: Butajira | C33: Wolkite | D33: Card Banking | F33: 1059 | M33: ATM cards & PIN mailers were not delivered to the respective account holders/ customers for a long period of time as presented below.(1059 CARD & 598 PIN) | O33: =E33+F33+G33+H33+I33+J33+K33-P33 -> 1059
A34: 28 | B34: Dargee | C34: Wolkite | D34: cash & cash item | K34: 1 | M34: Difference observed on ATM cash balance.(The physical cash count balance of ATM have shown a difference of Birr compared with the general ledger balance . ) | N34: 1000 | O34: =E34+F34+G34+H34+I34+J34+K34-P34 -> 1
A35: 29 | B35: Dargee | C35: Wolkite | D35: Account Management | K35: 1 | M35: Abnormal balance of ATM Balance | N35: 14.62 | O35: =E35+F35+G35+H35+I35+J35+K35-P35 -> 1
A36: 30 | B36: Dargee | C36: Wolkite | G36: 1 | M36: Migration suspense a/c | N36: 0.71 | O36: =E36+F36+G36+H36+I36+J36+K36-P36 -> 1
A37: 31 | B37: Dargee | C37: Wolkite | K37: 1 | L37: 25/09/2021 | M37: MTS/TTS Payable local LMTS | N37: 1600 | O37: =E37+F37+G37+H37+I37+J37+K37-P37 -> 1
A38: 32 | B38: Dargee | C38: Wolkite | I38: 138 | M38: Dormant accounts Found at the branch | N38: 19321 | O38: =E38+F38+G38+H38+I38+J38+K38-P38 -> 138
A39: 33 | B39: Dargee | C39: Wolkite | D39: Card Banking | F39: 343 | M39: ATM cards & PIN mailers were not delivered to the respective account holders/ customers for a long period of time as presented below.(343CARD) | O39: =E39+F39+G39+H39+I39+J39+K39-P39 -> 343
A40: 34 | B40: Ensino | C40: Wolkite | D40: cash & cash item | K40: 1 | M40: Difference observed on ATM cash balance.(The physical cash count balance of ATM have shown a difference of Birr ________compared with the general ledger balance . ) | N40: 5127.29 | O40: =E40+F40+G40+H40+I40+J40+K40-P40 -> 1
A41: 35 | B41: Ensino | C41: Wolkite | D41: Account Management | H41: 25 | M41: Zero(0.00) balance Account Found at branch | O41: =E41+F41+G41+H41+I41+J41+K41-P41 -> 25
A42: 36 | B42: Ensino | C42: Wolkite | I42: 4658 | M42: Dormant accounts Found at the branch | O42: =E42+F42+G42+H42+I42+J42+K42-P42 -> 4655 | P42: 3
A43: 37 | B43: Ensino | C43: Wolkite | D43: Card Banking | F43: 998 | M43: ATM cards 998 & PIN mailers 790 were not delivered to the respective account holders/ customers for a long period of time as presented below. 998ATM&790 PIN | O43: =E43+F43+G43+H43+I43+J43+K43-P43 -> 998
A44: 38 | B44: Ensino | C44: Wolkite | D44: Tcket vouching | K44: 1 | M44: Withdrowal Payment and transfer is made with out customer signature cash withdrawal with out signature: | O44: =E44+F44+G44+H44+I44+J44+K44-P44 -> 0 | P44: 1
A45: 39 | B45: Ensino | C45: Wolkite | M45: Jafer Shemsu Withdrowal-7000010950878 | N45: 50000 | O45: =E45+F45+G45+H45+I45+J45+K45-P45 -> -1 | P45: 1
A46: 40 | B46: Ensino | C46: Wolkite | K46: 1 | M46: Muhdin Sirwana FT 7000013897226 | N46: 50000 | O46: =E46+F46+G46+H46+I46+J46+K46-P46 -> 1
A47: 41 | B47: Ensino | C47: Wolkite | K47: 1 | M47: Shemsu Sebre Withdrowal 7000010950878 | N47: 20000 | O47: =E47+F47+G47+H47+I47+J47+K47-P47 -> 0 | P47: 1
A48: 42 | B48: Ensino | C48: Wolkite | K48: 1 | M48: Afrano Muste Withdrowal 7000031078348 | N48: 50000 | O48: =E48+F48+G48+H48+I48+J48+K48-P48 -> 0 | P48: 1
A49: 43 | B49: Ensino | C49: Wolkite | K49: 1 | M49: Abdi Darunga Withdrowal 7000024670657 | N49: 50000 | O49: =E49+F49+G49+H49+I49+J49+K49-P49 -> 0 | P49: 1
A50: 44 | B50: Emdebir | C50: Wolkite | D50: OTHERS | K50: 1 | M50: Improper handling of cash book | O50: =E50+F50+G50+H50+I50+J50+K50-P50 -> 1
A51: 45 | B51: Emdebir | C51: Wolkite | D51: cash & cash item | K51: 1 | M51: Difference observed on ATM cash balance.(The physical cash count balance of ATM have shown a difference of Birr ……….. compared with the general ledger balance . ) | N51: 52435 | O51: =E51+F51+G51+H51+I51+J51+K51-P51 -> 1
A52: 46 | B52: Emdebir | C52: Wolkite | D52: Account Management | G52: 1 | M52: Absence of source documents. Catch all un assigned PL | N52: 5485.76 | O52: =E52+F52+G52+H52+I52+J52+K52-P52 -> 1
A53: 47 | C53: Wolkite | M53: S/CREDITORS | O53: =E53+F53+G53+H53+I53+J53+K53-P53 -> 0
A54: 48 | B54: Emdebir | C54: Wolkite | K54: 1 | M54: LMT's Payable | N54: 64665.2 | O54: =E54+F54+G54+H54+I54+J54+K54-P54 -> 1
A55: 49 | B55: Emdebir | C55: Wolkite | K55: 1 | M55: Long Outstanding items cpo. | N55: 13442.5 | O55: =E55+F55+G55+H55+I55+J55+K55-P55 -> 1
A56: 50 | B56: Emdebir | C56: Wolkite | I56: 7757 | M56: Dormant Accountfound at the branch | O56: =E56+F56+G56+H56+I56+J56+K56-P56 -> 7757
A57: 51 | B57: Emdebir | C57: Wolkite | D57: Card Banking | F57: 794 | M57: ATM cards & PIN mailers were not delivered to the respective account holders/ customers for a long period of time as presented below.(794 ATM CARD & 448 PIN) | O57: =E57+F57+G57+H57+I57+J57+K57-P57 -> 794
A58: 52 | B58: Emdebir | C58: Wolkite | D58: OTHERS | K58: 1 | M58: Dis-functional metal detector. | O58: =E58+F58+G58+H58+I58+J58+K58-P58 -> 1
A59: 53 | B59: Endagegne | C59: Wolkite | D59: Account Management | M59: Absence of Source Doucument:- | O59: =E59+F59+G59+H59+I59+J59+K59-P59 -> 0
A60: 54 | B60: Endagegne | C60: Wolkite | G60: 1 | M60: Migration suspense accounts | N60: 1.23 | O60: =E60+F60+G60+H60+I60+J60+K60-P60 -> 1
A61: 55 | B61: Endagegne | C61: Wolkite | I61: 1861 | M61: Dormant account found | N61: 1085752 | O61: =E61+F61+G61+H61+I61+J61+K61-P61 -> 1857 | P61: 4
A62: 56 | B62: Endagegne | C62: Wolkite | D62: Card Banking | F62: 331 | M62: ATM cards & PIN mailers were not delivered to the respective account holders/ customers for a long period of time as presented below.( 331 ATM CARD | O62: =E62+F62+G62+H62+I62+J62+K62-P62 -> 331
A63: 57 | B63: Endagegne | C63: Wolkite | E63: 4 | M63: Mismatch between ATM cards(340) & PIN mailers(339) | O63: =E63+F63+G63+H63+I63+J63+K63-P63 -> 4
A64: 58 | B64: Gunchire | K64: 1 | M64: Difference observed on ATM cash balance.(The physical cash count balance of ATM have shown a difference of Birr ……….. compared with the general ledger balance . ) | N64: 29081.58 | O64: =E64+F64+G64+H64+I64+J64+K64-P64 -> 1
A65: 59 | B65: Gunchire | C65: Wolkite | D65: Account Management | G65: 1 | M65: Migration suspense accounts | N65: 122826.39 | O65: =E65+F65+G65+H65+I65+J65+K65-P65 -> 1
A66: 60 | B66: Gunchire | C66: Wolkite | G66: 1 | M66: Catch ALL-Unassigned -PL | N66: 27.28 | O66: =E66+F66+G66+H66+I66+J66+K66-P66 -> 1
A67: 61 | B67: Gunchire | C67: Wolkite | K67: 1 | M67: Sundry Creditors :(MULTI SUPPLIER PAYABLE ACC CASE OF MIGRATION | N67: 122902.55 | O67: =E67+F67+G67+H67+I67+J67+K67-P67 -> 1
A68: 62 | B68: Gunchire | C68: Wolkite | I68: 589 | M68: Dormant Accountfound at the branch | O68: =E68+F68+G68+H68+I68+J68+K68-P68 -> 589
